Workbook

Sheet Graphs
Q1: Count | R1: Company Name | S1: Request Log | T1: Request Date | U1: Request Link | V1: Referral Received | W1: Comment | X1: Message Ready | Y1: Resume Ready
M19: Important Links for Applications
M20: 1. Networking Message | N20: Link
M21: 2. Resume | N21: Link
M22: 3. Cover Letter | N22: Link
M23: 4. Extra Documents | N23: Link
M24: 5. Screenshots | N24: Link
M25: 6. Cover Letter Template | N25: Link
M62: I hope you're doing well! I previously worked as an SDE2 at Bounteous and am pursuing my Master’s in Data Science from Stony Brook University. I came across the Software Developer 2026 ELH position with Job ID: 91689, and wanted to check if you’d be open to reviewing my resume or referring me. Thank you!
S87: #REF!

Sheet Saved Jobs
A1: Date Saved | B1: Role | C1: Company | D1: Location | E1: Job Link
A2: 45961.71 | B2: Computational Imaging Research Scientist Manage My Job Request a Coach | C2: GLASS Imaging | D2: San Francisco Bay Area · 10 minutes ago · 0 applicants Promoted by hirer · No response insights available yet | E2: https://www.linkedin.com/jobs/view/4320212741/
A3: 45961.724 | B3: Embedded Software Engineer Manage My Job Request a Coach | C3: Vastika Inc | D3: Carrollton, TX · 15 minutes ago · 5 applicants Promoted by hirer · No response insights available yet | E3: https://www.linkedin.com/jobs/view/4320312705/
A4: 45961.734 | B4: AI Engineer | C4: New Resources Consulting | D4: Milwaukee, WI · Reposted 51 minutes ago · Over 100 applicants Promoted by hirer · Actively reviewing applicants | E4: https://www.linkedin.com/jobs/view/4314022965/
A5: 45961.76 | B5: Quantitative Strategy Developer - New Grad Manage My Job Request a Coach | C5: Susquehanna International Group | D5: Greater Philadelphia · 38 minutes ago · 17 people clicked apply Promoted by hirer · Responses managed off LinkedIn | E5: https://www.linkedin.com/jobs/view/4320152787/
A6: 45961.831 | B6: Devops Engineer | C6: Wipro | D6: Minneapolis, NC · 3 hours ago · 25 people clicked apply Promoted by hirer · Responses managed off LinkedIn | E6: https://www.linkedin.com/jobs/view/4320212736/
A7: 45961.837 | B7: Software Engineer – Microsoft AI Manage My Job Request a Coach | C7: Microsoft | D7: Redmond, WA · 3 hours ago · 48 people clicked apply Promoted by hirer · Responses managed off LinkedIn | E7: https://www.linkedin.com/jobs/view/4333328595/
A8: 45961.87 | B8: Real-Time /Embedded Firmware Engineer | C8: Nuvoton Technology Corporation America | D8: Austin, TX · 49 minutes ago · 6 applicants Promoted by hirer · Company review time is typically 1 week | E8: https://www.linkedin.com/jobs/view/4333369385/
A9: 45961.872 | B9: Front End Engineer- React & Map API Manage My Job Request a Coach | C9: Ascendion | D9: Seattle, WA · Reposted 54 minutes ago · Over 100 applicants Promoted by hirer · Actively reviewing applicants | E9: https://www.linkedin.com/jobs/view/4315044235/
A10: 45962.411 | B10: Applications Analyst Manage My Job Request a Coach | C10: Zekelman Industries | D10: Wheatland, PA · Reposted 42 minutes ago · 27 people clicked apply Promoted by hirer · Responses managed off LinkedIn | E10: https://www.linkedin.com/jobs/view/4313443958/
A11: 45963.12 | B11: AI Engineer Manage My Job Request a Coach | C11: Avesta Computer Services | D11: Fremont, CA · 42 minutes ago · 3 applicants Promoted by hirer · No response insights available yet | E11: https://www.linkedin.com/jobs/view/4332188017/
A12: 45963.13 | B12: Senior Web Developer Manage My Job Request a Coach | C12: SCIENTIFIC GAMES | D12: Alpharetta, GA · Reposted 10 minutes ago · 99 people clicked apply Promoted by hirer · Responses managed off LinkedIn | E12: https://www.linkedin.com/jobs/view/4309207109/
A13: 45963.198 | B13: Software Development Engineer III | C13: Optimum | D13: Bethpage, NY · Reposted 1 hour ago · Over 100 people clicked apply Responses managed off LinkedIn | E13: https://www.linkedin.com/jobs/view/4177889291/
... A67: 45969.997 | B67: Software Engineer Manage My Job Request a Coach | C67: Benchmark | D67: New York, NY · 1 month ago · Over 100 applicants Promoted by hirer · Actively reviewing applicants | E67: https://www.linkedin.com/jobs/view/4310415694/
A68: 11/13/2025, 12:00:00 AM | B68: Software Engineer | C68: Miller Cooper | D68: Remote | E68: https://millercooper.atsondemand.com/#/jobDescription/904556
A69: =IFERROR(__xludf.DUMMYFUNCTION("IFERROR( FILTER( { ARRAYFORMULA(TEXT(TO_DATE(Jobright!B2:B975), ""MM/dd/yyyy, h:mm:ss AM/PM"")), Jobright!A2:A975, Jobright!F2:F975, Jobright!E2:E975, Jobright!C2:C975, Jobright!M2:M975 }, LOWER(TRIM(Jobri"&"ght!M2:M975))=""Done"" ), ""No rows marked done"" ) "),"No rows marked done") -> No rows marked done
A70: 45975.53 | B70: Data Scientist - New Grad (2026 Start) Manage My Job Request a Coach | C70: Databricks | D70: Mountain View, CA · Reposted 7 hours ago · Over 100 people clicked apply Promoted by hirer · Responses managed off LinkedIn | E70: https://www.linkedin.com/jobs/view/4297746037/
A71: 45975.537 | B71: Quality Engineer Manage My Job Request a Coach | C71: Oerlikon | D71: Westbury, NY · Reposted 7 hours ago · 46 people clicked apply Promoted by hirer · Responses managed off LinkedIn | E71: https://www.linkedin.com/jobs/view/4306806143/
A72: 45975.537 | B72: Software Engineer Manage My Job Request a Coach | C72: Akamai Technologies | D72: United States · 1 minute ago · 0 people clicked apply Promoted by hirer · Responses managed off LinkedIn | E72: https://www.linkedin.com/jobs/view/4336231580/
A73: 45975.884 | B73: Software Engineer Backend/Platform Systems I (Full Time) – United States Manage My Job Request a Coach | C73: Cisco | D73: Fulton, MD · 19 minutes ago · 6 people clicked apply Promoted by hirer · Responses managed off LinkedIn | E73: https://www.linkedin.com/jobs/view/4336294749/
A74: 45975.886 | B74: Machine Learning Engineer, Strategy & Supply Optimization | C74: DoorDash | D74: San Francisco, CA · 46 minutes ago · 0 people clicked apply Promoted by hirer · Responses managed off LinkedIn | E74: https://www.linkedin.com/jobs/view/4340833443/
A75: 45975.887 | B75: Software Engineer Manage My Job Request a Coach | C75: Lowe's Companies, Inc. | D75: Charlotte, NC · 47 minutes ago · 5 people clicked apply Responses managed off LinkedIn | E75: https://www.linkedin.com/jobs/view/4322675546/
A76: 45975.892 | B76: (USA) Senior, Data Engineer Manage My Job Request a Coach | C76: Walmart | D76: Sunnyvale, CA · 20 minutes ago · 4 people clicked apply Promoted by hirer · Responses managed off LinkedIn | E76: https://www.linkedin.com/jobs/view/4340554040/
A77: 45975.898 | B77: Data Engineer Manage My Job Request a Coach | C77: Aquent | D77: Austin, TX · Reposted 1 hour ago · 3 people clicked apply Promoted by hirer · Responses managed off LinkedIn | E77: https://www.linkedin.com/jobs/view/4336284362/
A78: 45976.979 | B78: Data Engineer Manage My Job Request a Coach | C78: Tupl Inc. | D78: Dallas, TX · 1 day ago · Over 100 people clicked apply Promoted by hirer · Responses managed off LinkedIn | E78: https://www.linkedin.com/jobs/view/4335949863/
A79: 45976.996 | B79: Backend Engineer Manage My Job Request a Coach | C79: Bevel | D79: New York, NY · 1 week ago · Over 100 people clicked apply Responses managed off LinkedIn | E79: https://www.linkedin.com/jobs/view/4334860779/
A80: 45977.86 | B80: Software Engineer (Networking) Manage My Job Request a Coach | C80: ORDR | D80: Santa Clara, CA · 9 hours ago · 86 applicants Promoted by hirer · No response insights available yet | E80: https://www.linkedin.com/jobs/view/4322941297/
A81: 45977.86 | B81: New Grad | C81: Optiver | D81: Chicago | E81: https://optiver.com/working-at-optiver/career-opportunities/7986419002/?gh_jid=7986419002&gh_src=hk2so9u22us
... A175: 46000.022 | B175: Structural Designer Quick Apply | C175: Kiewit | D175: Omaha, NE · 1 week ago · 42 applicants Promoted by hirer · No response insights available yet | E175: https://www.linkedin.com/jobs/view/4324872849/
A176: 46000 | E176: https://nvidia.wd5.myworkdayjobs.com/en-US/NVIDIAExternalCareerSite/userHome
A177: 46000 | E177: https://www.linkedin.com/in/shaun-blair-25621812/
A178: 46000.035 | B178: Software Developer (GPS/GNSS):: 25-07166 Quick Apply | C178: Akraya, Inc. | D178: Mountain View, CA · Reposted 32 minutes ago · 9 applicants Promoted by hirer · No response insights available yet | E178: https://www.linkedin.com/jobs/view/4348389382/
A179: 46000.035 | B179: Epic Cadence/Referrals Analyst Quick Apply | C179: TEKsystems | D179: Virginia Beach, VA · Reposted 7 minutes ago · 0 people clicked apply Promoted by hirer · Responses managed off LinkedIn | E179: https://www.linkedin.com/jobs/view/4342588218/
A180: 46000.036 | B180: *Technical Specialist (Healthcare) Quick Apply | C180: Cotiviti | D180: United States · Reposted 17 minutes ago · Over 100 people clicked apply Promoted by hirer · Responses managed off LinkedIn | E180: https://www.linkedin.com/jobs/view/4325308202/
A181: 46000.038 | B181: Senior Software Engineer I, New Product Development Quick Apply | C181: Axon | D181: Seattle, WA · 11 minutes ago · 1 person clicked apply Responses managed off LinkedIn | E181: https://www.linkedin.com/jobs/view/4342667947/
A182: 46000.039 | B182: Software Engineer – PEGA (Full-Stack Growth Path) Quick Apply | C182: Intuit | D182: Mountain View, CA · 1 hour ago · 20 people clicked apply Promoted by hirer · Responses managed off LinkedIn | E182: https://www.linkedin.com/jobs/view/4342697468/
A183: 46000.045 | B183: Software Engineer Quick Apply | C183: ServiceNow | D183: Santa Clara, CA · 1 hour ago · Over 100 people clicked apply Promoted by hirer · Responses managed off LinkedIn | E183: https://www.linkedin.com/jobs/view/4342707707/
A184: 46000.048 | B184: Software Engineer – PEGA (Full-Stack Growth Path) Quick Apply | C184: Intuit | D184: New York, NY · 2 hours ago · 15 people clicked apply Promoted by hirer · Responses managed off LinkedIn | E184: https://www.linkedin.com/jobs/view/4342786882/
A185: 46000.051 | B185: Test Engineer Quick Apply | C185: swipejobs | D185: Brea, CA · 2 hours ago · 11 people clicked apply Promoted by hirer · Responses managed off LinkedIn | E185: https://www.linkedin.com/jobs/view/4342697461/
A186: 46000.052 | B186: Software Engineer Quick Apply | C186: Lowe's Companies, Inc. | D186: Charlotte, NC · 2 hours ago · Over 100 people clicked apply Promoted by hirer · Responses managed off LinkedIn | E186: https://www.linkedin.com/jobs/view/4342777380/
A187: 46000.066 | B187: Java Application Developer with AWS Migration - Remote position Quick Apply | C187: R Systems | D187: United States · 2 hours ago · 34 people clicked apply Promoted by hirer · Responses managed off LinkedIn | E187: https://www.linkedin.com/jobs/view/4326266040/
A188: 46000.066 | B188: Business Intelligence Engineer 2 - Remote Quick Apply | C188: Humana | D188: United States · 3 hours ago · 55 people clicked apply Promoted by hirer · Responses managed off LinkedIn | E188: https://www.linkedin.com/jobs/view/4349050419/
A189: 46000.07 | B189: Software Engineer, Fulfillment Foundations Quick Apply | C189: Uber | D189: San Francisco, CA · 3 hours ago · 88 people clicked apply Responses managed off LinkedIn | E189: https://www.linkedin.com/jobs/view/4342617779/
... A217: 46027 | B217: Software Developer - Spring 2026 New Graduate | C217: D2L | D217: Multi Location | E217: https://jobright.ai/jobs/info/69420f7914ee092a69002d4c?utm_source=1100&utm_campaign=Software Engineering
A218: 46027 | B218: Solution Engineer Assc - Solution Engineer | C218: American Electric Power | D218: Multi Location | E218: https://jobright.ai/jobs/info/69420f7914ee092a69002d4c?utm_source=1100&utm_campaign=Software Engineering | G218: Application Under Consideration
A219: 46027 | B219: New Grad Software Engineer, Backend 2026 | C219: Circle | D219: Multi Location | E219: https://jobright.ai/jobs/info/69420f7914ee092a69002d4c?utm_source=1100&utm_campaign=Software Engineering
A220: 46027 | B220: Junior Technical Consultant (Boomi Integrations) | C220: Strategic Information Group | D220: Multi Location | E220: https://jobright.ai/jobs/info/69420f7914ee092a69002d4c?utm_source=1100&utm_campaign=Software Engineering
A221: 46027 | B221: Software Engineer (New Grad Summer 2026) | C221: Freeform | D221: Multi Location | E221: https://jobright.ai/jobs/info/69420f7914ee092a69002d4c?utm_source=1100&utm_campaign=Software Engineering
A222: 46027 | B222: Software Engineer - Distributed Systems (Platform Software ) | C222: Rubrik | D222: Multi Location | E222: https://jobright.ai/jobs/info/69420f7914ee092a69002d4c?utm_source=1100&utm_campaign=Software Engineering
A223: 46027 | B223: Junior Software Developer | C223: Ace Parking | D223: Multi Location | E223: https://jobright.ai/jobs/info/69420f7914ee092a69002d4c?utm_source=1100&utm_campaign=Software Engineering
A224: 46027 | B224: Software Engineer - Distributed Systems (Platform Software ) | C224: Rubrik | D224: Multi Location | E224: https://jobright.ai/jobs/info/69420f7914ee092a69002d4c?utm_source=1100&utm_campaign=Software Engineering
A225: 46027 | B225: Optical Network Embedded Software Engineer - New Grad | C225: Ciena | D225: Multi Location | E225: https://jobright.ai/jobs/info/69420f7914ee092a69002d4c?utm_source=1100&utm_campaign=Software Engineering
A226: 46027 | B226: Software Engineer, Integrations - Bellevue | C226: Aircall | D226: Multi Location | E226: https://jobright.ai/jobs/info/69420f7914ee092a69002d4c?utm_source=1100&utm_campaign=Software Engineering
A227: 46027 | B227: Game Test Analyst | C227: Sony Interactive Entertainment | D227: Multi Location | E227: https://jobright.ai/jobs/info/69420f7914ee092a69002d4c?utm_source=1100&utm_campaign=Software Engineering
A228: 46027 | B228: Machine Learning Engineer l | C228: Cohere Health | D228: Multi Location | E228: https://jobright.ai/jobs/info/69420f7914ee092a69002d4c?utm_source=1100&utm_campaign=Software Engineering
A229: 46027 | B229: Associate Solution Engineer | C229: Snowflake | D229: Multi Location | E229: https://jobright.ai/jobs/info/69420f7914ee092a69002d4c?utm_source=1100&utm_campaign=Software Engineering
A230: 46027 | B230: Graduate 2026 Software Engineer I, US | C230: Uber | D230: Multi Location | E230: https://jobright.ai/jobs/info/69420f7914ee092a69002d4c?utm_source=1100&utm_campaign=Software Engineering
... A274: 46028 | B274: Software Engineer, New Grad | C274: Stripe | D274: Seattle, WA · 11 minutes ago · 1 person clicked apply Responses managed off LinkedIn | E274: https://stripe.com/jobs/listing/software-engineer-new-grad/7210112/apply?gh_src=Simplify
A275: 46026 | B275: (New Grad) Software Engineering | C275: Samsara | E275: https://jobright.ai/jobs/info/68ccee1cd11b445e0bee4649?utm_source=1100&utm_campaign=Software Engineering
A276: 46026 | B276: Android Engineer I (Growth) | C276: WHOOP | E276: https://jobright.ai/jobs/info/68e7d8a9c4895107182bec62?utm_source=1100&utm_campaign=Software Engineering
A277: 46025 | B277: Software Engineer I - Web Frameworks, Officer | C277: State Street | E277: https://jobright.ai/jobs/info/695601f8aa05c26e7ab04e23?utm_source=1100&utm_campaign=Software Engineering
A278: 46030.816 | B278: Front End Developer (Jr-Mid React) Quick Apply | C278: Bounteous | D278: United States · 1 week ago · Over 100 people clicked apply Promoted by hirer · Responses managed off LinkedIn | E278: https://www.linkedin.com/jobs/view/4329962289/
A279: 46035.596 | B279: Software Engineer, AI Platform | C279: LinkedIn | D279: Mountain View, CA · 5 hours ago · Over 100 applicants Promoted by hirer · No response insights available yet | E279: https://www.linkedin.com/jobs/view/4361551460/
A280: 46040.672 | B280: Software Engineer | C280: Goliath Partners | D280: New York City Metropolitan Area · 1 hour ago · Over 100 applicants Promoted by hirer · No response insights available yet | E280: https://www.linkedin.com/jobs/view/4363849934/
A281: 46042.472 | B281: Production Support Analyst Quick Apply | C281: InvisALERT Solutions | D281: West Chester, PA · 34 minutes ago · 14 applicants Promoted by hirer · No response insights available yet | E281: https://www.linkedin.com/jobs/view/4364365955/
A282: 46048 | B282: 2026 University Graduate - Machine Learning Engineer | C282: https://jobright.ai/jobs/info/68ce072c1ad6b16f028a13f9?utm_source=1100&utm_campaign=Software Engineering | D282: Seattle, WA | E282: Adobe | G282: yes
A283: 46048 | B283: 2026 University Graduate - Research Scientist/Engineer | C283: https://jobright.ai/jobs/info/69049feaff462851feff6988?utm_source=1100&utm_campaign=Software Engineering | D283: Multi Location San Francisco, CA Seattle, WA | E283: Adobe | G283: yes
A284: 46048 | B284: AI Engineer, Asset Management | C284: https://jobright.ai/jobs/info/6977423b52f3c27ec643455e?utm_source=1100&utm_campaign=Software Engineering | D284: Boston, MA | E284: Manulife
A285: 46048 | B285: 2026 University Graduate - Machine Learning Engineer | C285: https://jobright.ai/jobs/info/68c7b57027f0732240603828?utm_source=1100&utm_campaign=Software Engineering | D285: San Jose, CA | E285: Adobe | G285: yes
A286: 46049 | B286: Product Software Engineer | C286: https://jobright.ai/jobs/info/6978d8a388e2b47213bcf353?utm_source=1100&utm_campaign=Software Engineering | D286: Multi Location San Diego, CA San Diego, California, United States of America | E286: Qualcomm
A287: 46049 | B287: Engineer | C287: https://jobright.ai/jobs/info/6978d6e439f7f96cc6d133a9?utm_source=1100&utm_campaign=Software Engineering | D287: San Diego, CA | E287: Qualcomm
A288: 46049 | B288: Junior Software Engineer | C288: https://jobright.ai/jobs/info/6978d45352f3c27ec6451abb?utm_source=1100&utm_campaign=Software Engineering | D288: Foster City, CA | E288: PTC | G288: yes
A289: 46049 | B289: Software Engineer | C289: https://jobright.ai/jobs/info/6978b8e088e2b47213bce2d7?utm_source=1100&utm_campaign=Software Engineering | D289: United States | E289: Microsoft
A290: 46051.412 | B290: Full Stack Engineer Quick Apply | C290: Fidelity Investments | D290: Roanoke, TX · 8 hours ago · 74 people clicked apply Promoted by hirer · Responses managed off LinkedIn | E290: https://www.linkedin.com/jobs/view/4366994421/
A291: 46051 | B291: Stripe | C291: Software Engineer, New Grad | D291: https://jobright.ai/jobs/info/697303a9694e99351d144796?utm_source=1100&utm_campaign=Software Engineering | E291: Hybrid
A292: 46051 | B292: Figma | C292: Early Career, Software Engineer (2026) | D292: https://jobright.ai/jobs/info/68d1ed62a54edb3bf3e1796e?utm_source=1100&utm_campaign=Software Engineering | E292: On Site
A293: 46051 | B293: Accuris | C293: Junior Software Engineer | D293: https://jobright.ai/jobs/info/6927510ed47de4798ecdb594?utm_source=1100&utm_campaign=Software Engineering | E293: Hybrid
A294: 46051 | B294: Vinson & Elkins | C294: Financial Systems Programmer Analyst | D294: https://jobright.ai/jobs/info/6947690163141d188457136c?utm_source=1100&utm_campaign=Software Engineering | E294: Hybrid
A295: 46051 | B295: Two Sigma | C295: Reliability Engineer - Trading | D295: https://jobright.ai/jobs/info/6789b508fade8859f716b08e?utm_source=1100&utm_campaign=Software Engineering | E295: Hybrid
A296: 46051 | B296: Center for AI Safety | C296: Research Engineer | D296: https://jobright.ai/jobs/info/697b2fd31423772304eb5b2b?utm_source=1100&utm_campaign=Software Engineering | E296: On Site
A297: 46051 | B297: Nordstrom | C297: iOS Engineer 1 - Customer Mobile Applications Team (Hybrid - Seattle, WA) | D297: https://jobright.ai/jobs/info/697b2c2c17b11b1c2e424083?utm_source=1100&utm_campaign=Software Engineering | E297: Hybrid
A298: 46051 | B298: Axon.ai | C298: Backend Engineer, New Grad | D298: https://jobright.ai/jobs/info/691dfcc409cc522e877347d6?utm_source=1100&utm_campaign=Software Engineering | E298: On Site
A299: 46051 | B299: AppLovin | C299: Backend Engineer, New Grad | D299: https://jobright.ai/jobs/info/68cce286d11b445e0bee3cbc?utm_source=1100&utm_campaign=Software Engineering | E299: On Site
A300: 46051 | B300: Data QA Specialist | C300: 1X | D300: https://jobright.ai/jobs/info/697c23310b88cc7d64232804?utm_source=1100&utm_campaign=Software Engineering
A301: 46051 | B301: Junior Software Developer | C301: Ace Parking | D301: https://jobright.ai/jobs/info/697bd8bb1136d179eeef6919?utm_source=1100&utm_campaign=Software Engineering
A302: 46052 | B302: Research Associate, Cloud | C302: Activision | D302: https://jobright.ai/jobs/info/697c7c6b727747250d572d7c?utm_source=1100&utm_campaign=Software Engineering
A303: 46052.481 | B303: Senior LangGraph Developer | C303: Global Applications Solution | D303: Dallas, TX | E303: https://www.linkedin.com/jobs/view/4367481163/
A304: 46052 | B304: Software Development Engineer | C304: Adobe | D304: https://jobright.ai/jobs/info/697c8ac0727747250d574c88?utm_source=1100&utm_campaign=Software Engineering
A305: 46052 | B305: Software Engineer II, Backend (Infrastructure) | C305: Affirm | D305: https://jobright.ai/jobs/info/6944adcf50bbaf765056c56d?utm_source=1100&utm_campaign=Software Engineering
A306: 46052 | B306: Software Engineer II, Backend (Infrastructure) | C306: Affirm | D306: https://jobright.ai/jobs/info/6944b4c9a7227b3ece666036?utm_source=1100&utm_campaign=Software Engineering
A307: 46052 | B307: Software Engineer II, Backend (Identity Decisioning) | C307: Affirm | D307: https://jobright.ai/jobs/info/6940950caa598a08c3f0408c?utm_source=1100&utm_campaign=Software Engineering
A308: 46052.498 | B308: DevOps Engineer | C308: AMH | D308: Draper, UT · Reposted 5 hours ago · Over 100 applicants Promoted by hirer · No response insights available yet | E308: https://www.linkedin.com/jobs/view/4345022455/
A309: 46051 | B309: Junior Software Engineer - Portfolio Implementation Analytics | C309: AQR Capital Management | D309: https://jobright.ai/jobs/info/697bb89d0b88cc7d642283ca?utm_source=1100&utm_campaign=Software Engineering
A310: 46051 | B310: Apple | C310: AR/VR Software Development Engineer | D310: https://jobright.ai/jobs/info/697c8112137a0510256584f5?utm_source=1100&utm_campaign=Software Engineering
A311: 46051 | B311: Apple | C311: Software Development Engineer | D311: https://jobright.ai/jobs/info/697c8103137a0510256584cf?utm_source=1100&utm_campaign=Software Engineering
A312: 46051 | B312: Apple | C312: Software Development Engineer - Test | D312: https://jobright.ai/jobs/info/697c7af6727747250d572a0e?utm_source=1100&utm_campaign=Software Engineering
A313: 46051 | B313: Apple | C313: Software Development Engineer - Test | D313: https://jobright.ai/jobs/info/697c7b48727747250d572c75?utm_source=1100&utm_campaign=Software Engineering
A314: 46051 | B314: Apple | C314: Config/Release Engineer | D314: https://jobright.ai/jobs/info/697c811e137a0510256584ff?utm_source=1100&utm_campaign=Software Engineering
A315: 46051 | B315: Apple | C315: Software Development Engineer | D315: https://jobright.ai/jobs/info/697c8112137a0510256584f4?utm_source=1100&utm_campaign=Software Engineering
A316: 46058 | B316: Cellular Protocol Stack Developer | C316: https://jobright.ai/jobs/info/698514108da7a612045f6910?utm_source=1100&utm_campaign=Software Engineering | D316: On Site | E316: San Diego, California, United States | G316: $120300-$210100 /yr | H316: 10000+ | I316: Apps, Artificial Intelligence (AI) | J316: 1. Bachelors and/or Master's degree in Electrical Engineering, Computer Science, or equivalent field. 2. 0-2 years of experience in embedded system software development. 3. Strong Software Engineering skills including design, programming using C/C++. | K316: not sure | L316: yes
...

Sheet Pending Work 23th Feb
A1: Count | B1: Company Name | C1: Position Name | D1: Current Date | E1: Updated Date | F1: Comment | G1: Link
A2: 1 | B2: Nvidia | C2: Solution Architect | D2: 46075 | G2: https://nvidia.wd5.myworkdayjobs.com/NVIDIAExternalCareerSite/job/US-CA-Santa-Clara/Solutions-Architect--Worldwide-Field-Operations---New-College-Graduate-2026_JR2004686?source=Eightfold
A3: 2 | B3: Zip | C3: Software Engineer, New Grad (2026 Start) | D3: 46075 | F3: I need to reach out to the recuiter regarding the message suggested by gpt | G3: https://www.linkedin.com/in/bhavani-nkrishna/ | H3: Hi Bhavani, I just applied for the Software Engineer role at Zip via Ashby and wanted to introduce myself. I came across your profile through mutual connections and thought I’d reach out in case you’re the right person to speak with or can point me to the appropriate recruiter. Thanks for your time.

Sheet YCDI
A15: 46068 | B15: Android Engineer (Growth & Ecosystem) | C15: https://jobright.ai/jobs/info/68e7d8a9c4895107182bec62?utm_source=1100&utm_campaign=Software Engineering | D15: On Site | E15: Boston, MA | F15: WHOOP | G15: $105K-$145K /yr | H15: 501-1000 | I15: Consumer Electronics, Fitness | J15: 1. 0–2 years of professional experience in Android development (internship or academic experience acceptable) 2. Proficiency with Kotlin and familiarity with Android Studio and Jetpack libraries 3. Understanding of Android fundamentals including lifecycle, UI components, and REST API integration 4. Enthusiasm for writing clean code and collaborating in a team environment 5. Willingness to learn architecture patterns like MVVM and modular design ... | K15: not sure | L15: yes
A16: 46068 | B16: Software Engineer - Core Product | C16: https://jobright.ai/jobs/info/6991b50c6ea51a7610f40e53?utm_source=1100&utm_campaign=Software Engineering | D16: Remote | E16: New York, NY | F16: Baseten | G16: $150K-$230K /yr | H16: 101-250 | I16: AI Infrastructure, Artificial Intelligence (AI) | J16: 1. Bachelor's degree or higher in Computer Science or related field 2. 1-3 years experience in software engineering or infrastructure 3. Proficient coding abilities in one or more popular programming or scripting languages; Python, Go, or Javascript proficiency is a plus 4. Familiarity with web applications & databases 5. Good taste in product, particularly developer-oriented tools ... | K16: not sure
A17: 46068 | B17: Software Engineer - C++ Core Middleware | C17: https://jobright.ai/jobs/info/68cee4ad846f0b04af67d99a?utm_source=1100&utm_campaign=Software Engineering | D17: Hybrid | E17: Foster City, CA | F17: Zoox | G17: $175K-$212K /yr | H17: 1001-5000 | I17: Artificial Intelligence (AI), Autonomous Vehicles | J17: 1. 1+ years of professional software development experience 2. Strong proficiency in modern C++ (C++14/17) 3. Strong background in developing scalable, distributed applications in Linux and the Nvidia Drive platform 4. Experience with GPU/CUDA programming 5. Experience with robotics frameworks/middleware (e.g., ROS/ROS2) | K17: not sure
A18: 46068 | B18: Associate R & D Data Scientist | C18: https://jobright.ai/jobs/info/69580d75f1f8465b79eeaf5b?utm_source=1100&utm_campaign=Software Engineering | D18: Remote | E18: Princeton, NJ | F18: ETS | G18: N/A | H18: 5001-10000 | I18: Association, EdTech | J18: 1. Demonstrable proficiency and experience in Python and/or R for data analysis and modeling. 2. Hands-on experience with PyTorch/TensorFlow, Scikit-learn, and other machine learning frameworks. 3. Familiarity with generative AI methods and their practical applications. 4. Strong understanding of statistical methods, experimental design, and data visualization. 5. Ability to work in cloud computing environments (e.g., AWS) for model deployment and data processing. ... | K18: not sure
A19: 46068 | B19: Embedded NPU Software Engineer | C19: https://jobright.ai/jobs/info/69840c1f01214b4cdacc6e42?utm_source=1100&utm_campaign=Software Engineering | D19: On Site | E19: San Diego, CA | F19: Qualcomm | G19: $94200-$141200 /yr | H19: 10000+ | I19: Artificial Intelligence (AI), Generative AI | J19: 1. Bachelor's degree in Engineering, Information Systems, Computer Science, or related field. 2. Develop and validate embedded NPU software features in C/C++ for real-time systems. 3. Participate in the design and implementation of inter-processor communication and memory management mechanisms. 4. Assist in debugging, profiling, and optimizing software for performance and power efficiency. 5. Collaborate with cross-functional teams to integrate NPU software into broader system frameworks. ... | K19: not sure
A20: 46068 | B20: Deep Learning Kernel Software Performance Architect - New College Grad 2026, Deep Learning Kernel Software Performance Architect - New College Grad 2026 | C20: https://jobright.ai/jobs/info/69743bf0206da320f49e61ae?utm_source=1100&utm_campaign=Software Engineering | D20: On Site | E20: Santa Clara, CA | F20: NVIDIA | G20: $124K-$242K /yr | H20: 10000+ | I20: AI Infrastructure, Artificial Intelligence (AI) | J20: 1. Master's or PhD in Computer Science, Electrical Engineering or Computer Engineering, or equivalent experience. 2. Proven expertise in software design, including debugging, performance analysis, and test development 3. Hands-on experience with practical parallel programming, even if it’s not on GPUs. 4. Strong understanding of computer architecture, with practical experience on performance debugging. 5. Ability to identify bottlenecks, optimize resource utilization, and enhance system throughput ... | K20: not sure
A21: 46069 | B21: Systems Programmer I | C21: https://jobright.ai/jobs/info/6994d97fe0bddb6acac35703?utm_source=1100&utm_campaign=Software Engineering | D21: Hybrid | E21: St Charles, IL | F21: OSG USA, INC. | G21: $56K-$73K /yr | H21: 101-250 | I21: Industrial, Manufacturing | J21: 1. HS Diploma/GED or equivalent 2. Experience computer programming in X++, C#, and/or SQL 3. Experience with Microsoft Office Products 4. Excellent problem-solving and analytical skills 5. Basic knowledge of database management, SQL, and data modeling | K21: not sure
A22: 46069 | B22: El Mirage, Arizona- Network Infrastructure Engineer – Data Center | C22: https://jobright.ai/jobs/info/6993e38e81476f6176ab8092?utm_source=1100&utm_campaign=Software Engineering | D22: On Site | E22: El Mirage, AZ | F22: Catapult Federal Services | G22: $75K-$85K /yr | H22: 11-50 | J22: 1. 1–3 years of hands-on experience in a network support or systems administration role. 2. Comfortable working in active construction and commissioning environments and wearing required personal protective equipment (PPE) such as steel-toe boots, hard hats, and safety vests. 3. Ability to perform physical tasks including standing for extended periods, working in equipment racks, and lifting or moving network hardware as required. 4. Strong understanding of LAN/WAN fundamentals, including IP addressing, subnetting, VLANs, and routing. 5. Hands-on experience with Cisco networking equipment (switching and routing). ... | K22: not sure
A23: 46069 | B23: Zoho Developer | C23: https://jobright.ai/jobs/info/69955c76ce78e77b4fd97ff7?utm_source=1100&utm_campaign=Software Engineering | D23: Remote | E23: Remote job | F23: KDG | G23: $65000-$75000 /yr | H23: 11-50 | I23: Cyber Security, Digital Marketing | J23: 1. Demonstrated professional integrity, accountability, and ethical judgment, with a consistent commitment to doing what is right for the client, the team, and the business. 2. Strong business-first mindset, viewing technology as a tool to support operational efficiency, scalability, and long-term success—not as an end in itself. 3. Proven ability to communicate clearly and respectfully with Project Managers, Business Analysts, and customers, translating complex ideas into practical, shared understanding. 4. High sense of ownership and responsibility, following through on commitments, proactively addressing challenges, and taking pride in delivering meaningful outcomes. 5. Thoughtful and disciplined approach to listening, clarifying, and validating requirements before designing or building solutions. ... | K23: not sure
A24: 46069 | B24: System Administrator 1 | C24: https://jobright.ai/jobs/info/6993cedb81476f6176ab6a58?utm_source=1100&utm_campaign=Software Engineering | D24: Hybrid | E24: La Crosse, WI | F24: Kwik Trip, Inc. | G24: $27-$40 /hr | H24: 10000+ | I24: Consumer Goods, Food and Beverage | J24: 1. Associate degree in Information Systems/Network Systems Administration or equivalent combination of education and experience is required. 2. Experience related to server and infrastructure management, with specific focus on the setup and maintenance of servers and applications within a virtual environment. 3. Knowledge of Microsoft Windows client and server operating systems 4. Experience with Office 365 administration (including Exchange Online, SharePoint Online, etc.) 5. Experience with Microsoft Active Directory, and Microsoft Group Policy management. ... | K24: not sure
A25: 46069 | B25: Flight Software Engineer | C25: https://jobright.ai/jobs/info/6993f025e0bddb6acac23b53?utm_source=1100&utm_campaign=Software Engineering | D25: On Site | E25: San Francisco, CA | F25: Astro Mechanica | G25: $90K-$160K /yr | H25: 46032 | I25: Aerospace, Manufacturing | J25: 1. Bachelor’s degree in Computer Science, Engineering, Math, or a Science discipline 2. 0-3 years of professional software development experience, including internships and research experience 3. Experience in C++, Rust, or other systems programming language 4. Proven skills in debugging, performance optimization, and unit testing 5. Ambition to work in a fast-paced environment | K25: not sure | L25: yes
A26: 46069 | B26: INFORMATION TECHNOLOGY SPECIALIST I | C26: https://jobright.ai/jobs/info/6994d12081476f6176aca282?utm_source=1100&utm_campaign=Software Engineering | D26: Hybrid | E26: Sacramento, CA | F26: California State Treasurer's Office | G26: $6513-$10852 /mon | H26: 101-250 | I26: Banking, Education | J26: 1. The position(s) require(s) a Background Investigation be cleared prior to being hired. 2. Current version of the State Examination/Employment Application STD Form 678 (when not applying electronically), or the Electronic State Employment Application through your Applicant Account at www.CalCareers.ca.gov. All Experience and Education relating to the Minimum Qualifications listed on the Classification Specification should be included to demonstrate how you meet the Minimum Qualifications for the position. 3. Resume is required and must be included. 4. School Transcripts | K26: not sure
A27: 46069 | B27: Computer Science and Engineering Department: CROSS Practitioner in Residence Pool | C27: https://jobright.ai/jobs/info/6995703f81476f6176ad606f?utm_source=1100&utm_campaign=Software Engineering | D27: On Site | E27: Santa Cruz County, CA | F27: Waco Tribune-Herald | G27: $55000-$194800 /yr | H27: 101-250 | I27: Fitness, News | J27: 1. Bachelor’s degree or higher (or equivalent foreign degree). 2. Experience in open source software development. | K27: yes
A28: 46069 | B28: Software Engineer - Simulators | C28: https://jobright.ai/jobs/info/6997ded6e0bddb6acac6b3d6?utm_source=1100&utm_campaign=Software Engineering | D28: Hybrid | E28: Mountain View, CA | F28: MatX | G28: $120000-$200000 /yr | H28: 11-50 | I28: AI Infrastructure, Artificial Intelligence (AI) | J28: 1. Bachelor of Computer Science or equivalent degree 2. Excellent software engineering skills, with a focus on maintainable performant 3. Strong foundation in computer architecture fundamentals 4. Excellent cross-functional communication skills 5. Rust experience AND/OR experience writing cycle-accurate simulators ... | K28: not sure | L28: yes
A29: 46069 | B29: System Development Engineer I, REALM | C29: https://jobright.ai/jobs/info/6993d865ce78e77b4fd7abc3?utm_source=1100&utm_campaign=Software Engineering | D29: On Site | E29: Bellevue, Washington, USA | F29: Amazon | G29: $99,100-$160,000 /yr | H29: 10000+ | I29: Artificial Intelligence (AI), Delivery | J29: 1. Experience in automating, deploying, and supporting infrastructure 2. Experience programming with at least one modern language such as Python, Ruby, Golang, Java, C++, C#, Rust 3. Experience with Linux/Unix 4. 1+ years of DevOps or SysOps in a large-scale software development environment experience 5. Bachelor's degree in computer science, computer engineering, or related field | K29: not sure
A30: 46069 | B30: Data Engineer | C30: https://jobright.ai/jobs/info/69939ba3ce78e77b4fd76e5c?utm_source=1100&utm_campaign=Software Engineering | D30: Hybrid | E30: Multi Location Utah, United States Washington, United States Colorado, United States Oregon, United States | F30: Slalom | G30: $91000-$122000 /yr | H30: 10000+ | I30: Collaboration, Consulting | J30: 1. Experience with Big Data Platforms (Apache Spark, Presto, Amazon EMR) 2. Experience with Cloud Data Warehouses (Amazon Redshift, Snowflake, Google BigQuery) 3. Proficiency in Object Oriented Coding (Java, Python) 4. Experience with NoSQL Databases (DynamoDB, Cosmos DB, MongoDB) 5. Familiarity with Container Management Systems (Kubernetes, Amazon ECS) ... | K30: not sure
A31: 46069 | B31: Software Engineer, Autonomy-New Grad | C31: https://jobright.ai/jobs/info/693e643baa598a08c3eeb026?utm_source=1100&utm_campaign=Software Engineering | D31: On Site | E31: Mountain View, CA | F31: Nuro | G31: $145K-$219K /yr | H31: 501-1000 | I31: Artificial Intelligence (AI), Autonomous Vehicles | J31: 1. You are a recent graduate or graduating soon (BS, MS or PhD) with focus on one or more of the areas listed above 2. You are a skilled algorithm designer with strong problem solving 3. You are a talented software developer ideally with experience in C++/Python 4. You have experience working with machine learning or autonomous systems 5. You have a knack and real passion for searching and solving hard problems ... | K31: not sure | L31: yes
A32: 46069 | B32: Data Engineer | C32: https://jobright.ai/jobs/info/6993adeb81476f6176ab485f?utm_source=1100&utm_campaign=Software Engineering | D32: Remote | E32: 400 NW Plz Dr, St Ann, MO 63074, USA | F32: Save A Lot | G32: $85300-$107000 /yr | H32: 1001-5000 | I32: Food Processing | J32: 1. 1-3 years of IT experience 2. 1-3 years of experience with Python 3. 1-3 years of experience with SQL 4. 1-3 years of experience delivering projects in a complex enterprise environment 5. 1-3 years developing and delivering data engineering solutions in data warehousing ... | K32: not sure
A33: 46069 | B33: AI Prompt Engineer Associate (DMV) | C33: https://jobright.ai/jobs/info/6993f5c9ce78e77b4fd7d33f?utm_source=1100&utm_campaign=Software Engineering | D33: Remote | E33: Any Location / Remote | F33: General Dynamics Information Technology | G33: $80750-$109250 /yr | H33: 10000+ | I33: Artificial Intelligence (AI), Cloud Computing | J33: 1. Education: Bachelor of Arts/Bachelor of Science or High School Degree 2. Experience: 0+ years of related experience with BA/BS or 4 years of relevant experience with High School Degree 3. Excellent problem-solving skills with creative mindset 4. Strong communication skills to collaborate with other program members and stakeholders 5. Curiosity about AI systems, how they work, and how to optimize generative AI responses ... | K33: not sure | L33: yes
A34: 46069 | B34: App Review Specialist | C34: https://jobright.ai/jobs/info/699365a581476f6176ab059c?utm_source=1100&utm_campaign=Software Engineering | D34: On Site | E34: Sunnyvale, California, United States | F34: Apple | G34: $27.75-$47.02 /hr | H34: 10000+ | I34: Apps, Artificial Intelligence (AI) | J34: 1. Fluency in English and Spanish as this role will frequently be supporting language-specific apps. 2. Available to work a Tuesday–Saturday schedule. | K34: not sure
A35: 46069 | B35: Software Engineer | C35: https://jobright.ai/jobs/info/68afbe89b47fb001d688cc34?utm_source=1100&utm_campaign=Software Engineering | D35: Hybrid | E35: Seattle, WA | F35: Aircall | G35: $140K-$190K /yr | H35: 501-1000 | I35: Analytics, Call Center | J35: 1. At least 1 year of professional experience in back-end or full-stack development 2. Expert level programming ability with Typescript (+React), Python, or Ruby 3. Deep understanding of software development practices, scalable system architecture, security best practices and cloud-based platforms 4. Proven understanding of distributed computing principles and experience with cloud-based platforms 5. Exceptional analytical and problem-solving skills, with the ability to effectively troubleshoot complex data issues ... | K35: not sure
A36: 46069 | B36: Machine Learning Engineer l | C36: https://jobright.ai/jobs/info/68cddf34e23def7af55bfd8a?utm_source=1100&utm_campaign=Software Engineering | D36: Remote | E36: United States | F36: Cohere Health | G36: $95K-$115K /yr | H36: 501-1000 | I36: Consumer Software, Health Care | J36: 1. 1-3 years full time professional experience in ML 2. MS in computer science, machine learning, computational linguistics, statistics, mathematics or similar field 3. Hands on experience building with modern language models, including context-engineering LLMs or fine-tuning SLMs 4. Understanding of scientific best practice in experimental design and can independently perform data collection, measurement, and interpretation of results 5. Experience configuring, training, evaluating, deploying, and maintaining models in a production setting ... | K36: not sure
A37: 46069 | B37: AI Automation & Growth Analyst | C37: https://jobright.ai/jobs/info/6993231081476f6176aacbce?utm_source=1100&utm_campaign=Software Engineering | D37: On Site | E37: Los Angeles, CA | F37: Warner Music Group | G37: $70K-$80K /yr | H37: 1001-5000 | I37: Digital Entertainment, Media and Entertainment | J37: 1. Strong Scripting Skills (Python or JavaScript): You have strong hands-on experience using Python or JavaScript/TypeScript for data manipulation, API interaction, and process automation. You prefer writing a script to doing a task manually twice. 2. Data & SQL Fluency: You are comfortable writing SQL queries to pull, clean, and structure data from relational databases. You understand how to prepare data for AI context windows. 3. Version Control (Git): You understand the importance of source control. You are familiar with branching, merging, and pull requests to maintain a clean codebase in a team environment. 4. LLM & API Experience: You have built applications or scripts that utilize LLM APIs (OpenAI, Anthropic, Gemini). You understand concepts like context limits, temperature, and prompt engineering within code. 5. Grounded in Engineering Principles: You build for the long term. You strive to write clean, scalable, and reliable code that can be maintained and built upon by the team. ... | K37: not sure
A38: 46069 | B38: Software Engineer II, Backend (Credit Decisioning) | C38: https://jobright.ai/jobs/info/69766b97bc8e722e7b1b01c5?utm_source=1100&utm_campaign=Software Engineering | D38: Remote | E38: Multi Location Las Vegas, NV Denver, CO Atlanta, GA Houston, TX New York, NY San Diego, CA Portland, OR Pittsburgh, PA Salt Lake City, UT Detroit, MI Richmond, VA Boulder, CO Washington, DC Cleveland, OH Sioux Falls, SD Palo Alto, CA San Francisco, CA Minneapolis, MN Raleigh, NC Dallas, TX Nashville, TN Phoenix, AZ Boston, MA Chicago, IL Austin, TX Los Angeles, CA Philadelphia, PA San Jose, CA Madison, WI St Louis, MO Charlotte, NC Seattle, WA Miami, FL Baltimore, MD Boise, ID | F38: Affirm | G38: $160,000-$210,000 /yr | H38: 1001-5000 | I38: Financial Services, FinTech | J38: 1. You have a total of 1.5+ years of experience as a software engineer. 2. You have experience designing, developing and launching backend systems and are proficient in one of Python or Kotlin. 3. You are familiar with the building blocks of distributed systems, and the technologies like AWS, MySQL and Kubernetes. 4. You have mastered taking a simple problem or business scenario into a solution that interacts with multiple software components, and executing on it by writing clear, easily understood, well tested and extensible code. 5. You are comfortable navigating a large code base, debugging others' code, and providing feedback to other engineers through code reviews. ... | K38: not sure
A39: 46069 | B39: Game Test Analyst | C39: https://jobright.ai/jobs/info/690b95204a1b456627b10975?utm_source=1100&utm_campaign=Software Engineering | D39: On Site | E39: San Diego, CA | F39: Sony Interactive Entertainment | G39: $17-$18 /hr | H39: 10000+ | I39: Consumer Goods, Music | J39: 1. Must be at least 18 years of age 2. Strong analytical and problem solving skills 3. Excellent written and verbal communication (needs to be able to communicate bugs how did you find them? What exact steps are needed to make it happen again?) 4. Basic to intermediate understanding of networking setup and hardware, as well as how its principles and components apply to modern console, PC, and mobile gaming / functionality 5. Ability to work in both an individual and team environment ... | K39: not sure
A40: 46069 | B40: Junior Full Stack Engineer ($250k - $300k salary) | C40: https://jobright.ai/jobs/info/69933bb7e0bddb6acac18538?utm_source=1100&utm_campaign=Software Engineering | D40: On Site | E40: New York, NY | F40: Baton Corporation | G40: $250K-$300K /yr | H40: 11-50 | J40: 1. An exceptional early-career engineer with a strong foundation in computer science and the ability to ramp quickly on new systems and codebases 2. Studied at a top university or demonstrated equivalent ability through competitive programming, Olympiads, open-source contributions, or substantial personal projects 3. Comfortable working across the stack, with hands-on experience in technologies like TypeScript, React, Next.js, and Node.js (or adjacent modern frameworks) 4. Curious and intellectually rigorous - you enjoy understanding why systems work, not just how to use them 5. A strong problem solver who can break down ambiguous problems, reason from first principles, and iterate toward solid solutions ... | K40: not sure
A41: 46069 | B41: QA Analyst (Temp) | C41: https://jobright.ai/jobs/info/69485501d1953b5d11c1610e?utm_source=1100&utm_campaign=Software Engineering | D41: On Site | E41: Austin, TX | F41: Daybreak Game Company LLC | G41: $14-$17 /hr | H41: 501-1000 | I41: Gamification, Gaming | J41: 1. Proficient in QA Methodologies and best practices 2. Excellent written and verbal communication 3. 1 year of quality assurance experience 4. Create and execute test plans 5. Collaborate with other analysts and developers to ensure thorough testing of content ... | K41: not sure
A42: 46069 | B42: Engineer II - Software Defined Storage | C42: https://jobright.ai/jobs/info/6976c169206da320f4a077ca?utm_source=1100&utm_campaign=Software Engineering | D42: Hybrid | E42: Multi Location Palo Alto, CA Chevy Chase, MD Seattle, WA Dallas, TX | F42: GEICO | G42: $75K-$160K /yr | H42: 10000+ | I42: Auto Insurance, Financial Services | J42: 1. Understanding of various storage architectures and solutions, including object storage (with technologies like Amazon S3, OpenStack Swift), block storage (using software like iSCSI, Fibre Channel), and file storage (solutions such as NFS, SMB/CIFS) 2. Proficiency with data management and storage protocols/services (e.g., Fibre Channel, iSCSI, NFS, SMB/CIFS) 3. Familiarity with virtualization technologies (e.g., VMware, Hyper-V) and their interaction with underlying storage infrastructures 4. Understanding of and experience with software-defined storage services such as Ceph, MinIO, Swift, OpenStack, and GlusterFS 5. Proficiency with cloud services and infrastructure, including public and private cloud environments ... | K42: yes
A43: 46069 | B43: Trade Systems Engineer | C43: https://jobright.ai/jobs/info/6806869622b8e29f156721fb?utm_source=1100&utm_campaign=Software Engineering | D43: On Site | E43: Chicago, IL | F43: DRW | G43: $85K-$125K /yr | H43: 1001-5000 | I43: Consulting, Finance | J43: 1. 1–3 years of experience in trade support, systems administration, site reliability engineering, or a related technical role (internships or projects count!) 2. Bachelor’s degree in Computer Science, Engineering, or related STEM field 3. Basic understanding of networking concepts (TCP/IP, DNS, DHCP) and ability to use common troubleshooting tools 4. Ability to think through and troubleshoot technical problems under time pressure 5. Clear communication skills, written and verbal ... | K43: not sure
A44: 46070 | B44: Production Engineer, Global Banking & Markets, FICC Systematic Market Making (SMM) | C44: https://jobright.ai/jobs/info/69957643e0bddb6acac40d5e?utm_source=1100&utm_campaign=Software Engineering | D44: On Site | E44: Multi Location New York, NY New York, New York, United States | F44: Goldman Sachs | G44: $115000-$180000 /yr | H44: 10000+ | I44: Banking, Finance | J44: 1. 1 year or more of relevant work experience 2. Proficiency in one of the following: Python, C, C++, Java, or shell scripting 3. Aptitude for algorithms, data structures, and software design 4. Experience with Linux operating system internals and/or networking concepts 5. Strong analytical skills, with an ability to quickly identify scope and impact of issues during high-pressure situations ... | K44: not sure
A45: 46070 | B45: Software Engineer | C45: https://jobright.ai/jobs/info/6997e315e0bddb6acac6bdac?utm_source=1100&utm_campaign=Software Engineering | D45: On Site | E45: Sioux Falls, SD | F45: Sanford Health | G45: $32-$52 /hr | H45: 10000+ | I45: Children, Education | J45: 1. Bachelor's Degree in a computer-related field required. 2. Basic knowledge of computer principles and techniques necessary to develop and document software applications systems. 3. Basic knowledge of relational databases. 4. Basic knowledge of Object Oriented programming. 5. Basic knowledge of ASP.NET. ... | K45: not sure
A46: 46070 | B46: Firmware Validation Engineer & Flashing Engineer | C46: https://jobright.ai/jobs/info/6995608fce78e77b4fd98621?utm_source=1100&utm_campaign=Software Engineering | D46: On Site | E46: Palo Alto, CA | F46: Tesla | G46: $140000-$210000 /yr | H46: 10000+ | I46: Automotive, Electric Vehicle | J46: 1. Minimum of 1 to 3 years prior experience in embedded systems, software engineering (or similar role) 2. Bachelor’s Degree in Computer Science, Electrical Engineering, Computer Engineering, or related field, or equivalent experience 3. Solid Python experience 4. Understanding of branching, configuration management, testing, build and release processes for complex software 5. Must have fundamentals in electrical engineering ... | K46: not sure
A47: 46070 | B47: Firmware Validation Engineer & Flashing Engineer | C47: https://jobright.ai/jobs/info/69955f92ce78e77b4fd98538?utm_source=1100&utm_campaign=Software Engineering | D47: On Site | E47: Palo Alto, CA | F47: Tesla | G47: $140K-$210K /yr | H47: 10000+ | I47: Automotive, Electric Vehicle | J47: 1. Minimum of 1 to 3 years prior experience in embedded systems, software engineering (or similar role) 2. Bachelor’s Degree in Computer Science, Electrical Engineering, Computer Engineering, or related field, or equivalent experience 3. Solid Python experience 4. Understanding of branching, configuration management, testing, build and release processes for complex software 5. Must have fundamentals in electrical engineering ... | K47: not sure
A48: 46070 | B48: IT Systems Engineer | C48: https://jobright.ai/jobs/info/69955b49e0bddb6acac3eb98?utm_source=1100&utm_campaign=Software Engineering | D48: Hybrid | E48: San Francisco, CA | F48: You.com | G48: $90K-$120K /yr | H48: 51-100 | I48: Artificial Intelligence (AI), Chatbot | J48: 1. Bachelor's degree in Information Technology, Computer Science, or a related field (or equivalent practical experience). 2. 0–2 years of professional IT support experience. 3. Demonstrable Python and Bash scripting ability (personal projects, coursework, or professional experience). 4. Familiarity with Git/GitHub workflows. 5. Understand how to use command line on Linux and MacOS. | K48: not sure | L48: yes
A49: 46070 | B49: Software Engineer I / II - San Francisco | C49: https://jobright.ai/jobs/info/68f95f5acadb2e5a06a64637?utm_source=1100&utm_campaign=Software Engineering | D49: On Site | E49: Multi Location San Francisco, CA San Francisco Bay Area | F49: Giga | G49: $160K-$250K /yr | H49: 11-50 | I49: Artificial Intelligence (AI), B2C | J49: 1. 1-3 years of professional software engineering experience 2. Curious and ask good questions—you want to understand why things work, not just how 3. Can take feedback well and iterate quickly 4. Prefer shipping over perfection but still care about quality 5. Want to grow at a startup where you'll have real responsibility early | K49: not sure
A50: 46070 | B50: Junior Systems Administrator | C50: https://jobright.ai/jobs/info/6995b059ce78e77b4fd9c70f?utm_source=1100&utm_campaign=Software Engineering | D50: Hybrid | E50: Washington, DC | F50: Urban Land Institute | G50: $56K-$67K /yr | H50: 51-100 | I50: Association, Real Estate | J50: 1. Working knowledge of Windows 10/11 2. Working knowledge of macOS and iOS 3. Working knowledge of Microsoft 365 applications 4. Working knowledge of Active Directory and Azure Active Directory 5. Exposure to cloud platforms (Azure, AWS, or Google Workspace) preferred but not required ... | K50: not sure
A51: 46070 | B51: Associate Machine Learning Engineer | C51: https://jobright.ai/jobs/info/69955e8b81476f6176ad4958?utm_source=1100&utm_campaign=Software Engineering | D51: On Site | E51: SD Metro Area | F51: XiFin, Inc. | G51: $70K-$100K /yr | H51: 501-1000 | I51: Enterprise Software, Health Care | J51: 1. Bachelor’s or Master’s degree in Computer Science, Engineering, Data Science, or a related technical field 2. 0–3 years of programming experience in Python (including academic projects, internships, research, or personal projects) 3. Foundational understanding of data structures, algorithms, and software development principles 4. Demonstrated interest in artificial intelligence, automation, and applied machine learning 5. Demonstrate a strong growth mindset and eagerness to learn emerging AI technologies ... | K51: not sure | L51: yes
A52: 46070 | B52: Entry-Level Embedded Systems Engineer | C52: https://jobright.ai/jobs/info/69957131ce78e77b4fd99c9e?utm_source=1100&utm_campaign=Software Engineering | D52: On Site | E52: Allentown, PA | F52: Broadcom | G52: $73K-$117K /yr | H52: 10000+ | I52: Mobile, Semiconductor | J52: 1. Master’s Degree in Electrical Engineering or Computer Engineering 2. Proficient in C and Python 3. Self-directed and motivated | K52: not sure
A53: 46070 | B53: Security Engineer, New Grad | C53: https://jobright.ai/jobs/info/699949e6e0bddb6acac868fe?utm_source=1100&utm_campaign=Software Engineering | D53: Hybrid | E53: Multi Location San Francisco, CA Seattle, WA | F53: Stripe | G53: $129K-$193K /yr | H53: 5001-10000 | I53: Finance, FinTech | J53: 1. Currently enrolled in a Bachelor’s or Master’s program in Computer Science or related field (graduating by Summer 2026) 2. Some experience and familiarity with programming, either through side projects or classwork. We work mostly in Java, Ruby, Python, JavaScript, Scala, and Go. We believe new programming languages can be learned if the fundamentals and general knowledge are present 3. Experience from either previous internships or working collaboratively on multi-person coding projects (in a university or professional setting) 4. Ability to learn unfamiliar systems and form an understanding of those systems, through independent research and working with a mentor and subject matter experts 5. Aptitude to think like an attacker and reason through different approaches to reducing security risk. | K53: not sure | L53: yes
A54: 46070 | B54: R&D Engineer, Embedded Systems (Onsite) | C54: https://jobright.ai/jobs/info/6995dbe7e0bddb6acac44bfd?utm_source=1100&utm_campaign=Software Engineering | D54: On Site | E54: Sunnyvale,CA,US | F54: EBR Systems, Inc. | G54: $87500-$112500 /yr | H54: 51-100 | I54: Biotechnology, Health Care | J54: 1. Bachelor’s degree in Electrical Engineering, Computer Engineering, Embedded Systems, or related field. 2. Entry-level role with up to 2 years of experience (industry or strong academic projects). 3. Exposure to embedded C/C++, microcontrollers, and basic electronics concepts. 4. Curiosity, persistence, and comfort working through ambiguity. 5. Willingness to ask questions and learn from failures. ... | K54: not sure | L54: yes
A55: 46070 | B55: Firmware Validation Engineer I | C55: https://jobright.ai/jobs/info/69954703e0bddb6acac3d437?utm_source=1100&utm_campaign=Software Engineering | D55: On Site | E55: San Francisco, CA | F55: Capgemini Engineering | G55: $54K-$130K /yr | H55: 10000+ | I55: Consulting, Information Services | J55: 1. Bachelor's degree in computer science, software engineering or relevant field required. 2. Experience with embedded systems, RTOS environments, and microcontroller/microprocessor architectures (ARM, PIC, AVR, etc.). 3. Familiarity with test automation frameworks (Python, Robot Framework, Jenkins CI/CD for test execution). 4. Understanding of source control systems (Git), build pipelines, and test documentation standards. 5. Verbal and written communication skills, problem solving skills, customer service and interpersonal skills. ... | K55: not sure
A56: 46070 | B56: OT Data Engineer | C56: https://jobright.ai/jobs/info/69952396e0bddb6acac3ab2a?utm_source=1100&utm_campaign=Software Engineering | D56: Hybrid | E56: Baltimore, MD | F56: American Sugar Refining, Inc. | G56: $62K-$156K /yr | H56: 251-500 | I56: Agriculture, Food and Beverage | J56: 1. Bachelor’s degree in engineering, Computer Science, or related field. 2. Strong interest in manufacturing processes and data analytics. 3. Familiarity with databases (SQL), programming language (Python), analytics tools (Power BI, SSRS). 4. Understanding of data governance concepts is desirable. 5. Excellent problem-solving and communication skills. ... | K56: not sure
A57: 46070 | B57: Associate Machine Learning Engineer | C57: https://jobright.ai/jobs/info/69951b33ce78e77b4fd9328e?utm_source=1100&utm_campaign=Software Engineering | D57: On Site | E57: San Diego, CA, US | F57: XiFin, Inc. | G57: $70000-$100000 /yr | H57: 501-1000 | I57: Enterprise Software, Health Care | J57: 1. Bachelor’s or Master’s degree in Computer Science, Engineering, Data Science, or a related technical field 2. 0–3 years of programming experience in Python (including academic projects, internships, research, or personal projects) 3. Foundational understanding of data structures, algorithms, and software development principles 4. Demonstrated interest in artificial intelligence, automation, and applied machine learning | K57: not sure | L57: yes
A58: 46070 | B58: Full Stack Web Engineer, Palo Alto | C58: https://jobright.ai/jobs/info/6995401281476f6176ad227a?utm_source=1100&utm_campaign=Software Engineering | D58: On Site | E58: Palo Alto, CA | F58: Rhombus | G58: $80K-$110K /yr | H58: 51-100 | I58: Information Technology, Security | J58: 1. 1-3 years building and shipping production web applications 2. At least undergraduate degree in Computer Science, or similar degree 3. Strong frontend engineering skills (React, Next.js, or similar modern frameworks) 4. Solid backend experience (Node.js, Python, or PHP) 5. Deep understanding of HTML, CSS, responsive design, and performance optimization ... | K58: not sure
A59: 46070 | B59: Junior Systems Administrator | C59: https://jobright.ai/jobs/info/6995387bce78e77b4fd953dc?utm_source=1100&utm_campaign=Software Engineering | D59: Hybrid | E59: Washington, DC, US | F59: Urban Land Institute | G59: $55781-$66625 /yr | H59: 51-100 | I59: Association, Real Estate | J59: 1. Working knowledge of Windows 10/11 2. Working knowledge of macOS and iOS 3. Working knowledge of Microsoft 365 applications 4. Working knowledge of Active Directory and Azure Active Directory 5. Experience with ServiceNow or a comparable IT service management platform ... | K59: not sure
A60: 46070 | B60: Developer | C60: https://jobright.ai/jobs/info/699533f4ce78e77b4fd94ea4?utm_source=1100&utm_campaign=Software Engineering | D60: Hybrid | E60: Carpinteria, CA | F60: PlanMember Financial Corporation | G60: $75K-$95K /yr | H60: 51-100 | I60: Financial Services, FinTech | J60: 1. Proficient in UI development with 1-2 years of experience in HTML5/CSS3, Bootstrap or similar UI development framework. 2. 1-2 years of Web development experience in technologies such as PHP, Ruby, ColdFusion or ASP.Net 3. 1-3 years’ experience required with one of the JavaScript framework/libraries. (jQuery, AngularJS, React, Ember, Knockout etc.) 4. Database experience with SQL Server or MySQL. 5. Be comfortable with writing SQL queries. Should be good with SQL optimization using indexes or other optimization techniques. ... | K60: not sure
A61: 46070 | B61: Systems Administrator I | C61: https://jobright.ai/jobs/info/698f9bc66ea51a7610f20112?utm_source=1100&utm_campaign=Software Engineering | D61: On Site | E61: Buffalo, NY | F61: M&T Bank | G61: $23-$39 /hr | H61: 10000+ | J61: 1. Associates degree and a minimum of 1 years' relevant work experience, or in lieu of a degree, a combined minimum of 3 years' higher education and/or work experience, including a minimum of 1 years' relevant work experience 2. Experience working independently or functioning as a member of a team 3. Basic computer skills, including pertinent software 4. Proven analytical skills 5. Proven problem-solving skills ... | K61: not sure
A62: 46070 | B62: Software Engineer Grad | C62: https://jobright.ai/jobs/info/69952fc181476f6176ad0e80?utm_source=1100&utm_campaign=Software Engineering | D62: On Site | E62: Santa Clara, CA | F62: Pure Storage | G62: $119K-$179K /yr | H62: 5001-10000 | I62: Cloud Computing, Data Storage | J62: 1. Strong computer science fundamentals: A solid understanding of data structures, algorithms, concurrency, and design principles. You can apply these concepts to solve practical engineering problems. 2. Proficiency in C++: You're comfortable writing clean, efficient, and well-structured code in C++. 3. Problem-solving aptitude: A proactive and self-motivated approach to identifying and solving complex problems with a focus on delivering high-quality, impactful results. 4. Collaboration and communication skills: The ability to articulate complex technical ideas clearly and work effectively in a team-based, open office environment. | K62: not sure
A63: 46070 | B63: Production Engineer, Global Banking & Markets, FICC Systematic Market Making (SMM) | C63: https://jobright.ai/jobs/info/69955112e0bddb6acac3df17?utm_source=1100&utm_campaign=Software Engineering | D63: On Site | E63: New York, NY | F63: Goldman Sachs | G63: $115K-$180K /yr | H63: 10000+ | I63: Banking, Finance | J63: 1. 1 year or more of relevant work experience 2. Proficiency in one of the following: Python, C, C++, Java, or shell scripting 3. Aptitude for algorithms, data structures, and software design 4. Experience with Linux operating system internals and/or networking concepts 5. Strong analytical skills, with an ability to quickly identify scope and impact of issues during high-pressure situations ... | K63: not sure
A64: 46070 | B64: Full Stack Web Engineer, Palo Alto | C64: https://jobright.ai/jobs/info/69951ba2ce78e77b4fd932ef?utm_source=1100&utm_campaign=Software Engineering | D64: On Site | E64: Palo Alto, CA | F64: Rhombus Power Inc. | G64: $80K-$110K /yr | H64: 51-100 | I64: Artificial Intelligence (AI) | J64: 1. 1-3 years building and shipping production web applications 2. At least undergraduate degree in Computer Science, or similar degree 3. Strong frontend engineering skills (React, Next.js, or similar modern frameworks) 4. Solid backend experience (Node.js, Python, or PHP) 5. Deep understanding of HTML, CSS, responsive design, and performance optimization ... | K64: not sure
A65: 46070 | B65: Network Engineer | C65: https://jobright.ai/jobs/info/69955a8be0bddb6acac3eb0a?utm_source=1100&utm_campaign=Software Engineering | D65: Hybrid | E65: Los Angeles, CA | F65: Santa Monica Seafood | G65: $90K-$100K /yr | H65: 51-100 | I65: Food and Beverage | J65: 1. Ability to work independently. 2. Monitor and maintain LAN/WAN, SD-WAN, WLAN, and VPN infrastructure. 3. Respond to network outages and performance issues. 4. Support network hardware such as switches, routers, firewalls, and wireless access points. 5. Configure and deploy network equipment. ... | K65: not sure | L65: yes
A66: 46070 | B66: Software Engineer, Frontend | C66: https://jobright.ai/jobs/info/6994ea6cce78e77b4fd8fd2b?utm_source=1100&utm_campaign=Software Engineering | D66: On Site | E66: El Segundo, CA | F66: Radiant | G66: $74K-$173K /yr | H66: 101-250 | I66: Clean Energy, Energy | J66: 1. Bachelor's degree in Computer Science, Math, Physics, Engineering, or a related technical field. 2. 1+ Years of professional experience in front-end, full-stack, web development engineering. 3. Proficiency in React and Typescript for front-end development. 4. Strong experience building modern web applications with React, Typescript, and Vite as a stack. 5. Familiar with Nginx and Docker. ... | K66: not sure
A67: 46070 | B67: Full Stack Web Engineer, Palo Alto | C67: https://jobright.ai/jobs/info/69952098e0bddb6acac3a84b?utm_source=1100&utm_campaign=Software Engineering | D67: On Site | E67: Palo Alto, California, United States | F67: Rhombus Power Inc. | G67: $80000-$110000 /yr | H67: 51-100 | I67: Artificial Intelligence (AI) | J67: 1. 1-3 years building and shipping production web applications 2. At least undergraduate degree in Computer Science, or similar degree 3. Strong frontend engineering skills (React, Next.js, or similar modern frameworks) 4. Solid backend experience (Node.js, Python, or PHP) 5. Deep understanding of HTML, CSS, responsive design, and performance optimization ... | K67: not sure
A68: 46070 | B68: Software Engineer Grad | C68: https://jobright.ai/jobs/info/69952cd4e0bddb6acac3b489?utm_source=1100&utm_campaign=Software Engineering | D68: On Site | E68: Santa Clara, California | F68: Pure Storage | G68: $119,000-$179,000 /yr | H68: 5001-10000 | I68: Cloud Computing, Data Storage | J68: 1. Strong computer science fundamentals: A solid understanding of data structures, algorithms, concurrency, and design principles. You can apply these concepts to solve practical engineering problems. 2. Proficiency in C++: You're comfortable writing clean, efficient, and well-structured code in C++. 3. Problem-solving aptitude: A proactive and self-motivated approach to identifying and solving complex problems with a focus on delivering high-quality, impactful results. 4. Collaboration and communication skills: The ability to articulate complex technical ideas clearly and work effectively in a team-based, open office environment. | K68: not sure
A69: 46070 | B69: Post-Doctoral Associate | C69: https://jobright.ai/jobs/info/6994fb7e81476f6176acd5bc?utm_source=1100&utm_campaign=Software Engineering | D69: On Site | E69: Athens, GA | F69: The University of Georgia | G69: $47K-$56K /yr | H69: 10000+ | I69: Artificial Intelligence (AI), Information Technology | J69: 1. Pharm.D. or Ph.D. in Pharmaceutical Sciences, or a related discipline. 2. Extensive experience with clinical datasets and managing and analyzing big data repositories. 3. Competent with foundational principles in biostatics and at least one coding language (e.g., R, python, SAS, C++). 4. Excellent scientific writing ability and oral communication skills. 5. Have a growth mindset, enjoy working in a team, and be highly motivated to publish high-impact work. | K69: not sure
A70: 46070 | B70: Firmware Engineer | C70: https://jobright.ai/jobs/info/699504ece0bddb6acac38c3d?utm_source=1100&utm_campaign=Software Engineering | D70: On Site | E70: 1020 Stewart Drive, Sunnyvale, CA, 94085, US | F70: II-VI Aerospace & Defense | G70: $70,750-$115,875 /yr | H70: 251-500 | I70: Aerospace, Apps | J70: 1. Carry out firmware design under the guidance of senior members of the design team. 2. Use C++ to write firmware on ST MCUs. 3. Develop GUI for firmware testing using Python or other programming languages. 4. Utilize instruments like logic analyzer and oscilloscope for troubleshooting. 5. Collaborate with other team members on circuit design support. ... | K70: not sure
A71: 46070 | B71: Database Administrator | C71: https://jobright.ai/jobs/info/699666b2e0bddb6acac4dbd1?utm_source=1100&utm_campaign=Software Engineering | D71: Hybrid | E71: Sacramento, CA | F71: California Franchise Tax Board | G71: $6513-$10537 /mon | H71: 5001-10000 | I71: Government, Non Profit | J71: 1. Experience with Microsoft SQL Server Administration 2. Experience in Database Administration on Windows environment 3. Experience in scripting languages such as PowerShell, C#, Java, JavaScript, BASH, Perl, or Python etc. 4. Experience with Performance Tuning, Troubleshooting, Installing, and Configuration of Databases 5. Experience with Database Clusters, Database Migrations, Database Backup, Restore and Disaster Recovery ... | K71: not sure
A72: 46070 | B72: IT Systems Engineer | C72: https://jobright.ai/jobs/info/699522fece78e77b4fd93abe?utm_source=1100&utm_campaign=Software Engineering | D72: Remote | E72: San Francisco (Remote) | F72: You.com | G72: $150,000-$200,000 /yr | H72: 51-100 | I72: Artificial Intelligence (AI), Chatbot | J72: 1. Bachelor’s degree in Information Technology, Computer Science, or a related field (or equivalent practical experience). 2. Relevant certifications such as CompTIA A+, Google IT Support Professional Certificate, or AWS Cloud Practitioner are valued. 3. 0–2 years of professional IT support experience. 4. Demonstrable Python and Bash scripting ability (personal projects, coursework, or professional experience). 5. Familiarity with Git/GitHub workflows. ... | K72: not sure | L72: yes
A73: 46070 | B73: Postdoctoral Fellow, Kelley Lab - Gene Regulation Machine Learning | C73: https://jobright.ai/jobs/info/69952f94e0bddb6acac3b78d?utm_source=1100&utm_campaign=Software Engineering | D73: On Site | E73: South San Francisco, CA | F73: Calico Life Sciences | G73: $95000-$95000 /yr | H73: 251-500 | J73: 1. Must have recently completed a PhD degree in a relevant scientific or computational field 2. Current PhD student applicants should be within 12 months of completing their PhD 3. Applicants who have already graduated must have completed their PhD within the past 3 years and not have been employed as a postdoc at more than one other lab/company since graduation 4. Must have made important contributions to science in their area, ideally demonstrated by having had a meaningful first author paper accepted for publication 5. While specific technical skills are project-dependent, proficiency in core scientific methodologies, analytical skills, and quantitative problem-solving is essential ... | K73: not sure
A74: 46070 | B74: Security Operations Center (SOC) Analyst | C74: https://jobright.ai/jobs/info/69965767ce78e77b4fda5ccf?utm_source=1100&utm_campaign=Software Engineering | D74: Hybrid | E74: Hawaii | F74: RapDev | G74: $110000-$150000 /yr | H74: 101-250 | I74: Cloud Computing, Consulting | J74: 1. Bachelor's degree or equivalent experience in Cyber Security or related field 2. SIEM experience with Splunk, SumoLogic, Datadog, or similar. 3. Experience with security monitoring, incident response, and threat analysis 4. Experience with Cloud Native Technologies 5. Excellent problem-solving and analytical skills ... | K74: not sure
A75: 46070 | B75: Security Operations Center (SOC) Analyst | C75: https://jobright.ai/jobs/info/699657db81476f6176ae22a2?utm_source=1100&utm_campaign=Software Engineering | D75: Hybrid | E75: USA | F75: RapDev | G75: $70000-$125000 /yr | H75: 101-250 | I75: Cloud Computing, Consulting | J75: 1. Bachelor's degree or equivalent experience in Cyber Security or related field 2. SIEM experience with Splunk, SumoLogic, Datadog, or similar 3. Experience with security monitoring, incident response, and threat analysis 4. Experience with Cloud Native Technologies 5. Excellent problem-solving and analytical skills ... | K75: not sure
A76: 46070 | B76: Firmware Engineer | C76: https://jobright.ai/jobs/info/6994fb40e0bddb6acac3806c?utm_source=1100&utm_campaign=Software Engineering | D76: On Site | E76: 1020 Stewart Drive, Sunnyvale, CA, 94085, US | F76: Coherent Corp. | G76: $70750-$115875 /yr | H76: 5001-10000 | J76: 1. BS or MS in Electrical Engineering or related technical fields. 2. Solid foundation in digital circuit design. 3. Deep understanding of MCUs. 4. Ability to work with little supervision and to manage assigned tasks effectively. 5. Ability to learn and apply new technologies and tools to develop innovative solutions. ... | K76: not sure
A77: 46070 | B77: Back End Engineer | C77: https://jobright.ai/jobs/info/69965310e0bddb6acac4c17c?utm_source=1100&utm_campaign=Software Engineering | D77: Remote | E77: US, Remote | F77: Horizon3.ai | G77: $130000-$190000 /yr | H77: 251-500 | I77: Artificial Intelligence (AI), Cyber Security | J77: 1. Bachelor’s degree in Computer Science, Computer Engineering, or a related field, or equivalent practical experience. 2. 1–4 years of professional software engineering experience. 3. Experience building backend services using at least one modern language, such as Python, Go, Java, TypeScript, or similar. 4. Experience working with SQL and at least one relational database in production. 5. Experience building backend services on a cloud platform (AWS, GCP, or Azure), and familiarity with Docker and containerized applications. | K77: not sure
A78: 46070 | B78: GSOC Operator | C78: https://jobright.ai/jobs/info/69951220e0bddb6acac39ba0?utm_source=1100&utm_campaign=Software Engineering | D78: Remote | E78: Provo, UT | F78: Cobalt AI | G78: $16.50-$16.50 /hr | H78: 101-250 | J78: 1. Ability to monitor alarms and respond to security incidents. 2. Experience in managing and updating credentials in Credential Management systems. 3. Ability to provide remote access support to authorized personnel. 4. Excellent customer service skills for inbound phone call management. 5. Ability to manage alerts and notifications through an Intelligence platform. ... | K78: not sure
A79: 46070 | B79: Software Engineer | C79: https://jobright.ai/jobs/info/6995237b81476f6176ad00ff?utm_source=1100&utm_campaign=Software Engineering | D79: On Site | E79: Ripon, WI | F79: Accurate Controls, Inc. | G79: $55K-$65K /yr | H79: 51-100 | I79: 3D Printing, Cyber Security | J79: 1. Proven experience in software development with proficiency in multiple programming languages such as Java, C#, C++, Python, VBA, or JavaScript. 2. Strong understanding of web development frameworks including React, Express, Ruby on Rails, and RESTful API design principles. 3. Hands-on experience working with cloud platforms like AWS or Azure for deployment and infrastructure management. 4. Familiarity with IT infrastructure, Linux environments, version control systems (GitHub, SVN), and application deployment pipelines. 5. Knowledge of database systems such as MySQL or SQL Server for data modeling and query optimization. ... | K79: not sure
A80: 46070 | B80: Quantitative Developer | C80: https://jobright.ai/jobs/info/699513b9ce78e77b4fd92c06?utm_source=1100&utm_campaign=Software Engineering | D80: Hybrid | E80: Boston, MA | F80: Arrowstreet Capital, Limited Partnership | G80: $155K-$260K /yr | H80: 251-500 | I80: Financial Services, Venture Capital | J80: 1. An undergraduate or graduate degree from an educational institution in computer science with a quantitative application such as mathematics and/or finance, or vice versa – a quantitative degree with a computer science application 2. 1 - 3 years of relevant experience required 3. Demonstrated professional or academic success 4. Strong analytical, quantitative, and problem-solving skills 5. Experience implementing production-grade Python code for a data analytic business, preferably in investment management ... | K80: not sure
A81: 46070 | B81: Associate Game Designer (Technical) (Contingent) | C81: https://jobright.ai/jobs/info/6994e4e6ce78e77b4fd8f60f?utm_source=1100&utm_campaign=Software Engineering | D81: Hybrid | E81: Multi Location United States, Santa Monica, CA Santa Monica, CA | F81: Sony Interactive Entertainment | G81: $37-$50 /hr | H81: 10000+ | I81: Consumer Goods, Music | J81: 1. Significant programming ability (Computer Science undergraduate degree preferred) 2. Knowledge of 3D math 3. Experience with C++, C#, Lua, or other scripting language 4. Broad understanding of gaming landscape 5. Self-starter with excellent communication and teamwork skills ... | K81: not sure
A82: 46070 | B82: Junior Software Engineer | C82: https://jobright.ai/jobs/info/6995104cce78e77b4fd927fe?utm_source=1100&utm_campaign=Software Engineering | D82: On Site | E82: Ripon, WI | F82: Accurate Controls, Inc. | G82: $40K-$55K /yr | H82: 51-100 | I82: 3D Printing, Cyber Security | J82: 1. Develop and support programs in Python, TypeScript, C, C++, C# and other programming languages for use on existing and active projects. 2. Develop front-end user interfaces with HTML, CSS, JavaScript, PHP, and C#. 3. Perform coding, debugging, testing, and troubleshooting throughout the application development process. 4. Provide ongoing maintenance, support, and enhancements in existing systems and platforms. 5. Work alongside other engineers on the team to evaluate technology and apply best case solutions. ... | K82: not sure
A83: 46070 | B83: Epicor IT Specialist | C83: https://jobright.ai/jobs/info/6994ee77e0bddb6acac3706c?utm_source=1100&utm_campaign=Software Engineering | D83: On Site | E83: Springfield, MO | F83: Springfield Sign | G83: $65K-$125K /yr | H83: 101-250 | I83: Digital Signage, Graphic Design | J83: 1. Extensive experience with Epicor ERP system configuration, customization, and deployment. 2. Strong understanding of service-oriented architecture (SOA), solution architecture, and system design principles. 3. Proficiency in database management systems such as SQL Server, PostgreSQL, MySQL; familiarity with NoSQL databases is a plus. 4. Hands-on knowledge of IT infrastructure components including operating systems (Windows/Linux), virtualization (VMware/ESXi), cloud platforms (AWS/Azure), and networking fundamentals (DNS, DHCP, VPNs). 5. Expertise in web services development using RESTful APIs and SOAP; experience integrating third-party solutions like Salesforce or Pegasystems is highly desirable. ... | K83: not sure
A84: 46070 | B84: Full Stack Developer | C84: https://jobright.ai/jobs/info/699512dce0bddb6acac39c89?utm_source=1100&utm_campaign=Software Engineering | D84: Hybrid | E84: Multi Location Phoenix, AZ Phoenix, AZ (Hybrid) | F84: Maricopa County | G84: $62000-$119000 /yr | H84: 10000+ | I84: Association, Government | J84: 1. One year of relevant work experience, performing the duties and responsibilities of the role 2. Bachelor's degree from an accredited college or university in Computer Science, Information Technology, or related field 3. A combination of post-secondary education and/or job-related experience may substitute for the minimum qualifications on a year-for-year basis. | K84: not sure
A85: 46070 | B85: Global Currency and Emerging Markets (GCEM) - Software Engineer - New York - GBM Public | C85: https://jobright.ai/jobs/info/6994f8ace0bddb6acac37d8b?utm_source=1100&utm_campaign=Software Engineering | D85: On Site | E85: Multi Location New York, NY New York, New York, United States | F85: Goldman Sachs | G85: $115000-$180000 /yr | H85: 10000+ | I85: Banking, Finance | J85: 1. Strong analytical skills and a passion for problem solving. 2. Strong programming skills in OO languages such as Java or Python. 3. Ability to quickly learn new languages and technologies. 4. Strong background in computer science, mathematics, and/or a related field. 5. Comfort with multi-tasking and is self-motivated. ... | K85: not sure
A86: 46070 | B86: Global Currency and Emerging Markets (GCEM) - Software Engineer - New York - GBM Public | C86: https://jobright.ai/jobs/info/6994e71581476f6176acbcb1?utm_source=1100&utm_campaign=Software Engineering | D86: On Site | E86: New York, NY | F86: Goldman Sachs | G86: $115K-$180K /yr | H86: 10000+ | I86: Banking, Finance | J86: 1. Strong analytical skills and a passion for problem solving. 2. Strong programming skills in OO languages such as Java or Python. 3. Ability to quickly learn new languages and technologies. 4. Strong background in computer science, mathematics, and/or a related field. 5. Comfort with multi-tasking and is self-motivated. ... | K86: not sure
A87: 46070 | B87: Wavelogic Firmware Developer - New Grad | C87: https://jobright.ai/jobs/info/6940937baa598a08c3f03f56?utm_source=1100&utm_campaign=Software Engineering | D87: On Site | E87: Atlanta, GA | F87: Ciena | G87: $69K-$110K /yr | H87: 5001-10000 | I87: Collaboration, Delivery | J87: 1. Bachelor’s degree in Electrical or Computer Engineering. 2. Proficiency in the C programming language. 3. Working knowledge of embedded systems, including drivers, mutual exclusion, synchronization, interrupt handling, and inter-process communication. 4. Understanding of coherent optics, optical and electrical communication techniques. | K87: not sure | L87: yes
A88: 46070 | B88: Systems Programmer I | C88: https://jobright.ai/jobs/info/6994d072ce78e77b4fd8de83?utm_source=1100&utm_campaign=Software Engineering | D88: Hybrid | E88: Saint Charles, IL | F88: OSG Corporation | G88: $56K-$73K /yr | H88: 5001-10000 | I88: Manufacturing | J88: 1. HS Diploma/GED or equivalent 2. Experience computer programming in X++, C#, and/or SQL 3. Experience with Microsoft Office Products 4. Excellent problem-solving and analytical skills 5. Basic knowledge of database management, SQL, and data modeling | K88: not sure
A89: 46070 | B89: Application Programmer | C89: https://jobright.ai/jobs/info/6994f3aa81476f6176acce99?utm_source=1100&utm_campaign=Software Engineering | D89: On Site | E89: Malta, IL | F89: Kishwaukee College | G89: $58K-$66K /yr | H89: 251-500 | J89: 1. Demonstrate clear and effective written and verbal communication skills. 2. Demonstrate strong customer service and interpersonal skills. 3. Possess strong organizational and time management skills. 4. Ability to work independently as well as cooperatively in groups. 5. Experience with Windows and Linux Server Operating Systems. ... | K89: not sure
A90: 46070 | B90: Platform Control Software Engineer | C90: https://jobright.ai/jobs/info/6994f6ed81476f6176accf60?utm_source=1100&utm_campaign=Software Engineering | D90: On Site | E90: Clarksburg, MD | F90: Forterra | G90: $115000-$155000 /yr | H90: 251-500 | J90: 1. Minimum of 1-2 years of experience in control systems engineering. 2. Strong background in control theory and control systems design. 3. Proficiency in programming languages such as C++ 4. Experience with vehicle dynamics and actuation systems. | K90: not sure
A91: 46070 | B91: Junior Full Stack Software Engineer | C91: https://jobright.ai/jobs/info/6994d5c9e0bddb6acac35277?utm_source=1100&utm_campaign=Software Engineering | D91: Remote | E91: Maine, United States | F91: WEX | G91: $75K-$95K /yr | H91: 5001-10000 | I91: Financial Services, FinTech | J91: 1. Experience with C# .NET 2. Experience building microservices 3. Experience with AWS and Azure or equivalent cloud technologies 4. Experience with REST or GraphQL microservices, performance profiling, and tuning tools 5. Experience with Linux/Unix ... | K91: not sure
A92: 46070 | B92: Agentic AI Engineer in Test | C92: https://jobright.ai/jobs/info/699501d881476f6176acde66?utm_source=1100&utm_campaign=Software Engineering | D92: On Site | E92: Miami Coconut Grove Corp | F92: Santander | G92: $44250-$86000 /yr | H92: 10000+ | I92: Banking, Commercial Lending | J92: 1. Bachelor's Degree or equivalent work experience: Computer Science, Software Engineering or equivalent field. 2. 0+ Years Experience with test strategies, test plans, and test cases. 3. Experience in writing SQLs to query the backend during the test execution. 4. Expertise in testing web based applications and web services based systems with minimal to no user interface. 5. Experience building test automation frameworks for AI/ML or distributed systems. ... | K92: not sure | L92: yes
A93: 46070 | B93: Associate Quality Engineer | C93: https://jobright.ai/jobs/info/6994efec81476f6176acc902?utm_source=1100&utm_campaign=Software Engineering | D93: On Site | E93: Troy, NY | F93: WB Games New York | G93: $56K-$104K /yr | H93: 11-50 | I93: Information Technology, Online Games | J93: 1. Ability to write clear and concise bug reports that conform to the established bug writing standards of WB Games NY. 2. Able to read and write software in Python or some other general purpose programming language. 3. Experience running commands from a CLI (Command Line Interface). 4. Experience using and interacting with a REST API, and other web-based technologies. 5. Ability to identify bugs, duplicate them, perform additional research, and track the bug lifecycle. ... | K93: not sure
A94: 46070 | B94: DevOps Build Engineer | C94: https://jobright.ai/jobs/info/6994dfc9ce78e77b4fd8ef78?utm_source=1100&utm_campaign=Software Engineering | D94: Remote | E94: United States | F94: SAI360 | G94: €2166-€2400 /mon | H94: 501-1000 | I94: Information Services, Information Technology | J94: 1. Strong experience with Maven (configurations, multi module projects, dependency management) 2. Good understanding of the Java ecosystem (libraries, frameworks, runtimes, compatibility constraints) 3. Experience upgrading and maintaining components such as Tomcat, application servers, or containerised runtimes 4. Familiarity with CI/CD pipelines (e.g., Jenkins, GitLab CI, GitHub Actions, Azure DevOps) 5. Ability to write, maintain, and debug integration tests (JUnit, REST Assured, or similar) ... | K94: not sure
A95: 46070 | B95: Network System Administrator- Tier 2 | C95: https://jobright.ai/jobs/info/6994da68e0bddb6acac35823?utm_source=1100&utm_campaign=Software Engineering | D95: Hybrid | E95: Rockville, MD | F95: OSIbeyond | G95: $66K-$74K /yr | H95: 11-50 | I95: Cloud Computing, Consulting | J95: 1. 1+ year experience as T2 Helpdesk Support 2. CompTIA A+ 3. CompTIA Network+ 4. CompTIA Security+ 5. MD-102: Microsoft 365 Certified: Endpoint Administrator Associate ... | K95: not sure
A96: 46070 | B96: Machine Learning Engineer | C96: https://jobright.ai/jobs/info/6994e497ce78e77b4fd8f5ab?utm_source=1100&utm_campaign=Software Engineering | D96: Hybrid | E96: Multi Location Austin, TX Chicago, IL | F96: PayPal | G96: $118K-$174K /yr | H96: 10000+ | I96: E-Commerce Platforms, FinTech | J96: 1. 1+ years relevant experience and a Bachelor’s degree OR Any equivalent combination of education and experience. 2. Familiarity with ML frameworks like TensorFlow or scikit-learn. 3. Strong analytical and problem-solving skills. | K96: not sure
A97: 46070 | B97: Associate QA Engineer | C97: https://jobright.ai/jobs/info/6994992081476f6176ac5e36?utm_source=1100&utm_campaign=Software Engineering | D97: Remote | E97: United States | F97: Funnel Leasing | G97: $70K-$90K /yr | H97: 101-250 | I97: Cloud Data Services, Marketing | J97: 1. Bachelor's degree or other relevant technical training or experience 2. Ability to collaborate with and communicate effectively to teams having both a technical and non-technical audience 3. Experience in QA or software development, or relevant work experience (customer support, product management, user research, business analytics, etc) 4. Familiarity in being able to test software and write automated tests (eg, Playwright) 5. Ability to read requirements for a product and create a plan for testing those requirements ... | K97: not sure
A98: 46070 | B98: SDET | C98: https://jobright.ai/jobs/info/6977e54a52f3c27ec6440e37?utm_source=1100&utm_campaign=Software Engineering | D98: Hybrid | E98: Greater Chicago Area | F98: RAPP | G98: $81K-$97K /yr | H98: 5001-10000 | I98: Advertising, Marketing | J98: 1. Bachelor’s degree in computer science, ML Engineering, or related field. 2. 0–3 years in software testing or development with exposure to automation. 3. Proficiency in Python or JavaScript. 4. Familiarity with Playwright or Cypress. 5. Basic understanding of unit testing frameworks such as PyTest, Mocha, or Jest. ... | K98: not sure | L98: yes
A99: 46070 | B99: Testing Specialist | C99: https://jobright.ai/jobs/info/6917aac015b415636717a430?utm_source=1100&utm_campaign=Software Engineering | D99: On Site | E99: Greater Chicago Area | F99: Trustmark | G99: $24-$36 /hr | H99: 1001-5000 | I99: Fitness, Health Care | J99: 1. Two-year college or technical degree 2. Minimum 1 year testing experience 3. Technical aptitude 4. Proficient with MS Office suite 5. Experience with using tools to query data, creating and formatting files and forms ... | K99: not sure
A100: 46070 | B100: Software Engineer | C100: https://jobright.ai/jobs/info/6994c6d7e0bddb6acac340ae?utm_source=1100&utm_campaign=Software Engineering | D100: On Site | E100: SD, Sioux Falls | F100: Sanford Health | G100: $32.50-$52 /hr | H100: 10000+ | I100: Children, Education | J100: 1. Bachelor's Degree in a computer-related field required. 2. Basic knowledge of computer principles and techniques necessary to develop and document software applications systems. 3. Basic knowledge of relational databases. 4. Basic knowledge of Object Oriented programming. 5. Basic knowledge of ASP.NET. ... | K100: not sure
A101: 46070 | B101: System Administrator, Distribution | C101: https://jobright.ai/jobs/info/6994d00081476f6176aca139?utm_source=1100&utm_campaign=Software Engineering | D101: Hybrid | E101: Issaquah, WA | F101: SanMar | G101: $80K-$105K /yr | H101: 1001-5000 | I101: Apparel, Fashion | J101: 1. Bachelor's Degree in IT/computer science or Supply Chain or equivalent experience 2. 1-3 years experience supporting technology-based distribution systems including Körber (HighJump)/WMS software, Voice and RF WMS equipment or other point-of-pick hardware, ProShip/Parcel management software, Label generation tools such as Bartender or Minisoft, Conveyor hardware/software interfaces, or equivalent industry solutions 3. Working knowledge of Windows Server administration 4. Knowledge of integration, middleware, and/or messaging topologies 5. Understanding of network technologies such as load balancing, network/socket communication ... | K101: not sure
A102: 46070 | B102: Associate Quality Engineer | C102: https://jobright.ai/jobs/info/6994c1f5e0bddb6acac33711?utm_source=1100&utm_campaign=Software Engineering | D102: Hybrid | E102: NY Troy 5 3rd Street | F102: Warner Bros. Discovery | G102: $56,012-$104,023 /yr | H102: 10000+ | I102: Advertising, Broadcasting | J102: 1. Ability to write clear and concise bug reports that conform to the established bug writing standards of WB Games NY. 2. Able to read and write software in Python or some other general purpose programming language. 3. Experience running commands from a CLI (Command Line Interface). 4. Experience using and interacting with a REST API, and other web-based technologies. 5. Ability to identify bugs, duplicate them, perform additional research, and track the bug lifecycle. ... | K102: not sure
A103: 46070 | B103: Software Engineer, I - Mobile (iOS) | C103: https://jobright.ai/jobs/info/698b93c50f6f7e7a2ce70a99?utm_source=1100&utm_campaign=Software Engineering | D103: Remote | E103: United States | F103: Coursera | G103: $110000-$140000 /yr | H103: 1001-5000 | I103: EdTech, Education | J103: 1. Experience building iOS applications using Swift, including some experience with SwiftUI (professional experience, internships, or substantial project work). 2. Familiarity with core iOS concepts in Swift and SwiftUI. 3. Exposure to working with APIs. 4. Basic understanding of Git-based workflows and collaborative development. 5. Ability to work effectively on well-defined problems with guidance and support. ... | K103: not sure
A104: 46070 | B104: Flight Test Operator - Device Platform | C104: https://jobright.ai/jobs/info/6940a54850bbaf765052aec4?utm_source=1100&utm_campaign=Software Engineering | D104: On Site | E104: San Mateo, CA | F104: Skydio | G104: $90K-$110K /yr | H104: 501-1000 | I104: Artificial Intelligence (AI), Drone Management | J104: 1. Background in human factors, mobile UI/UX validation or design, flight testing, and/or real-world system testing 2. Strong debugging and troubleshooting skills across mobile, embedded, and networked systems 3. Experience with UAS operations and high-reliability operator workflows 4. Understanding of human factors, usability engineering, and cognitive workload 5. Strong documentation and technical communication skills ... | K104: not sure
A105: 46070 | B105: Software Engineer, C++ (New Grad Summer 2026) | C105: https://jobright.ai/jobs/info/69532d10f1f8465b79ea7f29?utm_source=1100&utm_campaign=Software Engineering | D105: On Site | E105: Los Angeles, CA | F105: Freeform | G105: $115K-$125K /yr | H105: 11-50 | I105: 3D Technology, Electronics | J105: 1. Bachelor's degree in computer science or computer engineering from an ABET accredited university or college 2. Internship or engineering club experience such as FSAE, Baja SAE, solar car, rocket club, robotics club, hackathons, or similar programming with C/C++ | K105: not sure | L105: yes
A106: 46070 | B106: Autonomy Software Engineer | C106: https://jobright.ai/jobs/info/6940ada3aa598a08c3f04efd?utm_source=1100&utm_campaign=Software Engineering | D106: Hybrid | E106: San Mateo, CA | F106: Skydio | G106: $147K-$210K /yr | H106: 501-1000 | I106: Artificial Intelligence (AI), Drone Management | J106: 1. 1+ years of experience writing production level code for autonomous robots, preferably flying robots with a high level of proficiency in C++ and Python 2. Practical experience implementing state of the art algorithms in a robotics-adjacent area including computer vision, state estimation, motion planning, controls, sensor characterization and integration, UAS software and hardware development 3. Highly curious, creative, and able to communicate concepts to non-technical audiences 4. Strong software engineering fundamentals and a commitment to writing clean, well-designed, maintainable, readable code 5. Excited to use robotics to make the world safer, more productive, and more creative | K106: not sure
A107: 46070 | B107: Machine Learning Scientist I/II, Decision Making for Physical Sciences | C107: https://jobright.ai/jobs/info/69827024348f733a5c3549fd?utm_source=1100&utm_campaign=Software Engineering | D107: On Site | E107: Cambridge, MA USA | F107: Lila Sciences | G107: $176000-$304000 /yr | H107: 101-250 | I107: Artificial Intelligence (AI), Foundational AI | J107: 1. Advanced degree (PhD or MS with equivalent research/industry experience) in Computer Science, Applied Math/Statistics, Physics, Materials Science, Chemical Engineering, or related field. 2. Strong foundation in sequential decision‑making: Bayesian Optimization, active learning, contextual bandits, model‑based RL, or Bayesian experimental design. 3. Proficiency in Python and modern ML tooling (e.g., PyTorch/JAX; BoTorch/GPyTorch/Ax or similar); strong software engineering practices. | K107: not sure
A108: 46070 | B108: Software Engineer I | C108: https://jobright.ai/jobs/info/695cc73bf1f8465b79f2eee4?utm_source=1100&utm_campaign=Software Engineering | D108: On Site | E108: Multi Location San Francisco, CA Seattle, WA | F108: Twitch | G108: $110,500-$160,000 /yr | H108: 1001-5000 | I108: Gaming, Media and Entertainment | J108: 1. 0-2 years of professional software development experience 2. Excellent verbal and written communication skills; Ability to effectively collaborate with teammates is critical to success. 3. A track record of building consumer-facing products that users love 4. Demonstrable experience of modern programming languages and frameworks 5. Sharp problem-solving skills with a focus on algorithms, data structures, and schema design ... | K108: not sure | L108: yes
A109: 46070 | B109: Software Engineer, Full Stack | C109: https://jobright.ai/jobs/info/6906b43363502c0aded82a7e?utm_source=1100&utm_campaign=Software Engineering | D109: Hybrid | E109: Multi Location San Francisco, CA New York, NY United States | F109: Figma | G109: $149K-$350K /yr | H109: 1001-5000 | I109: Collaboration, Developer Tools | J109: 1. Proven experience in shipping and maintaining full-stack applications in production 2. Strong proficiency in modern front-end frameworks (e.g., React/TypeScript) and back-end technologies (e.g., Ruby, Python, Go, C++, PostgreSQL) 3. A product mindset, with the ability to translate user needs into scalable technical solutions 4. Excellent collaboration and communication skills, with experience working effectively across cross-functional teams 5. Passion for engineering craft and building polished, maintainable, and scalable systems | K109: not sure
A110: 46070 | B110: AI Engineer | C110: https://jobright.ai/jobs/info/698bc9470f6f7e7a2ce73f66?utm_source=1100&utm_campaign=Software Engineering | D110: Hybrid | E110: New York, United States | F110: Lazard | G110: $110K-$140K /yr | H110: 1001-5000 | I110: Advice, Asset Management | J110: 1. Bachelor’s or advanced degree in Computer Science, AI, Data Science, Machine Learning, or related fields. 2. 1-3 years of experience developing large scale GenAI applications 3. Expertise in Python and frameworks such as TensorFlow, PyTorch, and scikit-learn. 4. Deep knowledge of machine learning algorithms and experience in productionizing AI models. 5. Proficiency with frameworks for large language models (LLMs) such as LangChain, LlamaIndex, and VectorDBs. ... | K110: not sure
A111: 46070 | B111: Software Engineer - Automation Tools and Infrastructure | C111: https://jobright.ai/jobs/info/69252701d47de4798eccd7d9?utm_source=1100&utm_campaign=Software Engineering | D111: Hybrid | E111: Foster City, CA | F111: Zoox | G111: $141K-$188K /yr | H111: 1001-5000 | I111: Artificial Intelligence (AI), Autonomous Vehicles | J111: 1. BS in relevant engineering discipline and 1+ years of relevant work experience 2. HIL and/or SIL Test Frameworks 3. Object-oriented programming experience (Python or C++ preferred) 4. Experience building cross-platform software with source control (Git) 5. Strong interpersonal and communication skills | K111: not sure
A112: 46070 | B112: Platform Engineer - Anaplan | C112: https://jobright.ai/jobs/info/695c27a222c9dc0d3d540859?utm_source=1100&utm_campaign=Software Engineering | D112: Hybrid | E112: Newark, NJ | F112: Prudential Financial | G112: $85K-$126K /yr | H112: 10000+ | I112: Asset Management, Finance | J112: 1. Bachelor of Computer Science or Engineering or experience in related fields 2. Diverse ideas, experiences, thoughts and perspectives to the benefit of the organization 3. Experience with agile development methodologies and Test-Driven Development (TDD) 4. Knowledge of business concepts tools and processes that are needed for making sound decisions in the context of the company's business 5. Ability to learn new skills and knowledge on an on-going basis through self-initiative and tackling challenges ... | K112: not sure
A113: 46070 | B113: Assistant Systems Administrator | C113: https://jobright.ai/jobs/info/698f17a26ea51a7610f1407d?utm_source=1100&utm_campaign=Software Engineering | D113: On Site | E113: Culver, IN | F113: Culver Academies | G113: $24-$26 /hr | H113: 251-500 | I113: Education, Primary Education | J113: 1. Associate’s degree in Information Technology or related field 2. at least one technical certification (e.g., CompTIA Network+, Security+, Microsoft Certified Fundamentals) or equivalent experience 3. strong analytical and problem-solving skills 4. ability to work independently 5. familiarity with Windows Server, Active Directory, and Microsoft 365 environments ... | K113: not sure
A114: 46070 | B114: Entry-Level Python Engineer [32868] | C114: https://jobright.ai/jobs/info/69944c83ce78e77b4fd83d08?utm_source=1100&utm_campaign=Software Engineering | D114: Remote | E114: Boston, MA | F114: Stealth Startup | G114: $150000-$150000 /yr | H114: 101-250 | J114: 1. Bachelor’s degree in Computer Science, Engineering, or related field (or equivalent experience) 2. Solid understanding of Python fundamentals 3. Knowledge of data structures, algorithms, and OOP concepts 4. Familiarity with Git and basic development workflows 5. Strong problem-solving skills and eagerness to learn | K114: not sure
...

Sheet Archive Referral List
A1: Count | B1: Company Name | C1: Request Log | D1: Request Date | E1: Updated Date | F1: Request Link | G1: Referral Received | H1: Comment | I1: Message Ready | J1: Resume Ready
A2: 1 | B2: Snapchat | C2: Snapchat - Software Engineer Machine Learning - H126SWEMLI2 | D2: 46071 | F2: https://wd1.myworkdaysite.com/en-US/recruiting/snapchat/snap/job/Software-Engineer--ML-Infrastructure--Level-4_H126SWEMLI2-1 | G2: Reject | H2: Ananya: Mostly i was 2 weeks late for the position
A3: 2 | B3: Snapchat | C3: Snapchat - Software Engineer Backend - Q126SWEB2 | D3: 46071 | G3: Applied | H3: sai
A4: 3 | B4: Snowflake | C4: Snoflake - Software Engineer - ASHREQ-5421 | D4: 46071 | F4: https://careers.snowflake.com/us/en/job/SNCOUS7791AB6A66D34A20BCE877FFC470EA41EXTERNALENUS5F4AE8D3BF84430D8F9F325F14DDF947/Software-Engineer-APG?utm_source=Q2P9NP2NNP&utm_medium=phenom-feeds&gh_src=ed5543a62 | G4: Requested
A5: 4 | B5: Stripe | C5: Stripe - Software Engineering - New Grad | D5: 46071 | F5: https://stripe.com/jobs/listing/software-engineer-new-grad/7210112?gh_src=73vnei | G5: Requested
A6: 5 | B6: Google | C6: Google - Software Engineering II | D6: 46069 | G6: Applied
A7: 6 | B7: Amazon | C7: Amazon SDE | D7: 46069 | G7: Applied | H7: Meet*2
A8: 7 | B8: Amazon | C8: Amazon Software Engineering | D8: 46069 | G8: Applied | H8: Sradha
A9: 8 | B9: Cisco | C9: Cisco - 2007003 Software Engineer 1 | D9: 46068 | G9: Applied | H9: Aman Jain
A10: 9 | B10: Bounteous | C10: Software Engineering | D10: 46068 | G10: Applied | H10: Ankit Jain
A11: 10 | B11: Microsoft | C11: Software Engineering | D11: 46073 | G11: Requested | H11: Desi Runner Community he said he will reply today a k a 21st of feb
A12: 11 | B12: Gold Man Sach | C12: Software Engineering | D12: 46073 | G12: Applied | H12: Sai
A13: 12 | B13: Amazon | C13: Software Development Engineer | D13: 46073 | F13: https://www.amazon.jobs/en/jobs/3185058/software-development-engineer?cmpid=SPLICX0248M&utm_source=jobright&utm_campaign=cxro&utm_medium=social_media&utm_content=job_posting&ss=paid | G13: Requested | H13: Meet
A14: 13 | B14: Stackline | C14: Full Stack Engineer | D14: 46073 | F14: https://boards.greenhouse.io/embed/job_app?token=4613319005&utm_source=jobright | G14: Requested
A15: 14 | B15: Cisco | C15: Software Engineering 2 ID2007168 | F15: https://careers.cisco.com/global/en/job/2007168/Software-Engineer-II-Full-Time-United-States | G15: Pending | H15: Yash | I15: ID2007168
A17: 16 | B17: Rivian | C17: Software Engineer II, Full-Stack (QMS) | D17: 46075 | E17: 46075 | F17: https://internal-careers-rivian.icims.com/jobs/26472/software-engineer-ii%2c-full-stack-%28qms%29/job | G17: Message Ready | I17: I hope you're doing well! I previously worked as an SDE2 at Bounteous and am pursuing my Master’s in Data Science from Stony Brook University. I came across the Software Engineer II position with Job ID: 26472 at Rivian, and wanted to check if you’d be open to reviewing my resume or referring me. Thank you! | J17: Project Multi Purpose Resume
A18: 17 | B18: Paypal | C18: Software Engineer , Java | D18: 46074 | E18: 46075 | F18: http://paypal.eightfold.ai/careers/job/274917022927?source=JobBoardIndeed-Organic | G18: Requested | I18: I hope you're doing well! I previously worked as an SDE2 at Bounteous and am pursuing my Master’s in Data Science from Stony Brook University. I came across the Software Engineer, Java position with Job ID: R0133240 at Paypal, and wanted to check if you’d be open to reviewing my resume or referring me. Thank you!

Sheet Daily Rating
B1: DEC | C1: JAN | D1: FEB | E1: MAR | F1: APR | G1: MAY | H1: JUN | I1: JUL | J1: AUG | K1: SEP | L1: OCT | M1: NOV | N1: DEC
A2: 1
A3: 2
A4: 3
A5: 4
A6: 5
A7: 6
A8: 7
A9: 8
A10: 9
A11: 10
A12: 11
A13: 12
... A27: 26
A28: 27 | B28: P
A29: 28 | B29: P
A30: 29 | B30: P
A31: 30 | B31: P
A32: 31 | B32: P
P36: Amazing | S36: AP | T36: Academic Productive
P37: Good | S37: P | T37: Productive
P38: Mediocre | S38: NP | T38: Not at all Productive
P39: Poor | S39: ILL | T39: Literally ILL
P40: Nightmare | S40: D | T40: Demotivated
S41: ST | T41: Stressed

Sheet Daily Notes
A1: Date | B1: Comments
A2: 45992
A3: 29th December | B3: Mailroom Total time spent 11AM - 4PM not alot of work got some time to spend on resume but need to come up with a plan by EOY. Good: Recieved Deskmate (Manifestation works feels like) Bad: Alot of mails, told angelique about the missing timesheet Costco: Sirji got the membership spend around 2 hours store was mid but enjoyed Good: Bought Rice for 20.48$ cheaper then what i was placing order on Amazon same for 15LB Bad: Was not able to complete task in hand 1 Harriet St: Need to spend task being more productive, Fees paid by BOB finaily - Indian banking system need better people in this era tbh. Good: Starting of recording days sounds fun, got puma socks for 10 for 10 very good deal. Tried Spotify's feature to add 8 second of buffer mix between songs curently nuteral feeling to be honest Bad: Second time failed to make paneer, beacuse of the onions, need to keep it in mind that i have grid and cook at the same time. Droped my phone i guess i got a scratch but i still feel like without cover is my style Getting the feeling like i am becoming more like nanu where he used to record his feeling or daily activty in a dairy and i am using google sheets lol This feeling is not that i am getting old but more like i am getting more educated about life maybe but definatelty not because i am getting old for sure Miss you nanu
A4: 30th December | B4: Mailroom: Total Time spent 11AM - 4PM was tired because i didnt got a good amount of sleep yesterday mike point out 2 mistake, one in mail hunt and second one was non TBA scan then when i was talking to heather on phone i flaged one locker too, not my day at mailroom for sure. 1 Harriet St: Good: Fees think for Fall 2025 got resolved, got to eat watermaleon after years for sure, filled petrol for car 48$ Bad: Slept at 4 AM, Reached home at 5:30PM and slept till 8:30PM watched Demons Slayer and didnt have mood to do anything
A5: 31st December | B5: Mailroom: Reached exact 9AM today total time spent was 9:00AM - 1:00PM, did literally nothing till the time i am filling this daily notes. Hopefully i will be able to compelte the new sheet by eod today, need to think about the reusme format, need to apply for the RA posistion as well damn. 1 Harriet St: Good: It snowed for a while, mooraish flight got cancel sad, need to complete the sheet. Bad: Need to be more productive
A7: 46023 | B7: Expectation for the Month of January 2026: 1. Need to be more productive when it comes to job applications 2. You are gonna be turning 27 this year act like one take responsibilites make better decissions 3. Control your diet 4. 5.

Sheet Enhanced Jobs Data
A1: {='Saved Jobs'!A1:E995} -> Date Saved | B1: Role | C1: Company | D1: Location | E1: Job Link | F1: Date | G1: Month | H1: Week | I1: Day | J1: OA | K1: Referral | L1: Location | M1: Application Applied Time | N1: Number of Applicant | O1: OA Deadline | P1: Referral Count | Q1: Requested Referral Person Name | R1: Response | S1: Comment | Z1: Date | AA1: Week Number | AB1: Month | AC1: Week Start Date | AD1: Day Number
A2: 45961.71 | B2: Computational Imaging Research Scientist Manage My Job Request a Coach | C2: GLASS Imaging | D2: San Francisco Bay Area · 10 minutes ago · 0 applicants Promoted by hirer · No response insights available yet | E2: https://www.linkedin.com/jobs/view/4320212741/ | F2: =IFERROR(__xludf.DUMMYFUNCTION("ARRAYFORMULA( IF( A2:A995="""", , IFERROR( IF( ISNUMBER(A2:A995), TO_DATE(A2:A995), IFERROR( DATEVALUE(REGEXEXTRACT(A2:A995,""(\d{1,2}/\d{1,2}/\d{4})"")) + TIMEVALUE(REGEXEXTRACT(A2:A995,""(\"&"d{1,2}:\d{2}:\d{2}\s*[APMapm]{2})"")), IFERROR( DATEVALUE(REGEXEXTRACT(A2:A995,""(\d{4}-\d{2}-\d{2})"")) + TIMEVALUE(REGEXEXTRACT(A2:A995,""(\d{2}:\d{2}:\d{2})"")), DATEVALUE(A2:A995) ) ) "&" ), """" ) ) ) "),45961.70983796296) -> 45961.71 | G2: {=IF(F2:F995="",,TEXT(F2:F995,"mmm yyyy"))} -> Oct 2025 | H2: {=IF(F2:F995="",,WEEKNUM(F2:F995))} -> 44 | I2: {=IF(F2:F995="",,TEXT(F2:F995,"ddd"))} -> Fri | J2: =IF(A1<>"","No","") -> No | K2: =IF(A1<>"","No","") -> No | L2: =IFERROR(__xludf.DUMMYFUNCTION("ARRAYFORMULA( IF(D2:D995="""","""", { TRIM(IFERROR(REGEXEXTRACT(D2:D995,""^(.*?)·""),REGEXEXTRACT(D2:D995,""^(.*)$""))), TRIM(IFERROR(REGEXEXTRACT(D2:D995,""·\s*(.*?)\s*·""),"""")), IFERROR(VALUE(REGEXEXTRACT(D2:D995,""(\d+)"")),"""&""") } ) ) "),"San Francisco Bay Area") -> San Francisco Bay Area | M2: =IFERROR(__xludf.DUMMYFUNCTION("""COMPUTED_VALUE"""),"10 minutes ago") -> 10 minutes ago | N2: =IFERROR(__xludf.DUMMYFUNCTION("""COMPUTED_VALUE"""),10.0) -> 10 | P2: =IF(A1<>"","0","") -> 0 | R2: =IF(A1<>"","Review","") -> Review | Z2: {=IF(F2:F995="",,INT(F2:F995))} -> 45961 | AA2: {=IF(F2:F995="",,YEAR(F2:F995)&"-W"&TEXT(ISOWEEKNUM(F2:F995),"00"))} -> 2025-W44 | AB2: {=IF(F2:F995="",,TEXT(F2:F995,"yyyy-mm"))} -> 2025-10 | AC2: =IF(Z2="","", Z2 - WEEKDAY(Z2, 2) + 1) -> 45957 | AD2: =IF(Z2="","", WEEKDAY(Z2, 2)) -> 5
A3: 45961.724 | B3: Embedded Software Engineer Manage My Job Request a Coach | C3: Vastika Inc | D3: Carrollton, TX · 15 minutes ago · 5 applicants Promoted by hirer · No response insights available yet | E3: https://www.linkedin.com/jobs/view/4320312705/ | F3: =IFERROR(__xludf.DUMMYFUNCTION("""COMPUTED_VALUE"""),45961.72439814815) -> 45961.724 | G3: Oct 2025 | H3: 44 | I3: Fri | J3: =IF(A2<>"","No","") -> No | K3: =IF(A2<>"","No","") -> No | L3: =IFERROR(__xludf.DUMMYFUNCTION("""COMPUTED_VALUE"""),"Carrollton, TX") -> Carrollton, TX | M3: =IFERROR(__xludf.DUMMYFUNCTION("""COMPUTED_VALUE"""),"15 minutes ago") -> 15 minutes ago | N3: =IFERROR(__xludf.DUMMYFUNCTION("""COMPUTED_VALUE"""),15.0) -> 15 | P3: =IF(A2<>"","0","") -> 0 | R3: =IF(A2<>"","Review","") -> Review | Z3: 45961 | AA3: 2025-W44 | AB3: 2025-10 | AC3: =IF(Z3="","", Z3 - WEEKDAY(Z3, 2) + 1) -> 45957 | AD3: =IF(Z3="","", WEEKDAY(Z3, 2)) -> 5
A4: 45961.734 | B4: AI Engineer | C4: New Resources Consulting | D4: Milwaukee, WI · Reposted 51 minutes ago · Over 100 applicants Promoted by hirer · Actively reviewing applicants | E4: https://www.linkedin.com/jobs/view/4314022965/ | F4: =IFERROR(__xludf.DUMMYFUNCTION("""COMPUTED_VALUE"""),45961.73446759259) -> 45961.734 | G4: Oct 2025 | H4: 44 | I4: Fri | J4: =IF(A3<>"","No","") -> No | K4: =IF(A3<>"","No","") -> No | L4: =IFERROR(__xludf.DUMMYFUNCTION("""COMPUTED_VALUE"""),"Milwaukee, WI") -> Milwaukee, WI | M4: =IFERROR(__xludf.DUMMYFUNCTION("""COMPUTED_VALUE"""),"Reposted 51 minutes ago") -> Reposted 51 minutes ago | N4: =IFERROR(__xludf.DUMMYFUNCTION("""COMPUTED_VALUE"""),51.0) -> 51 | P4: =IF(A3<>"","0","") -> 0 | R4: =IF(A3<>"","Review","") -> Review | Z4: 45961 | AA4: 2025-W44 | AB4: 2025-10 | AC4: =IF(Z4="","", Z4 - WEEKDAY(Z4, 2) + 1) -> 45957 | AD4: =IF(Z4="","", WEEKDAY(Z4, 2)) -> 5
A5: 45961.76 | B5: Quantitative Strategy Developer - New Grad Manage My Job Request a Coach | C5: Susquehanna International Group | D5: Greater Philadelphia · 38 minutes ago · 17 people clicked apply Promoted by hirer · Responses managed off LinkedIn | E5: https://www.linkedin.com/jobs/view/4320152787/ | F5: =IFERROR(__xludf.DUMMYFUNCTION("""COMPUTED_VALUE"""),45961.76006944444) -> 45961.76 | G5: Oct 2025 | H5: 44 | I5: Fri | J5: Yes | K5: =IF(A4<>"","No","") -> No | L5: =IFERROR(__xludf.DUMMYFUNCTION("""COMPUTED_VALUE"""),"Greater Philadelphia") -> Greater Philadelphia | M5: =IFERROR(__xludf.DUMMYFUNCTION("""COMPUTED_VALUE"""),"38 minutes ago") -> 38 minutes ago | N5: =IFERROR(__xludf.DUMMYFUNCTION("""COMPUTED_VALUE"""),38.0) -> 38 | O5: 2nd Jan 3:18PM | P5: =IF(A4<>"","0","") -> 0 | R5: OA | Z5: 45961 | AA5: 2025-W44 | AB5: 2025-10 | AC5: =IF(Z5="","", Z5 - WEEKDAY(Z5, 2) + 1) -> 45957 | AD5: =IF(Z5="","", WEEKDAY(Z5, 2)) -> 5
A6: 45961.831 | B6: Devops Engineer | C6: Wipro | D6: Minneapolis, NC · 3 hours ago · 25 people clicked apply Promoted by hirer · Responses managed off LinkedIn | E6: https://www.linkedin.com/jobs/view/4320212736/ | F6: =IFERROR(__xludf.DUMMYFUNCTION("""COMPUTED_VALUE"""),45961.831041666665) -> 45961.831 | G6: Oct 2025 | H6: 44 | I6: Fri | J6: =IF(A5<>"","No","") -> No | K6: =IF(A5<>"","No","") -> No | L6: =IFERROR(__xludf.DUMMYFUNCTION("""COMPUTED_VALUE"""),"Minneapolis, NC") -> Minneapolis, NC | M6: =IFERROR(__xludf.DUMMYFUNCTION("""COMPUTED_VALUE"""),"3 hours ago") -> 3 hours ago | N6: =IFERROR(__xludf.DUMMYFUNCTION("""COMPUTED_VALUE"""),3.0) -> 3 | P6: =IF(A5<>"","0","") -> 0 | R6: =IF(A5<>"","Review","") -> Review | Z6: 45961 | AA6: 2025-W44 | AB6: 2025-10 | AC6: =IF(Z6="","", Z6 - WEEKDAY(Z6, 2) + 1) -> 45957 | AD6: =IF(Z6="","", WEEKDAY(Z6, 2)) -> 5
A7: 45961.837 | B7: Software Engineer – Microsoft AI Manage My Job Request a Coach | C7: Microsoft | D7: Redmond, WA · 3 hours ago · 48 people clicked apply Promoted by hirer · Responses managed off LinkedIn | E7: https://www.linkedin.com/jobs/view/4333328595/ | F7: =IFERROR(__xludf.DUMMYFUNCTION("""COMPUTED_VALUE"""),45961.83665509259) -> 45961.837 | G7: Oct 2025 | H7: 44 | I7: Fri | J7: =IF(A6<>"","No","") -> No | K7: =IF(A6<>"","No","") -> No | L7: =IFERROR(__xludf.DUMMYFUNCTION("""COMPUTED_VALUE"""),"Redmond, WA") -> Redmond, WA | M7: =IFERROR(__xludf.DUMMYFUNCTION("""COMPUTED_VALUE"""),"3 hours ago") -> 3 hours ago | N7: =IFERROR(__xludf.DUMMYFUNCTION("""COMPUTED_VALUE"""),3.0) -> 3 | P7: =IF(A6<>"","0","") -> 0 | R7: =IF(A6<>"","Review","") -> Review | Z7: 45961 | AA7: 2025-W44 | AB7: 2025-10 | AC7: =IF(Z7="","", Z7 - WEEKDAY(Z7, 2) + 1) -> 45957 | AD7: =IF(Z7="","", WEEKDAY(Z7, 2)) -> 5
A8: 45961.87 | B8: Real-Time /Embedded Firmware Engineer | C8: Nuvoton Technology Corporation America | D8: Austin, TX · 49 minutes ago · 6 applicants Promoted by hirer · Company review time is typically 1 week | E8: https://www.linkedin.com/jobs/view/4333369385/ | F8: =IFERROR(__xludf.DUMMYFUNCTION("""COMPUTED_VALUE"""),45961.86969907407) -> 45961.87 | G8: Oct 2025 | H8: 44 | I8: Fri | J8: =IF(A7<>"","No","") -> No | K8: =IF(A7<>"","No","") -> No | L8: =IFERROR(__xludf.DUMMYFUNCTION("""COMPUTED_VALUE"""),"Austin, TX") -> Austin, TX | M8: =IFERROR(__xludf.DUMMYFUNCTION("""COMPUTED_VALUE"""),"49 minutes ago") -> 49 minutes ago | N8: =IFERROR(__xludf.DUMMYFUNCTION("""COMPUTED_VALUE"""),49.0) -> 49 | P8: =IF(A7<>"","0","") -> 0 | R8: =IF(A7<>"","Review","") -> Review | Z8: 45961 | AA8: 2025-W44 | AB8: 2025-10 | AC8: =IF(Z8="","", Z8 - WEEKDAY(Z8, 2) + 1) -> 45957 | AD8: =IF(Z8="","", WEEKDAY(Z8, 2)) -> 5
A9: 45961.872 | B9: Front End Engineer- React & Map API Manage My Job Request a Coach | C9: Ascendion | D9: Seattle, WA · Reposted 54 minutes ago · Over 100 applicants Promoted by hirer · Actively reviewing applicants | E9: https://www.linkedin.com/jobs/view/4315044235/ | F9: =IFERROR(__xludf.DUMMYFUNCTION("""COMPUTED_VALUE"""),45961.87230324074) -> 45961.872 | G9: Oct 2025 | H9: 44 | I9: Fri | J9: =IF(A8<>"","No","") -> No | K9: =IF(A8<>"","No","") -> No | L9: =IFERROR(__xludf.DUMMYFUNCTION("""COMPUTED_VALUE"""),"Seattle, WA") -> Seattle, WA | M9: =IFERROR(__xludf.DUMMYFUNCTION("""COMPUTED_VALUE"""),"Reposted 54 minutes ago") -> Reposted 54 minutes ago | N9: =IFERROR(__xludf.DUMMYFUNCTION("""COMPUTED_VALUE"""),54.0) -> 54 | P9: =IF(A8<>"","0","") -> 0 | R9: =IF(A8<>"","Review","") -> Review | Z9: 45961 | AA9: 2025-W44 | AB9: 2025-10 | AC9: =IF(Z9="","", Z9 - WEEKDAY(Z9, 2) + 1) -> 45957 | AD9: =IF(Z9="","", WEEKDAY(Z9, 2)) -> 5
A10: 45962.411 | B10: Applications Analyst Manage My Job Request a Coach | C10: Zekelman Industries | D10: Wheatland, PA · Reposted 42 minutes ago · 27 people clicked apply Promoted by hirer · Responses managed off LinkedIn | E10: https://www.linkedin.com/jobs/view/4313443958/ | F10: =IFERROR(__xludf.DUMMYFUNCTION("""COMPUTED_VALUE"""),45962.41068287037) -> 45962.411 | G10: Nov 2025 | H10: 44 | I10: Sat | J10: =IF(A9<>"","No","") -> No | K10: =IF(A9<>"","No","") -> No | L10: =IFERROR(__xludf.DUMMYFUNCTION("""COMPUTED_VALUE"""),"Wheatland, PA") -> Wheatland, PA | M10: =IFERROR(__xludf.DUMMYFUNCTION("""COMPUTED_VALUE"""),"Reposted 42 minutes ago") -> Reposted 42 minutes ago | N10: =IFERROR(__xludf.DUMMYFUNCTION("""COMPUTED_VALUE"""),42.0) -> 42 | P10: =IF(A9<>"","0","") -> 0 | R10: =IF(A9<>"","Review","") -> Review | Z10: 45962 | AA10: 2025-W44 | AB10: 2025-11 | AC10: =IF(Z10="","", Z10 - WEEKDAY(Z10, 2) + 1) -> 45957 | AD10: =IF(Z10="","", WEEKDAY(Z10, 2)) -> 6
A11: 45963.12 | B11: AI Engineer Manage My Job Request a Coach | C11: Avesta Computer Services | D11: Fremont, CA · 42 minutes ago · 3 applicants Promoted by hirer · No response insights available yet | E11: https://www.linkedin.com/jobs/view/4332188017/ | F11: =IFERROR(__xludf.DUMMYFUNCTION("""COMPUTED_VALUE"""),45963.11966435185) -> 45963.12 | G11: Nov 2025 | H11: 45 | I11: Sun | J11: =IF(A10<>"","No","") -> No | K11: =IF(A10<>"","No","") -> No | L11: =IFERROR(__xludf.DUMMYFUNCTION("""COMPUTED_VALUE"""),"Fremont, CA") -> Fremont, CA | M11: =IFERROR(__xludf.DUMMYFUNCTION("""COMPUTED_VALUE"""),"42 minutes ago") -> 42 minutes ago | N11: =IFERROR(__xludf.DUMMYFUNCTION("""COMPUTED_VALUE"""),42.0) -> 42 | P11: =IF(A10<>"","0","") -> 0 | R11: =IF(A10<>"","Review","") -> Review | Z11: 45963 | AA11: 2025-W44 | AB11: 2025-11 | AC11: =IF(Z11="","", Z11 - WEEKDAY(Z11, 2) + 1) -> 45957 | AD11: =IF(Z11="","", WEEKDAY(Z11, 2)) -> 7
A12: 45963.13 | B12: Senior Web Developer Manage My Job Request a Coach | C12: SCIENTIFIC GAMES | D12: Alpharetta, GA · Reposted 10 minutes ago · 99 people clicked apply Promoted by hirer · Responses managed off LinkedIn | E12: https://www.linkedin.com/jobs/view/4309207109/ | F12: =IFERROR(__xludf.DUMMYFUNCTION("""COMPUTED_VALUE"""),45963.13024305556) -> 45963.13 | G12: Nov 2025 | H12: 45 | I12: Sun | J12: =IF(A11<>"","No","") -> No | K12: =IF(A11<>"","No","") -> No | L12: =IFERROR(__xludf.DUMMYFUNCTION("""COMPUTED_VALUE"""),"Alpharetta, GA") -> Alpharetta, GA | M12: =IFERROR(__xludf.DUMMYFUNCTION("""COMPUTED_VALUE"""),"Reposted 10 minutes ago") -> Reposted 10 minutes ago | N12: =IFERROR(__xludf.DUMMYFUNCTION("""COMPUTED_VALUE"""),10.0) -> 10 | P12: =IF(A11<>"","0","") -> 0 | R12: =IF(A11<>"","Review","") -> Review | Z12: 45963 | AA12: 2025-W44 | AB12: 2025-11 | AC12: =IF(Z12="","", Z12 - WEEKDAY(Z12, 2) + 1) -> 45957 | AD12: =IF(Z12="","", WEEKDAY(Z12, 2)) -> 7
A13: 45963.198 | B13: Software Development Engineer III | C13: Optimum | D13: Bethpage, NY · Reposted 1 hour ago · Over 100 people clicked apply Responses managed off LinkedIn | E13: https://www.linkedin.com/jobs/view/4177889291/ | F13: =IFERROR(__xludf.DUMMYFUNCTION("""COMPUTED_VALUE"""),45963.19826388889) -> 45963.198 | G13: Nov 2025 | H13: 45 | I13: Sun | J13: =IF(A12<>"","No","") -> No | K13: =IF(A12<>"","No","") -> No | L13: =IFERROR(__xludf.DUMMYFUNCTION("""COMPUTED_VALUE"""),"Bethpage, NY") -> Bethpage, NY | M13: =IFERROR(__xludf.DUMMYFUNCTION("""COMPUTED_VALUE"""),"Reposted 1 hour ago") -> Reposted 1 hour ago | N13: =IFERROR(__xludf.DUMMYFUNCTION("""COMPUTED_VALUE"""),1.0) -> 1 | P13: =IF(A12<>"","0","") -> 0 | R13: =IF(A12<>"","Review","") -> Review | Z13: 45963 | AA13: 2025-W44 | AB13: 2025-11 | AC13: =IF(Z13="","", Z13 - WEEKDAY(Z13, 2) + 1) -> 45957 | AD13: =IF(Z13="","", WEEKDAY(Z13, 2)) -> 7
A14: 45963.208 | B14: Principal Software Engineer (.NET) Manage My Job Request a Coach | C14: Qualitest | D14: California, United States · Reposted 28 minutes ago · 36 people clicked apply Promoted by hirer · Responses managed off LinkedIn | E14: https://www.linkedin.com/jobs/view/4319099936/ | F14: =IFERROR(__xludf.DUMMYFUNCTION("""COMPUTED_VALUE"""),45963.207604166666) -> 45963.208 | G14: Nov 2025 | H14: 45 | I14: Sun | J14: =IF(A13<>"","No","") -> No | K14: =IF(A13<>"","No","") -> No | L14: =IFERROR(__xludf.DUMMYFUNCTION("""COMPUTED_VALUE"""),"California, United States") -> California, United States | M14: =IFERROR(__xludf.DUMMYFUNCTION("""COMPUTED_VALUE"""),"Reposted 28 minutes ago") -> Reposted 28 minutes ago | N14: =IFERROR(__xludf.DUMMYFUNCTION("""COMPUTED_VALUE"""),28.0) -> 28 | P14: =IF(A13<>"","0","") -> 0 | R14: =IF(A13<>"","Review","") -> Review | Z14: 45963 | AA14: 2025-W44 | AB14: 2025-11 | AC14: =IF(Z14="","", Z14 - WEEKDAY(Z14, 2) + 1) -> 45957 | AD14: =IF(Z14="","", WEEKDAY(Z14, 2)) -> 7
A15: 45963.514 | B15: REMOTE - Lead AI Engineer | C15: CyberCoders | D15: San Francisco, CA · Reposted 1 hour ago · 93 applicants Promoted by hirer · No response insights available yet | E15: https://www.linkedin.com/jobs/view/4292870840/ | F15: =IFERROR(__xludf.DUMMYFUNCTION("""COMPUTED_VALUE"""),45963.51403935185) -> 45963.514 | G15: Nov 2025 | H15: 45 | I15: Sun | J15: =IF(A14<>"","No","") -> No | K15: =IF(A14<>"","No","") -> No | L15: =IFERROR(__xludf.DUMMYFUNCTION("""COMPUTED_VALUE"""),"San Francisco, CA") -> San Francisco, CA | M15: =IFERROR(__xludf.DUMMYFUNCTION("""COMPUTED_VALUE"""),"Reposted 1 hour ago") -> Reposted 1 hour ago | N15: =IFERROR(__xludf.DUMMYFUNCTION("""COMPUTED_VALUE"""),1.0) -> 1 | P15: =IF(A14<>"","0","") -> 0 | R15: Reject | Z15: 45963 | AA15: 2025-W44 | AB15: 2025-11 | AC15: =IF(Z15="","", Z15 - WEEKDAY(Z15, 2) + 1) -> 45957 | AD15: =IF(Z15="","", WEEKDAY(Z15, 2)) -> 7
A16: 45963.55 | B16: Big Data Engineer Manage My Job Request a Coach | C16: Modis | D16: Plano, TX · Reposted 2 hours ago · Over 100 people clicked apply Promoted by hirer · Responses managed off LinkedIn | E16: https://www.linkedin.com/jobs/view/4242967875/ | F16: =IFERROR(__xludf.DUMMYFUNCTION("""COMPUTED_VALUE"""),45963.5496412037) -> 45963.55 | G16: Nov 2025 | H16: 45 | I16: Sun | J16: =IF(A15<>"","No","") -> No | K16: =IF(A15<>"","No","") -> No | L16: =IFERROR(__xludf.DUMMYFUNCTION("""COMPUTED_VALUE"""),"Plano, TX") -> Plano, TX | M16: =IFERROR(__xludf.DUMMYFUNCTION("""COMPUTED_VALUE"""),"Reposted 2 hours ago") -> Reposted 2 hours ago | N16: =IFERROR(__xludf.DUMMYFUNCTION("""COMPUTED_VALUE"""),2.0) -> 2 | P16: =IF(A15<>"","0","") -> 0 | R16: =IF(A15<>"","Review","") -> Review | Z16: 45963 | AA16: 2025-W44 | AB16: 2025-11 | AC16: =IF(Z16="","", Z16 - WEEKDAY(Z16, 2) + 1) -> 45957 | AD16: =IF(Z16="","", WEEKDAY(Z16, 2)) -> 7
A17: 45963.553 | B17: (USA) Staff, Software Engineer Manage My Job Request a Coach | C17: Walmart | D17: Bentonville, AR · Reposted 2 hours ago · 44 people clicked apply Promoted by hirer · Responses managed off LinkedIn | E17: https://www.linkedin.com/jobs/view/4255482699/ | F17: =IFERROR(__xludf.DUMMYFUNCTION("""COMPUTED_VALUE"""),45963.5534837963) -> 45963.553 | G17: Nov 2025 | H17: 45 | I17: Sun | J17: =IF(A16<>"","No","") -> No | K17: =IF(A16<>"","No","") -> No | L17: =IFERROR(__xludf.DUMMYFUNCTION("""COMPUTED_VALUE"""),"Bentonville, AR") -> Bentonville, AR | M17: =IFERROR(__xludf.DUMMYFUNCTION("""COMPUTED_VALUE"""),"Reposted 2 hours ago") -> Reposted 2 hours ago | N17: =IFERROR(__xludf.DUMMYFUNCTION("""COMPUTED_VALUE"""),2.0) -> 2 | P17: =IF(A16<>"","0","") -> 0 | R17: =IF(A16<>"","Review","") -> Review | Z17: 45963 | AA17: 2025-W44 | AB17: 2025-11 | AC17: =IF(Z17="","", Z17 - WEEKDAY(Z17, 2) + 1) -> 45957 | AD17: =IF(Z17="","", WEEKDAY(Z17, 2)) -> 7
A18: 45963.966 | B18: Software Engineer | C18: Like a Son | D18: Charleston, SC · 49 minutes ago · 29 applicants Promoted by hirer · No response insights available yet | E18: https://www.linkedin.com/jobs/view/4333891398/ | F18: =IFERROR(__xludf.DUMMYFUNCTION("""COMPUTED_VALUE"""),45963.965682870374) -> 45963.966 | G18: Nov 2025 | H18: 45 | I18: Sun | J18: =IF(A17<>"","No","") -> No | K18: =IF(A17<>"","No","") -> No | L18: =IFERROR(__xludf.DUMMYFUNCTION("""COMPUTED_VALUE"""),"Charleston, SC") -> Charleston, SC | M18: =IFERROR(__xludf.DUMMYFUNCTION("""COMPUTED_VALUE"""),"49 minutes ago") -> 49 minutes ago | N18: =IFERROR(__xludf.DUMMYFUNCTION("""COMPUTED_VALUE"""),49.0) -> 49 | P18: =IF(A17<>"","0","") -> 0 | R18: =IF(A17<>"","Review","") -> Review | Z18: 45963 | AA18: 2025-W44 | AB18: 2025-11 | AC18: =IF(Z18="","", Z18 - WEEKDAY(Z18, 2) + 1) -> 45957 | AD18: =IF(Z18="","", WEEKDAY(Z18, 2)) -> 7
A19: 45964.441 | B19: GIS Developer | C19: Satwic Inc | D19: Los Angeles, CA · 12 minutes ago · 0 applicants Promoted by hirer · Company review time is typically 1 week | E19: https://www.linkedin.com/jobs/view/4333847443/ | F19: =IFERROR(__xludf.DUMMYFUNCTION("""COMPUTED_VALUE"""),45964.441400462965) -> 45964.441 | G19: Nov 2025 | H19: 45 | I19: Mon | J19: =IF(A18<>"","No","") -> No | K19: =IF(A18<>"","No","") -> No | L19: =IFERROR(__xludf.DUMMYFUNCTION("""COMPUTED_VALUE"""),"Los Angeles, CA") -> Los Angeles, CA | M19: =IFERROR(__xludf.DUMMYFUNCTION("""COMPUTED_VALUE"""),"12 minutes ago") -> 12 minutes ago | N19: =IFERROR(__xludf.DUMMYFUNCTION("""COMPUTED_VALUE"""),12.0) -> 12 | P19: =IF(A18<>"","0","") -> 0 | R19: =IF(A18<>"","Review","") -> Review | Z19: 45964 | AA19: 2025-W45 | AB19: 2025-11 | AC19: =IF(Z19="","", Z19 - WEEKDAY(Z19, 2) + 1) -> 45964 | AD19: =IF(Z19="","", WEEKDAY(Z19, 2)) -> 1
A20: 45964.442 | B20: Python and Node Full Stack Developer Manage My Job Request a Coach | C20: BeaconFire Solution Inc. | D20: East Windsor, NJ · Reposted 7 minutes ago · Over 100 applicants Promoted by hirer · Actively reviewing applicants | E20: https://www.linkedin.com/jobs/view/4309215421/ | F20: =IFERROR(__xludf.DUMMYFUNCTION("""COMPUTED_VALUE"""),45964.441875) -> 45964.442 | G20: Nov 2025 | H20: 45 | I20: Mon | J20: =IF(A19<>"","No","") -> No | K20: =IF(A19<>"","No","") -> No | L20: =IFERROR(__xludf.DUMMYFUNCTION("""COMPUTED_VALUE"""),"East Windsor, NJ") -> East Windsor, NJ | M20: =IFERROR(__xludf.DUMMYFUNCTION("""COMPUTED_VALUE"""),"Reposted 7 minutes ago") -> Reposted 7 minutes ago | N20: =IFERROR(__xludf.DUMMYFUNCTION("""COMPUTED_VALUE"""),7.0) -> 7 | P20: =IF(A19<>"","0","") -> 0 | R20: =IF(A19<>"","Review","") -> Review | Z20: 45964 | AA20: 2025-W45 | AB20: 2025-11 | AC20: =IF(Z20="","", Z20 - WEEKDAY(Z20, 2) + 1) -> 45964 | AD20: =IF(Z20="","", WEEKDAY(Z20, 2)) -> 1
A21: 45964.442 | B21: MERN/MEAN Stack Developer Manage My Job Request a Coach | C21: BeaconFire Inc. | D21: East Windsor, NJ · Reposted 8 minutes ago · Over 100 applicants Promoted by hirer · Actively reviewing applicants | E21: https://www.linkedin.com/jobs/view/4301098096/ | F21: =IFERROR(__xludf.DUMMYFUNCTION("""COMPUTED_VALUE"""),45964.44215277778) -> 45964.442 | G21: Nov 2025 | H21: 45 | I21: Mon | J21: =IF(A20<>"","No","") -> No | K21: =IF(A20<>"","No","") -> No | L21: =IFERROR(__xludf.DUMMYFUNCTION("""COMPUTED_VALUE"""),"East Windsor, NJ") -> East Windsor, NJ | M21: =IFERROR(__xludf.DUMMYFUNCTION("""COMPUTED_VALUE"""),"Reposted 8 minutes ago") -> Reposted 8 minutes ago | N21: =IFERROR(__xludf.DUMMYFUNCTION("""COMPUTED_VALUE"""),8.0) -> 8 | P21: =IF(A20<>"","0","") -> 0 | R21: =IF(A20<>"","Review","") -> Review | Z21: 45964 | AA21: 2025-W45 | AB21: 2025-11 | AC21: =IF(Z21="","", Z21 - WEEKDAY(Z21, 2) + 1) -> 45964 | AD21: =IF(Z21="","", WEEKDAY(Z21, 2)) -> 1
A22: 45964.442 | B22: Java Software Engineer Manage My Job Request a Coach | C22: BeaconFire Solution Inc. | D22: East Windsor, NJ · Reposted 8 minutes ago · Over 100 applicants Promoted by hirer · Actively reviewing applicants | E22: https://www.linkedin.com/jobs/view/4303401301/ | F22: =IFERROR(__xludf.DUMMYFUNCTION("""COMPUTED_VALUE"""),45964.442395833335) -> 45964.442 | G22: Nov 2025 | H22: 45 | I22: Mon | J22: =IF(A21<>"","No","") -> No | K22: =IF(A21<>"","No","") -> No | L22: =IFERROR(__xludf.DUMMYFUNCTION("""COMPUTED_VALUE"""),"East Windsor, NJ") -> East Windsor, NJ | M22: =IFERROR(__xludf.DUMMYFUNCTION("""COMPUTED_VALUE"""),"Reposted 8 minutes ago") -> Reposted 8 minutes ago | N22: =IFERROR(__xludf.DUMMYFUNCTION("""COMPUTED_VALUE"""),8.0) -> 8 | P22: =IF(A21<>"","0","") -> 0 | R22: =IF(A21<>"","Review","") -> Review | Z22: 45964 | AA22: 2025-W45 | AB22: 2025-11 | AC22: =IF(Z22="","", Z22 - WEEKDAY(Z22, 2) + 1) -> 45964 | AD22: =IF(Z22="","", WEEKDAY(Z22, 2)) -> 1
A23: 45964.443 | B23: MERN/MEAN Stack Developer Manage My Job Request a Coach | C23: BeaconFire Inc. | D23: New York, United States · Reposted 11 minutes ago · Over 100 applicants Promoted by hirer · Actively reviewing applicants | E23: https://www.linkedin.com/jobs/view/4315410648/ | F23: =IFERROR(__xludf.DUMMYFUNCTION("""COMPUTED_VALUE"""),45964.4425462963) -> 45964.443 | G23: Nov 2025 | H23: 45 | I23: Mon | J23: =IF(A22<>"","No","") -> No | K23: =IF(A22<>"","No","") -> No | L23: =IFERROR(__xludf.DUMMYFUNCTION("""COMPUTED_VALUE"""),"New York, United States") -> New York, United States | M23: =IFERROR(__xludf.DUMMYFUNCTION("""COMPUTED_VALUE"""),"Reposted 11 minutes ago") -> Reposted 11 minutes ago | N23: =IFERROR(__xludf.DUMMYFUNCTION("""COMPUTED_VALUE"""),11.0) -> 11 | P23: =IF(A22<>"","0","") -> 0 | R23: =IF(A22<>"","Review","") -> Review | Z23: 45964 | AA23: 2025-W45 | AB23: 2025-11 | AC23: =IF(Z23="","", Z23 - WEEKDAY(Z23, 2) + 1) -> 45964 | AD23: =IF(Z23="","", WEEKDAY(Z23, 2)) -> 1
A24: 45964.443 | B24: Java Software Engineer | C24: BeaconFire Solution Inc. | D24: East Windsor, NJ · Reposted 9 minutes ago · Over 100 applicants Promoted by hirer · Actively reviewing applicants | E24: https://www.linkedin.com/jobs/view/4266998367/ | F24: =IFERROR(__xludf.DUMMYFUNCTION("""COMPUTED_VALUE"""),45964.44283564815) -> 45964.443 | G24: Nov 2025 | H24: 45 | I24: Mon | J24: =IF(A23<>"","No","") -> No | K24: =IF(A23<>"","No","") -> No | L24: =IFERROR(__xludf.DUMMYFUNCTION("""COMPUTED_VALUE"""),"East Windsor, NJ") -> East Windsor, NJ | M24: =IFERROR(__xludf.DUMMYFUNCTION("""COMPUTED_VALUE"""),"Reposted 9 minutes ago") -> Reposted 9 minutes ago | N24: =IFERROR(__xludf.DUMMYFUNCTION("""COMPUTED_VALUE"""),9.0) -> 9 | P24: =IF(A23<>"","0","") -> 0 | R24: =IF(A23<>"","Review","") -> Review | Z24: 45964 | AA24: 2025-W45 | AB24: 2025-11 | AC24: =IF(Z24="","", Z24 - WEEKDAY(Z24, 2) + 1) -> 45964 | AD24: =IF(Z24="","", WEEKDAY(Z24, 2)) -> 1
A25: 45964.443 | B25: Full Stack Web Developer Manage My Job Request a Coach | C25: BeaconFire Inc. | D25: East Windsor, NJ · Reposted 9 minutes ago · Over 100 applicants Promoted by hirer · Actively reviewing applicants | E25: https://www.linkedin.com/jobs/view/4309572283/ | F25: =IFERROR(__xludf.DUMMYFUNCTION("""COMPUTED_VALUE"""),45964.44290509259) -> 45964.443 | G25: Nov 2025 | H25: 45 | I25: Mon | J25: =IF(A24<>"","No","") -> No | K25: =IF(A24<>"","No","") -> No | L25: =IFERROR(__xludf.DUMMYFUNCTION("""COMPUTED_VALUE"""),"East Windsor, NJ") -> East Windsor, NJ | M25: =IFERROR(__xludf.DUMMYFUNCTION("""COMPUTED_VALUE"""),"Reposted 9 minutes ago") -> Reposted 9 minutes ago | N25: =IFERROR(__xludf.DUMMYFUNCTION("""COMPUTED_VALUE"""),9.0) -> 9 | P25: =IF(A24<>"","0","") -> 0 | R25: =IF(A24<>"","Review","") -> Review | Z25: 45964 | AA25: 2025-W45 | AB25: 2025-11 | AC25: =IF(Z25="","", Z25 - WEEKDAY(Z25, 2) + 1) -> 45964 | AD25: =IF(Z25="","", WEEKDAY(Z25, 2)) -> 1
A26: 45964.454 | B26: Jr. Software Simulation Engineer Manage My Job Request a Coach | C26: Kavaliro | D26: Jacksonville, FL · Reposted 35 minutes ago · Over 100 people clicked apply Promoted by hirer · Responses managed off LinkedIn | E26: https://www.linkedin.com/jobs/view/4307842196/ | F26: =IFERROR(__xludf.DUMMYFUNCTION("""COMPUTED_VALUE"""),45964.45413194445) -> 45964.454 | G26: Nov 2025 | H26: 45 | I26: Mon | J26: =IF(A25<>"","No","") -> No | K26: =IF(A25<>"","No","") -> No | L26: =IFERROR(__xludf.DUMMYFUNCTION("""COMPUTED_VALUE"""),"Jacksonville, FL") -> Jacksonville, FL | M26: =IFERROR(__xludf.DUMMYFUNCTION("""COMPUTED_VALUE"""),"Reposted 35 minutes ago") -> Reposted 35 minutes ago | N26: =IFERROR(__xludf.DUMMYFUNCTION("""COMPUTED_VALUE"""),35.0) -> 35 | P26: =IF(A25<>"","0","") -> 0 | R26: =IF(A25<>"","Review","") -> Review | Z26: 45964 | AA26: 2025-W45 | AB26: 2025-11 | AC26: =IF(Z26="","", Z26 - WEEKDAY(Z26, 2) + 1) -> 45964 | AD26: =IF(Z26="","", WEEKDAY(Z26, 2)) -> 1
A27: 45964.461 | B27: Software Engineer II Manage My Job Request a Coach | C27: Cadence | D27: San Jose, CA · Reposted 51 minutes ago · Over 100 people clicked apply Promoted by hirer · Responses managed off LinkedIn | E27: https://www.linkedin.com/jobs/view/4269082937/ | F27: =IFERROR(__xludf.DUMMYFUNCTION("""COMPUTED_VALUE"""),45964.46059027778) -> 45964.461 | G27: Nov 2025 | H27: 45 | I27: Mon | J27: =IF(A26<>"","No","") -> No | K27: =IF(A26<>"","No","") -> No | L27: =IFERROR(__xludf.DUMMYFUNCTION("""COMPUTED_VALUE"""),"San Jose, CA") -> San Jose, CA | M27: =IFERROR(__xludf.DUMMYFUNCTION("""COMPUTED_VALUE"""),"Reposted 51 minutes ago") -> Reposted 51 minutes ago | N27: =IFERROR(__xludf.DUMMYFUNCTION("""COMPUTED_VALUE"""),51.0) -> 51 | P27: =IF(A26<>"","0","") -> 0 | R27: Reject | Z27: 45964 | AA27: 2025-W45 | AB27: 2025-11 | AC27: =IF(Z27="","", Z27 - WEEKDAY(Z27, 2) + 1) -> 45964 | AD27: =IF(Z27="","", WEEKDAY(Z27, 2)) -> 1
A28: 45964.471 | B28: C# Developer Manage My Job Request a Coach | C28: Insight Global | D28: Irving, TX · 1 hour ago · 56 applicants Promoted by hirer · Company review time is typically 1 week | E28: https://www.linkedin.com/jobs/view/4320344393/ | F28: =IFERROR(__xludf.DUMMYFUNCTION("""COMPUTED_VALUE"""),45964.47126157407) -> 45964.471 | G28: Nov 2025 | H28: 45 | I28: Mon | J28: =IF(A27<>"","No","") -> No | K28: =IF(A27<>"","No","") -> No | L28: =IFERROR(__xludf.DUMMYFUNCTION("""COMPUTED_VALUE"""),"Irving, TX") -> Irving, TX | M28: =IFERROR(__xludf.DUMMYFUNCTION("""COMPUTED_VALUE"""),"1 hour ago") -> 1 hour ago | N28: =IFERROR(__xludf.DUMMYFUNCTION("""COMPUTED_VALUE"""),1.0) -> 1 | P28: =IF(A27<>"","0","") -> 0 | R28: =IF(A27<>"","Review","") -> Review | Z28: 45964 | AA28: 2025-W45 | AB28: 2025-11 | AC28: =IF(Z28="","", Z28 - WEEKDAY(Z28, 2) + 1) -> 45964 | AD28: =IF(Z28="","", WEEKDAY(Z28, 2)) -> 1
A29: 45964.472 | B29: Unity Developer Manage My Job Request a Coach | C29: Qualitest | D29: Redmond, WA · Reposted 19 minutes ago · Over 100 people clicked apply Responses managed off LinkedIn | E29: https://www.linkedin.com/jobs/view/4333532799/ | F29: =IFERROR(__xludf.DUMMYFUNCTION("""COMPUTED_VALUE"""),45964.47236111111) -> 45964.472 | G29: Nov 2025 | H29: 45 | I29: Mon | J29: =IF(A28<>"","No","") -> No | K29: =IF(A28<>"","No","") -> No | L29: =IFERROR(__xludf.DUMMYFUNCTION("""COMPUTED_VALUE"""),"Redmond, WA") -> Redmond, WA | M29: =IFERROR(__xludf.DUMMYFUNCTION("""COMPUTED_VALUE"""),"Reposted 19 minutes ago") -> Reposted 19 minutes ago | N29: =IFERROR(__xludf.DUMMYFUNCTION("""COMPUTED_VALUE"""),19.0) -> 19 | P29: =IF(A28<>"","0","") -> 0 | R29: =IF(A28<>"","Review","") -> Review | Z29: 45964 | AA29: 2025-W45 | AB29: 2025-11 | AC29: =IF(Z29="","", Z29 - WEEKDAY(Z29, 2) + 1) -> 45964 | AD29: =IF(Z29="","", WEEKDAY(Z29, 2)) -> 1
A30: 45964.473 | B30: Remote AI Digitalization Expert Manage My Job Request a Coach | C30: MSX International | D30: Southfield, MI · Reposted 36 minutes ago · 64 people clicked apply Promoted by hirer · Responses managed off LinkedIn | E30: https://www.linkedin.com/jobs/view/4314145584/ | F30: =IFERROR(__xludf.DUMMYFUNCTION("""COMPUTED_VALUE"""),45964.47321759259) -> 45964.473 | G30: Nov 2025 | H30: 45 | I30: Mon | J30: =IF(A29<>"","No","") -> No | K30: =IF(A29<>"","No","") -> No | L30: =IFERROR(__xludf.DUMMYFUNCTION("""COMPUTED_VALUE"""),"Southfield, MI") -> Southfield, MI | M30: =IFERROR(__xludf.DUMMYFUNCTION("""COMPUTED_VALUE"""),"Reposted 36 minutes ago") -> Reposted 36 minutes ago | N30: =IFERROR(__xludf.DUMMYFUNCTION("""COMPUTED_VALUE"""),36.0) -> 36 | P30: =IF(A29<>"","0","") -> 0 | R30: Reject | Z30: 45964 | AA30: 2025-W45 | AB30: 2025-11 | AC30: =IF(Z30="","", Z30 - WEEKDAY(Z30, 2) + 1) -> 45964 | AD30: =IF(Z30="","", WEEKDAY(Z30, 2)) -> 1
A31: 45965.042 | B31: Data Scientist Manage My Job Request a Coach | C31: Advance Auto Parts | D31: Raleigh, NC · 7 minutes ago · 6 applicants Promoted by hirer · No response insights available yet | E31: https://www.linkedin.com/jobs/view/4320528197/ | F31: =IFERROR(__xludf.DUMMYFUNCTION("""COMPUTED_VALUE"""),45965.041655092595) -> 45965.042 | G31: Nov 2025 | H31: 45 | I31: Tue | J31: =IF(A31<>"","No","") -> No | K31: Yes | L31: =IFERROR(__xludf.DUMMYFUNCTION("""COMPUTED_VALUE"""),"Raleigh, NC") -> Raleigh, NC | M31: =IFERROR(__xludf.DUMMYFUNCTION("""COMPUTED_VALUE"""),"7 minutes ago") -> 7 minutes ago | N31: =IFERROR(__xludf.DUMMYFUNCTION("""COMPUTED_VALUE"""),7.0) -> 7 | P31: 2 | Q31: Ipsita, Sakshi | R31: =IF(A30<>"","Review","") -> Review | Z31: 45965 | AA31: 2025-W45 | AB31: 2025-11 | AC31: =IF(Z31="","", Z31 - WEEKDAY(Z31, 2) + 1) -> 45964 | AD31: =IF(Z31="","", WEEKDAY(Z31, 2)) -> 2
A32: 45965.063 | B32: Software Development Engineer I Manage My Job Request a Coach | C32: Yardi | D32: Santa Barbara, CA · 2 minutes ago · 14 people clicked apply Promoted by hirer · Responses managed off LinkedIn | E32: https://www.linkedin.com/jobs/view/4320479332/ | F32: =IFERROR(__xludf.DUMMYFUNCTION("""COMPUTED_VALUE"""),45965.062789351854) -> 45965.063 | G32: Nov 2025 | H32: 45 | I32: Tue | J32: =IF(A32<>"","No","") -> No | K32: =IF(A32<>"","No","") -> No | L32: =IFERROR(__xludf.DUMMYFUNCTION("""COMPUTED_VALUE"""),"Santa Barbara, CA") -> Santa Barbara, CA | M32: =IFERROR(__xludf.DUMMYFUNCTION("""COMPUTED_VALUE"""),"2 minutes ago") -> 2 minutes ago | N32: =IFERROR(__xludf.DUMMYFUNCTION("""COMPUTED_VALUE"""),2.0) -> 2 | P32: =IF(A31<>"","0","") -> 0 | R32: Reject | Z32: 45965 | AA32: 2025-W45 | AB32: 2025-11 | AC32: =IF(Z32="","", Z32 - WEEKDAY(Z32, 2) + 1) -> 45964 | AD32: =IF(Z32="","", WEEKDAY(Z32, 2)) -> 2
A33: 45965.437 | B33: AI Mathematics Specialist Manage My Job Request a Coach | C33: Emma of Torre.ai | D33: United States · 32 minutes ago · 6 people clicked apply Promoted by hirer · Responses managed off LinkedIn | E33: https://www.linkedin.com/jobs/view/4337427172/ | F33: =IFERROR(__xludf.DUMMYFUNCTION("""COMPUTED_VALUE"""),45965.43740740741) -> 45965.437 | G33: Nov 2025 | H33: 45 | I33: Tue | J33: =IF(A33<>"","No","") -> No | K33: =IF(A33<>"","No","") -> No | L33: =IFERROR(__xludf.DUMMYFUNCTION("""COMPUTED_VALUE"""),"United States") -> United States | M33: =IFERROR(__xludf.DUMMYFUNCTION("""COMPUTED_VALUE"""),"32 minutes ago") -> 32 minutes ago | N33: =IFERROR(__xludf.DUMMYFUNCTION("""COMPUTED_VALUE"""),32.0) -> 32 | P33: =IF(A33<>"","0","") -> 0 | R33: Reject | Z33: 45965 | AA33: 2025-W45 | AB33: 2025-11 | AC33: =IF(Z33="","", Z33 - WEEKDAY(Z33, 2) + 1) -> 45964 | AD33: =IF(Z33="","", WEEKDAY(Z33, 2)) -> 2
A34: 45965.466 | B34: Data Engineer, E-Commerce Manage My Job Request a Coach | C34: ExecutivePlacements.com | D34: San Jose, CA · 12 minutes ago · 1 person clicked apply Promoted by hirer · Responses managed off LinkedIn | E34: https://www.linkedin.com/jobs/view/4334035367/ | F34: =IFERROR(__xludf.DUMMYFUNCTION("""COMPUTED_VALUE"""),45965.46554398148) -> 45965.466 | G34: Nov 2025 | H34: 45 | I34: Tue | J34: =IF(A34<>"","No","") -> No | K34: =IF(A34<>"","No","") -> No | L34: =IFERROR(__xludf.DUMMYFUNCTION("""COMPUTED_VALUE"""),"San Jose, CA") -> San Jose, CA | M34: =IFERROR(__xludf.DUMMYFUNCTION("""COMPUTED_VALUE"""),"12 minutes ago") -> 12 minutes ago | N34: =IFERROR(__xludf.DUMMYFUNCTION("""COMPUTED_VALUE"""),12.0) -> 12 | P34: =IF(A34<>"","0","") -> 0 | R34: =IF(A34<>"","Review","") -> Review | Z34: 45965 | AA34: 2025-W45 | AB34: 2025-11 | AC34: =IF(Z34="","", Z34 - WEEKDAY(Z34, 2) + 1) -> 45964 | AD34: =IF(Z34="","", WEEKDAY(Z34, 2)) -> 2
A35: 45965.466 | B35: Computer Vision Engineer Manage My Job Request a Coach | C35: Sibitalent Corp | D35: Orlando, FL · 12 minutes ago · 6 applicants Promoted by hirer · Company review time is typically 1 week | E35: https://www.linkedin.com/jobs/view/4320782797/ | F35: =IFERROR(__xludf.DUMMYFUNCTION("""COMPUTED_VALUE"""),45965.46592592593) -> 45965.466 | G35: Nov 2025 | H35: 45 | I35: Tue | J35: =IF(A35<>"","No","") -> No | K35: =IF(A35<>"","No","") -> No | L35: =IFERROR(__xludf.DUMMYFUNCTION("""COMPUTED_VALUE"""),"Orlando, FL") -> Orlando, FL | M35: =IFERROR(__xludf.DUMMYFUNCTION("""COMPUTED_VALUE"""),"12 minutes ago") -> 12 minutes ago | N35: =IFERROR(__xludf.DUMMYFUNCTION("""COMPUTED_VALUE"""),12.0) -> 12 | P35: =IF(A35<>"","0","") -> 0 | R35: =IF(A35<>"","Review","") -> Review | Z35: 45965 | AA35: 2025-W45 | AB35: 2025-11 | AC35: =IF(Z35="","", Z35 - WEEKDAY(Z35, 2) + 1) -> 45964 | AD35: =IF(Z35="","", WEEKDAY(Z35, 2)) -> 2
A36: 45965.467 | B36: Machine Learning Intern | C36: Emonics LLC | D36: Los Angeles, CA · 29 minutes ago · 11 applicants Promoted by hirer · No response insights available yet | E36: https://www.linkedin.com/jobs/view/4320782742/ | F36: =IFERROR(__xludf.DUMMYFUNCTION("""COMPUTED_VALUE"""),45965.4666087963) -> 45965.467 | G36: Nov 2025 | H36: 45 | I36: Tue | J36: =IF(A36<>"","No","") -> No | K36: =IF(A36<>"","No","") -> No | L36: =IFERROR(__xludf.DUMMYFUNCTION("""COMPUTED_VALUE"""),"Los Angeles, CA") -> Los Angeles, CA | M36: =IFERROR(__xludf.DUMMYFUNCTION("""COMPUTED_VALUE"""),"29 minutes ago") -> 29 minutes ago | N36: =IFERROR(__xludf.DUMMYFUNCTION("""COMPUTED_VALUE"""),29.0) -> 29 | P36: =IF(A36<>"","0","") -> 0 | R36: =IF(A36<>"","Review","") -> Review | Z36: 45965 | AA36: 2025-W45 | AB36: 2025-11 | AC36: =IF(Z36="","", Z36 - WEEKDAY(Z36, 2) + 1) -> 45964 | AD36: =IF(Z36="","", WEEKDAY(Z36, 2)) -> 2
A37: 45965.467 | B37: Machine Learning Engineer Manage My Job Request a Coach | C37: Harvey Nash | D37: Cupertino, CA · 57 minutes ago · Over 100 applicants Promoted by hirer · Company review time is typically 1 week | E37: https://www.linkedin.com/jobs/view/4320663000/ | F37: =IFERROR(__xludf.DUMMYFUNCTION("""COMPUTED_VALUE"""),45965.466678240744) -> 45965.467 | G37: Nov 2025 | H37: 45 | I37: Tue | J37: =IF(A37<>"","No","") -> No | K37: =IF(A37<>"","No","") -> No | L37: =IFERROR(__xludf.DUMMYFUNCTION("""COMPUTED_VALUE"""),"Cupertino, CA") -> Cupertino, CA | M37: =IFERROR(__xludf.DUMMYFUNCTION("""COMPUTED_VALUE"""),"57 minutes ago") -> 57 minutes ago | N37: =IFERROR(__xludf.DUMMYFUNCTION("""COMPUTED_VALUE"""),57.0) -> 57 | P37: =IF(A37<>"","0","") -> 0 | R37: =IF(A37<>"","Review","") -> Review | Z37: 45965 | AA37: 2025-W45 | AB37: 2025-11 | AC37: =IF(Z37="","", Z37 - WEEKDAY(Z37, 2) + 1) -> 45964 | AD37: =IF(Z37="","", WEEKDAY(Z37, 2)) -> 2
A38: 45965.467 | B38: Software Engineer 1 Manage My Job Request a Coach | C38: Intuit | D38: Mountain View, CA · 16 minutes ago · 77 people clicked apply Responses managed off LinkedIn | E38: https://www.linkedin.com/jobs/view/4333948404/ | F38: =IFERROR(__xludf.DUMMYFUNCTION("""COMPUTED_VALUE"""),45965.4669212963) -> 45965.467 | G38: Nov 2025 | H38: 45 | I38: Tue | J38: =IF(A38<>"","No","") -> No | K38: Yes | L38: =IFERROR(__xludf.DUMMYFUNCTION("""COMPUTED_VALUE"""),"Mountain View, CA") -> Mountain View, CA | M38: =IFERROR(__xludf.DUMMYFUNCTION("""COMPUTED_VALUE"""),"16 minutes ago") -> 16 minutes ago | N38: =IFERROR(__xludf.DUMMYFUNCTION("""COMPUTED_VALUE"""),16.0) -> 16 | P38: =IF(A38<>"","0","") -> 0 | R38: =IF(A38<>"","Review","") -> Review | S38: Need to ask for Refferal | Z38: 45965 | AA38: 2025-W45 | AB38: 2025-11 | AC38: =IF(Z38="","", Z38 - WEEKDAY(Z38, 2) + 1) -> 45964 | AD38: =IF(Z38="","", WEEKDAY(Z38, 2)) -> 2
A39: 45965.67 | B39: Machine Learning Engineer, Computer Vision | C39: Metropolis Technologies | D39: Los Angeles, CA · 5 hours ago · Over 100 applicants Promoted by hirer · No response insights available yet | E39: https://www.linkedin.com/jobs/view/4333928645/ | F39: =IFERROR(__xludf.DUMMYFUNCTION("""COMPUTED_VALUE"""),45965.66954861111) -> 45965.67 | G39: Nov 2025 | H39: 45 | I39: Tue | J39: =IF(A39<>"","No","") -> No | K39: =IF(A39<>"","No","") -> No | L39: =IFERROR(__xludf.DUMMYFUNCTION("""COMPUTED_VALUE"""),"Los Angeles, CA") -> Los Angeles, CA | M39: =IFERROR(__xludf.DUMMYFUNCTION("""COMPUTED_VALUE"""),"5 hours ago") -> 5 hours ago | N39: =IFERROR(__xludf.DUMMYFUNCTION("""COMPUTED_VALUE"""),5.0) -> 5 | P39: =IF(A39<>"","0","") -> 0 | R39: =IF(A39<>"","Review","") -> Review | Z39: 45965 | AA39: 2025-W45 | AB39: 2025-11 | AC39: =IF(Z39="","", Z39 - WEEKDAY(Z39, 2) + 1) -> 45964 | AD39: =IF(Z39="","", WEEKDAY(Z39, 2)) -> 2
A40: 45965.857 | B40: Software Engineer, Core Platform Manage My Job Request a Coach | C40: Moveworks | D40: Mountain View, CA · Reposted 6 minutes ago · Over 100 people clicked apply Promoted by hirer · Responses managed off LinkedIn | E40: https://www.linkedin.com/jobs/view/4298782129/ | F40: =IFERROR(__xludf.DUMMYFUNCTION("""COMPUTED_VALUE"""),45965.85674768518) -> 45965.857 | G40: Nov 2025 | H40: 45 | I40: Tue | J40: =IF(A40<>"","No","") -> No | K40: =IF(A40<>"","No","") -> No | L40: =IFERROR(__xludf.DUMMYFUNCTION("""COMPUTED_VALUE"""),"Mountain View, CA") -> Mountain View, CA | M40: =IFERROR(__xludf.DUMMYFUNCTION("""COMPUTED_VALUE"""),"Reposted 6 minutes ago") -> Reposted 6 minutes ago | N40: =IFERROR(__xludf.DUMMYFUNCTION("""COMPUTED_VALUE"""),6.0) -> 6 | P40: =IF(A40<>"","0","") -> 0 | R40: =IF(A40<>"","Review","") -> Review | S40: Need to ask for Refferal | Z40: 45965 | AA40: 2025-W45 | AB40: 2025-11 | AC40: =IF(Z40="","", Z40 - WEEKDAY(Z40, 2) + 1) -> 45964 | AD40: =IF(Z40="","", WEEKDAY(Z40, 2)) -> 2
A41: 45965.86 | B41: Data Specialist Manage My Job Request a Coach | C41: Russell Tobin | D41: Boston, MA · 21 minutes ago · 0 applicants Promoted by hirer · Company review time is typically 1 week | E41: https://www.linkedin.com/jobs/view/4337718627/ | F41: =IFERROR(__xludf.DUMMYFUNCTION("""COMPUTED_VALUE"""),45965.86002314815) -> 45965.86 | G41: Nov 2025 | H41: 45 | I41: Tue | J41: =IF(A41<>"","No","") -> No | K41: =IF(A41<>"","No","") -> No | L41: =IFERROR(__xludf.DUMMYFUNCTION("""COMPUTED_VALUE"""),"Boston, MA") -> Boston, MA | M41: =IFERROR(__xludf.DUMMYFUNCTION("""COMPUTED_VALUE"""),"21 minutes ago") -> 21 minutes ago | N41: =IFERROR(__xludf.DUMMYFUNCTION("""COMPUTED_VALUE"""),21.0) -> 21 | P41: =IF(A41<>"","0","") -> 0 | R41: =IF(A41<>"","Review","") -> Review | Z41: 45965 | AA41: 2025-W45 | AB41: 2025-11 | AC41: =IF(Z41="","", Z41 - WEEKDAY(Z41, 2) + 1) -> 45964 | AD41: =IF(Z41="","", WEEKDAY(Z41, 2)) -> 2
A42: 45965.86 | B42: AI/Machine Learning Engineer Manage My Job Request a Coach | C42: Citizen Health | D42: San Mateo, CA · 20 minutes ago · 4 people clicked apply Promoted by hirer · Responses managed off LinkedIn | E42: https://www.linkedin.com/jobs/view/4334173239/ | F42: =IFERROR(__xludf.DUMMYFUNCTION("""COMPUTED_VALUE"""),45965.86023148148) -> 45965.86 | G42: Nov 2025 | H42: 45 | I42: Tue | J42: =IF(A42<>"","No","") -> No | K42: =IF(A42<>"","No","") -> No | L42: =IFERROR(__xludf.DUMMYFUNCTION("""COMPUTED_VALUE"""),"San Mateo, CA") -> San Mateo, CA | M42: =IFERROR(__xludf.DUMMYFUNCTION("""COMPUTED_VALUE"""),"20 minutes ago") -> 20 minutes ago | N42: =IFERROR(__xludf.DUMMYFUNCTION("""COMPUTED_VALUE"""),20.0) -> 20 | P42: =IF(A42<>"","0","") -> 0 | R42: Reject | Z42: 45965 | AA42: 2025-W45 | AB42: 2025-11 | AC42: =IF(Z42="","", Z42 - WEEKDAY(Z42, 2) + 1) -> 45964 | AD42: =IF(Z42="","", WEEKDAY(Z42, 2)) -> 2
A43: 45965.861 | B43: Product Analyst Manage My Job Request a Coach | C43: EVgo | D43: Los Angeles, CA · Reposted 15 minutes ago · Over 100 people clicked apply Promoted by hirer · Responses managed off LinkedIn | E43: https://www.linkedin.com/jobs/view/4311153416/ | F43: =IFERROR(__xludf.DUMMYFUNCTION("""COMPUTED_VALUE"""),45965.86141203704) -> 45965.861 | G43: Nov 2025 | H43: 45 | I43: Tue | J43: =IF(A43<>"","No","") -> No | K43: =IF(A43<>"","No","") -> No | L43: =IFERROR(__xludf.DUMMYFUNCTION("""COMPUTED_VALUE"""),"Los Angeles, CA") -> Los Angeles, CA | M43: =IFERROR(__xludf.DUMMYFUNCTION("""COMPUTED_VALUE"""),"Reposted 15 minutes ago") -> Reposted 15 minutes ago | N43: =IFERROR(__xludf.DUMMYFUNCTION("""COMPUTED_VALUE"""),15.0) -> 15 | P43: =IF(A43<>"","0","") -> 0 | R43: =IF(A43<>"","Review","") -> Review | Z43: 45965 | AA43: 2025-W45 | AB43: 2025-11 | AC43: =IF(Z43="","", Z43 - WEEKDAY(Z43, 2) + 1) -> 45964 | AD43: =IF(Z43="","", WEEKDAY(Z43, 2)) -> 2
A44: 45965.87 | B44: Full Stack developer Manage My Job Request a Coach | C44: Vertisystem (A MOURI Tech Company) | D44: Downey, CA · 29 minutes ago · 6 applicants Promoted by hirer · Company review time is typically 1 week | E44: https://www.linkedin.com/jobs/view/4334272664/ | F44: =IFERROR(__xludf.DUMMYFUNCTION("""COMPUTED_VALUE"""),45965.86974537037) -> 45965.87 | G44: Nov 2025 | H44: 45 | I44: Tue | J44: =IF(A44<>"","No","") -> No | K44: =IF(A44<>"","No","") -> No | L44: =IFERROR(__xludf.DUMMYFUNCTION("""COMPUTED_VALUE"""),"Downey, CA") -> Downey, CA | M44: =IFERROR(__xludf.DUMMYFUNCTION("""COMPUTED_VALUE"""),"29 minutes ago") -> 29 minutes ago | N44: =IFERROR(__xludf.DUMMYFUNCTION("""COMPUTED_VALUE"""),29.0) -> 29 | P44: =IF(A44<>"","0","") -> 0 | R44: =IF(A44<>"","Review","") -> Review | Z44: 45965 | AA44: 2025-W45 | AB44: 2025-11 | AC44: =IF(Z44="","", Z44 - WEEKDAY(Z44, 2) + 1) -> 45964 | AD44: =IF(Z44="","", WEEKDAY(Z44, 2)) -> 2
A45: 45965.881 | B45: Python Software Engineer Manage My Job Request a Coach | C45: ADPMN Inc | D45: Seattle, WA · 42 minutes ago · 7 people clicked apply Responses managed off LinkedIn | E45: https://www.linkedin.com/jobs/view/4334173362/ | F45: =IFERROR(__xludf.DUMMYFUNCTION("""COMPUTED_VALUE"""),45965.88082175926) -> 45965.881 | G45: Nov 2025 | H45: 45 | I45: Tue | J45: =IF(A45<>"","No","") -> No | K45: =IF(A45<>"","No","") -> No | L45: =IFERROR(__xludf.DUMMYFUNCTION("""COMPUTED_VALUE"""),"Seattle, WA") -> Seattle, WA | M45: =IFERROR(__xludf.DUMMYFUNCTION("""COMPUTED_VALUE"""),"42 minutes ago") -> 42 minutes ago | N45: =IFERROR(__xludf.DUMMYFUNCTION("""COMPUTED_VALUE"""),42.0) -> 42 | P45: =IF(A45<>"","0","") -> 0 | R45: =IF(A45<>"","Review","") -> Review | Z45: 45965 | AA45: 2025-W45 | AB45: 2025-11 | AC45: =IF(Z45="","", Z45 - WEEKDAY(Z45, 2) + 1) -> 45964 | AD45: =IF(Z45="","", WEEKDAY(Z45, 2)) -> 2
A46: 45965.881 | B46: Machine Learning Engineer Manage My Job Request a Coach | C46: Reducto | D46: San Francisco, CA · 27 minutes ago · 19 people clicked apply Promoted by hirer · Responses managed off LinkedIn | E46: https://www.linkedin.com/jobs/view/4334352218/ | F46: =IFERROR(__xludf.DUMMYFUNCTION("""COMPUTED_VALUE"""),45965.880949074075) -> 45965.881 | G46: Nov 2025 | H46: 45 | I46: Tue | J46: =IF(A46<>"","No","") -> No | K46: =IF(A46<>"","No","") -> No | L46: =IFERROR(__xludf.DUMMYFUNCTION("""COMPUTED_VALUE"""),"San Francisco, CA") -> San Francisco, CA | M46: =IFERROR(__xludf.DUMMYFUNCTION("""COMPUTED_VALUE"""),"27 minutes ago") -> 27 minutes ago | N46: =IFERROR(__xludf.DUMMYFUNCTION("""COMPUTED_VALUE"""),27.0) -> 27 | P46: =IF(A46<>"","0","") -> 0 | R46: =IF(A46<>"","Review","") -> Review | S46: Need to ask for Refferal | Z46: 45965 | AA46: 2025-W45 | AB46: 2025-11 | AC46: =IF(Z46="","", Z46 - WEEKDAY(Z46, 2) + 1) -> 45964 | AD46: =IF(Z46="","", WEEKDAY(Z46, 2)) -> 2
A47: 45965.883 | B47: Data Analyst - Strategy & Insights Operations Manage My Job Request a Coach | C47: Realty Income Corporation | D47: Del Mar, CA · Reposted 1 hour ago · Over 100 people clicked apply Promoted by hirer · Responses managed off LinkedIn | E47: https://www.linkedin.com/jobs/view/4331308619/ | F47: =IFERROR(__xludf.DUMMYFUNCTION("""COMPUTED_VALUE"""),45965.883368055554) -> 45965.883 | G47: Nov 2025 | H47: 45 | I47: Tue | J47: =IF(A47<>"","No","") -> No | K47: =IF(A47<>"","No","") -> No | L47: =IFERROR(__xludf.DUMMYFUNCTION("""COMPUTED_VALUE"""),"Del Mar, CA") -> Del Mar, CA | M47: =IFERROR(__xludf.DUMMYFUNCTION("""COMPUTED_VALUE"""),"Reposted 1 hour ago") -> Reposted 1 hour ago | N47: =IFERROR(__xludf.DUMMYFUNCTION("""COMPUTED_VALUE"""),1.0) -> 1 | P47: =IF(A47<>"","0","") -> 0 | R47: Reject | Z47: 45965 | AA47: 2025-W45 | AB47: 2025-11 | AC47: =IF(Z47="","", Z47 - WEEKDAY(Z47, 2) + 1) -> 45964 | AD47: =IF(Z47="","", WEEKDAY(Z47, 2)) -> 2
A48: 45965.887 | B48: Technical Data Analyst Manage My Job Request a Coach | C48: GreenPath Financial Wellness | D48: Farmington Hills, MI · 1 hour ago · 13 people clicked apply Promoted by hirer · Responses managed off LinkedIn | E48: https://www.linkedin.com/jobs/view/4334322099/ | F48: =IFERROR(__xludf.DUMMYFUNCTION("""COMPUTED_VALUE"""),45965.886516203704) -> 45965.887 | G48: Nov 2025 | H48: 45 | I48: Tue | J48: =IF(A48<>"","No","") -> No | K48: =IF(A48<>"","No","") -> No | L48: =IFERROR(__xludf.DUMMYFUNCTION("""COMPUTED_VALUE"""),"Farmington Hills, MI") -> Farmington Hills, MI | M48: =IFERROR(__xludf.DUMMYFUNCTION("""COMPUTED_VALUE"""),"1 hour ago") -> 1 hour ago | N48: =IFERROR(__xludf.DUMMYFUNCTION("""COMPUTED_VALUE"""),1.0) -> 1 | P48: =IF(A48<>"","0","") -> 0 | R48: =IF(A48<>"","Review","") -> Review | Z48: 45965 | AA48: 2025-W45 | AB48: 2025-11 | AC48: =IF(Z48="","", Z48 - WEEKDAY(Z48, 2) + 1) -> 45964 | AD48: =IF(Z48="","", WEEKDAY(Z48, 2)) -> 2
A49: 45965.895 | B49: Senior Data Analyst Manage My Job Request a Coach | C49: IDEXX | D49: Portland, ME · 57 minutes ago · 10 people clicked apply Promoted by hirer · Responses managed off LinkedIn | E49: https://www.linkedin.com/jobs/view/4334302426/ | F49: =IFERROR(__xludf.DUMMYFUNCTION("""COMPUTED_VALUE"""),45965.89454861111) -> 45965.895 | G49: Nov 2025 | H49: 45 | I49: Tue | J49: =IF(A49<>"","No","") -> No | K49: =IF(A49<>"","No","") -> No | L49: =IFERROR(__xludf.DUMMYFUNCTION("""COMPUTED_VALUE"""),"Portland, ME") -> Portland, ME | M49: =IFERROR(__xludf.DUMMYFUNCTION("""COMPUTED_VALUE"""),"57 minutes ago") -> 57 minutes ago | N49: =IFERROR(__xludf.DUMMYFUNCTION("""COMPUTED_VALUE"""),57.0) -> 57 | P49: =IF(A49<>"","0","") -> 0 | R49: =IF(A49<>"","Review","") -> Review | Z49: 45965 | AA49: 2025-W45 | AB49: 2025-11 | AC49: =IF(Z49="","", Z49 - WEEKDAY(Z49, 2) + 1) -> 45964 | AD49: =IF(Z49="","", WEEKDAY(Z49, 2)) -> 2
A50: 45965.897 | B50: Sr Data Engineer Manage My Job Request a Coach | C50: Aquent | D50: Salem, OR · Reposted 1 hour ago · 4 people clicked apply Promoted by hirer · Responses managed off LinkedIn | E50: https://www.linkedin.com/jobs/view/4334272463/ | F50: =IFERROR(__xludf.DUMMYFUNCTION("""COMPUTED_VALUE"""),45965.897361111114) -> 45965.897 | G50: Nov 2025 | H50: 45 | I50: Tue | J50: =IF(A50<>"","No","") -> No | K50: =IF(A50<>"","No","") -> No | L50: =IFERROR(__xludf.DUMMYFUNCTION("""COMPUTED_VALUE"""),"Salem, OR") -> Salem, OR | M50: =IFERROR(__xludf.DUMMYFUNCTION("""COMPUTED_VALUE"""),"Reposted 1 hour ago") -> Reposted 1 hour ago | N50: =IFERROR(__xludf.DUMMYFUNCTION("""COMPUTED_VALUE"""),1.0) -> 1 | P50: =IF(A50<>"","0","") -> 0 | R50: =IF(A50<>"","Review","") -> Review | Z50: 45965 | AA50: 2025-W45 | AB50: 2025-11 | AC50: =IF(Z50="","", Z50 - WEEKDAY(Z50, 2) + 1) -> 45964 | AD50: =IF(Z50="","", WEEKDAY(Z50, 2)) -> 2
A51: 45965.921 | B51: Data Engineer Manage My Job Request a Coach | C51: Vivanti Consulting | D51: New York, United States · 1 hour ago · 24 people clicked apply Promoted by hirer · Responses managed off LinkedIn | E51: https://www.linkedin.com/jobs/view/4320830587/ | F51: =IFERROR(__xludf.DUMMYFUNCTION("""COMPUTED_VALUE"""),45965.92128472222) -> 45965.921 | G51: Nov 2025 | H51: 45 | I51: Tue | J51: Yes | K51: Yes | L51: =IFERROR(__xludf.DUMMYFUNCTION("""COMPUTED_VALUE"""),"New York, United States") -> New York, United States | M51: =IFERROR(__xludf.DUMMYFUNCTION("""COMPUTED_VALUE"""),"1 hour ago") -> 1 hour ago | N51: =IFERROR(__xludf.DUMMYFUNCTION("""COMPUTED_VALUE"""),1.0) -> 1 | P51: =IF(A51<>"","0","") -> 0 | Q51: Vamsi Krishna Sundaraneedi | R51: OA | S51: Automoted OA * 6 | Z51: 45965 | AA51: 2025-W45 | AB51: 2025-11 | AC51: =IF(Z51="","", Z51 - WEEKDAY(Z51, 2) + 1) -> 45964 | AD51: =IF(Z51="","", WEEKDAY(Z51, 2)) -> 2
A52: 45966.977 | B52: Senior Software Engineer | C52: TBD | D52: New York, NY · 9 minutes ago · 1 applicant Promoted by hirer · No response insights available yet | E52: https://www.linkedin.com/jobs/view/4337874133/ | F52: =IFERROR(__xludf.DUMMYFUNCTION("""COMPUTED_VALUE"""),45966.97725694445) -> 45966.977 | G52: Nov 2025 | H52: 45 | I52: Wed | J52: =IF(A52<>"","No","") -> No | K52: =IF(A52<>"","No","") -> No | L52: =IFERROR(__xludf.DUMMYFUNCTION("""COMPUTED_VALUE"""),"New York, NY") -> New York, NY | M52: =IFERROR(__xludf.DUMMYFUNCTION("""COMPUTED_VALUE"""),"9 minutes ago") -> 9 minutes ago | N52: =IFERROR(__xludf.DUMMYFUNCTION("""COMPUTED_VALUE"""),9.0) -> 9 | P52: =IF(A52<>"","0","") -> 0 | R52: =IF(A52<>"","Review","") -> Review | Z52: 45966 | AA52: 2025-W45 | AB52: 2025-11 | AC52: =IF(Z52="","", Z52 - WEEKDAY(Z52, 2) + 1) -> 45964 | AD52: =IF(Z52="","", WEEKDAY(Z52, 2)) -> 3
A53: 45967.017 | B53: Software Development Engineer Manage My Job Request a Coach | C53: Adobe | D53: San Jose, CA · 1 hour ago · 35 people clicked apply Promoted by hirer · Responses managed off LinkedIn | E53: https://www.linkedin.com/jobs/view/4337954703/ | F53: =IFERROR(__xludf.DUMMYFUNCTION("""COMPUTED_VALUE"""),45967.01736111111) -> 45967.017 | G53: Nov 2025 | H53: 45 | I53: Thu | J53: =IF(A53<>"","No","") -> No | K53: Yes | L53: =IFERROR(__xludf.DUMMYFUNCTION("""COMPUTED_VALUE"""),"San Jose, CA") -> San Jose, CA | M53: =IFERROR(__xludf.DUMMYFUNCTION("""COMPUTED_VALUE"""),"1 hour ago") -> 1 hour ago | N53: =IFERROR(__xludf.DUMMYFUNCTION("""COMPUTED_VALUE"""),1.0) -> 1 | P53: =IF(A53<>"","0","") -> 0 | R53: Reject | Z53: 45967 | AA53: 2025-W45 | AB53: 2025-11 | AC53: =IF(Z53="","", Z53 - WEEKDAY(Z53, 2) + 1) -> 45964 | AD53: =IF(Z53="","", WEEKDAY(Z53, 2)) -> 4
A54: 45967.029 | B54: Software Development Engineer Manage My Job Request a Coach | C54: Adobe | D54: San Jose, CA · 1 hour ago · 36 people clicked apply Promoted by hirer · Responses managed off LinkedIn | E54: https://www.linkedin.com/jobs/view/4337875028/ | F54: =IFERROR(__xludf.DUMMYFUNCTION("""COMPUTED_VALUE"""),45967.029340277775) -> 45967.029 | G54: Nov 2025 | H54: 45 | I54: Thu | J54: =IF(A54<>"","No","") -> No | K54: Yes | L54: =IFERROR(__xludf.DUMMYFUNCTION("""COMPUTED_VALUE"""),"San Jose, CA") -> San Jose, CA | M54: =IFERROR(__xludf.DUMMYFUNCTION("""COMPUTED_VALUE"""),"1 hour ago") -> 1 hour ago | N54: =IFERROR(__xludf.DUMMYFUNCTION("""COMPUTED_VALUE"""),1.0) -> 1 | P54: =IF(A54<>"","0","") -> 0 | R54: Reject | Z54: 45967 | AA54: 2025-W45 | AB54: 2025-11 | AC54: =IF(Z54="","", Z54 - WEEKDAY(Z54, 2) + 1) -> 45964 | AD54: =IF(Z54="","", WEEKDAY(Z54, 2)) -> 4
A55: 45967.053 | B55: ML Engineer Manage My Job Request a Coach | C55: Tata Consultancy Services | D55: Cupertino, CA · 1 hour ago · 14 people clicked apply Promoted by hirer · Responses managed off LinkedIn | E55: https://www.linkedin.com/jobs/view/4337885105/ | F55: =IFERROR(__xludf.DUMMYFUNCTION("""COMPUTED_VALUE"""),45967.053125) -> 45967.053 | G55: Nov 2025 | H55: 45 | I55: Thu | J55: =IF(A55<>"","No","") -> No | K55: =IF(A55<>"","No","") -> No | L55: =IFERROR(__xludf.DUMMYFUNCTION("""COMPUTED_VALUE"""),"Cupertino, CA") -> Cupertino, CA | M55: =IFERROR(__xludf.DUMMYFUNCTION("""COMPUTED_VALUE"""),"1 hour ago") -> 1 hour ago | N55: =IFERROR(__xludf.DUMMYFUNCTION("""COMPUTED_VALUE"""),1.0) -> 1 | P55: =IF(A55<>"","0","") -> 0 | R55: =IF(A55<>"","Review","") -> Review | Z55: 45967 | AA55: 2025-W45 | AB55: 2025-11 | AC55: =IF(Z55="","", Z55 - WEEKDAY(Z55, 2) + 1) -> 45964 | AD55: =IF(Z55="","", WEEKDAY(Z55, 2)) -> 4
A56: 45967.054 | B56: Jr. Java Engineer (remote) | C56: Claritev | D56: Naperville, IL | E56: https://www.linkedin.com/jobs/view/4337965058/ | F56: =IFERROR(__xludf.DUMMYFUNCTION("""COMPUTED_VALUE"""),45967.053564814814) -> 45967.054 | G56: Nov 2025 | H56: 45 | I56: Thu | J56: =IF(A56<>"","No","") -> No | K56: Yes | L56: =IFERROR(__xludf.DUMMYFUNCTION("""COMPUTED_VALUE"""),"Naperville, IL") -> Naperville, IL | M56: =IFERROR(__xludf.DUMMYFUNCTION("""COMPUTED_VALUE"""),"") | N56: =IFERROR(__xludf.DUMMYFUNCTION("""COMPUTED_VALUE"""),"") | P56: 5 | Q56: Min Zou | R56: Reject | Z56: 45967 | AA56: 2025-W45 | AB56: 2025-11 | AC56: =IF(Z56="","", Z56 - WEEKDAY(Z56, 2) + 1) -> 45964 | AD56: =IF(Z56="","", WEEKDAY(Z56, 2)) -> 4
A57: 45967.07 | B57: Jr. Java Engineer (remote) Manage My Job Request a Coach | C57: Claritev | D57: Bedford, MA · 1 hour ago · 28 people clicked apply Promoted by hirer · Responses managed off LinkedIn | E57: https://www.linkedin.com/jobs/view/4337885244/ | F57: =IFERROR(__xludf.DUMMYFUNCTION("""COMPUTED_VALUE"""),45967.07048611111) -> 45967.07 | G57: Nov 2025 | H57: 45 | I57: Thu | J57: =IF(A57<>"","No","") -> No | K57: Yes | L57: =IFERROR(__xludf.DUMMYFUNCTION("""COMPUTED_VALUE"""),"Bedford, MA") -> Bedford, MA | M57: =IFERROR(__xludf.DUMMYFUNCTION("""COMPUTED_VALUE"""),"1 hour ago") -> 1 hour ago | N57: =IFERROR(__xludf.DUMMYFUNCTION("""COMPUTED_VALUE"""),1.0) -> 1 | P57: =IF(A57<>"","0","") -> 0 | R57: Reject | Z57: 45967 | AA57: 2025-W45 | AB57: 2025-11 | AC57: =IF(Z57="","", Z57 - WEEKDAY(Z57, 2) + 1) -> 45964 | AD57: =IF(Z57="","", WEEKDAY(Z57, 2)) -> 4
A58: 45967.071 | B58: Entry Level Frontend Developer Manage My Job Request a Coach | C58: Revature | D58: New Jersey, United States · 55 minutes ago · 7 people clicked apply Promoted by hirer · Responses managed off LinkedIn | E58: https://www.linkedin.com/jobs/view/4337935174/ | F58: =IFERROR(__xludf.DUMMYFUNCTION("""COMPUTED_VALUE"""),45967.070763888885) -> 45967.071 | G58: Nov 2025 | H58: 45 | I58: Thu | J58: =IF(A58<>"","No","") -> No | K58: =IF(A58<>"","No","") -> No | L58: =IFERROR(__xludf.DUMMYFUNCTION("""COMPUTED_VALUE"""),"New Jersey, United States") -> New Jersey, United States | M58: =IFERROR(__xludf.DUMMYFUNCTION("""COMPUTED_VALUE"""),"55 minutes ago") -> 55 minutes ago | N58: =IFERROR(__xludf.DUMMYFUNCTION("""COMPUTED_VALUE"""),55.0) -> 55 | P58: =IF(A58<>"","0","") -> 0 | R58: =IF(A58<>"","Review","") -> Review | Z58: 45967 | AA58: 2025-W45 | AB58: 2025-11 | AC58: =IF(Z58="","", Z58 - WEEKDAY(Z58, 2) + 1) -> 45964 | AD58: =IF(Z58="","", WEEKDAY(Z58, 2)) -> 4
A59: 45967.072 | B59: Entry Level .NET Developer Manage My Job Request a Coach | C59: Revature | D59: Plano, TX · 1 hour ago · 3 people clicked apply Promoted by hirer · Responses managed off LinkedIn | E59: https://www.linkedin.com/jobs/view/4337925163/ | F59: =IFERROR(__xludf.DUMMYFUNCTION("""COMPUTED_VALUE"""),45967.07158564815) -> 45967.072 | G59: Nov 2025 | H59: 45 | I59: Thu | J59: =IF(A59<>"","No","") -> No | K59: =IF(A59<>"","No","") -> No | L59: =IFERROR(__xludf.DUMMYFUNCTION("""COMPUTED_VALUE"""),"Plano, TX") -> Plano, TX | M59: =IFERROR(__xludf.DUMMYFUNCTION("""COMPUTED_VALUE"""),"1 hour ago") -> 1 hour ago | N59: =IFERROR(__xludf.DUMMYFUNCTION("""COMPUTED_VALUE"""),1.0) -> 1 | P59: =IF(A59<>"","0","") -> 0 | R59: =IF(A59<>"","Review","") -> Review | Z59: 45967 | AA59: 2025-W45 | AB59: 2025-11 | AC59: =IF(Z59="","", Z59 - WEEKDAY(Z59, 2) + 1) -> 45964 | AD59: =IF(Z59="","", WEEKDAY(Z59, 2)) -> 4
A60: 45967.072 | B60: Entry level Data Engineers Manage My Job Request a Coach | C60: Revature | D60: Dallas, TX · 58 minutes ago · 9 people clicked apply Promoted by hirer · Responses managed off LinkedIn | E60: https://www.linkedin.com/jobs/view/4337955185/ | F60: =IFERROR(__xludf.DUMMYFUNCTION("""COMPUTED_VALUE"""),45967.07209490741) -> 45967.072 | G60: Nov 2025 | H60: 45 | I60: Thu | J60: =IF(A60<>"","No","") -> No | K60: =IF(A60<>"","No","") -> No | L60: =IFERROR(__xludf.DUMMYFUNCTION("""COMPUTED_VALUE"""),"Dallas, TX") -> Dallas, TX | M60: =IFERROR(__xludf.DUMMYFUNCTION("""COMPUTED_VALUE"""),"58 minutes ago") -> 58 minutes ago | N60: =IFERROR(__xludf.DUMMYFUNCTION("""COMPUTED_VALUE"""),58.0) -> 58 | P60: =IF(A60<>"","0","") -> 0 | R60: =IF(A60<>"","Review","") -> Review | Z60: 45967 | AA60: 2025-W45 | AB60: 2025-11 | AC60: =IF(Z60="","", Z60 - WEEKDAY(Z60, 2) + 1) -> 45964 | AD60: =IF(Z60="","", WEEKDAY(Z60, 2)) -> 4
A61: 45967.087 | B61: Front End Developer Manage My Job Request a Coach | C61: Wright Manufacturing Inc | D61: Frederick, MD · 9 minutes ago · 2 applicants Promoted by hirer · No response insights available yet | E61: https://www.linkedin.com/jobs/view/4337866056/ | F61: =IFERROR(__xludf.DUMMYFUNCTION("""COMPUTED_VALUE"""),45967.087488425925) -> 45967.087 | G61: Nov 2025 | H61: 45 | I61: Thu | J61: =IF(A61<>"","No","") -> No | K61: =IF(A61<>"","No","") -> No | L61: =IFERROR(__xludf.DUMMYFUNCTION("""COMPUTED_VALUE"""),"Frederick, MD") -> Frederick, MD | M61: =IFERROR(__xludf.DUMMYFUNCTION("""COMPUTED_VALUE"""),"9 minutes ago") -> 9 minutes ago | N61: =IFERROR(__xludf.DUMMYFUNCTION("""COMPUTED_VALUE"""),9.0) -> 9 | P61: =IF(A61<>"","0","") -> 0 | R61: =IF(A61<>"","Review","") -> Review | Z61: 45967 | AA61: 2025-W45 | AB61: 2025-11 | AC61: =IF(Z61="","", Z61 - WEEKDAY(Z61, 2) + 1) -> 45964 | AD61: =IF(Z61="","", WEEKDAY(Z61, 2)) -> 4
A62: 45967.474 | B62: Software Engineer 1 Manage My Job Request a Coach | C62: Intuit | D62: Mountain View, CA · 10 minutes ago · 98 people clicked apply Promoted by hirer · Responses managed off LinkedIn | E62: https://www.linkedin.com/jobs/view/4334568052/ | F62: =IFERROR(__xludf.DUMMYFUNCTION("""COMPUTED_VALUE"""),45967.47357638889) -> 45967.474 | G62: Nov 2025 | H62: 45 | I62: Thu | J62: =IF(A62<>"","No","") -> No | K62: Yes | L62: =IFERROR(__xludf.DUMMYFUNCTION("""COMPUTED_VALUE"""),"Mountain View, CA") -> Mountain View, CA | M62: =IFERROR(__xludf.DUMMYFUNCTION("""COMPUTED_VALUE"""),"10 minutes ago") -> 10 minutes ago | N62: =IFERROR(__xludf.DUMMYFUNCTION("""COMPUTED_VALUE"""),10.0) -> 10 | P62: 10 | R62: =IF(A62<>"","Review","") -> Review | Z62: 45967 | AA62: 2025-W45 | AB62: 2025-11 | AC62: =IF(Z62="","", Z62 - WEEKDAY(Z62, 2) + 1) -> 45964 | AD62: =IF(Z62="","", WEEKDAY(Z62, 2)) -> 4
A63: 45967.474 | B63: Database Programmer – NCCT CTMC Informatics | C63: Atrium Health | D63: North Carolina | E63: https://aah.wd5.myworkdayjobs.com/en-US/External/job/Database-Programmer---NCCT-CTMC-Informatics_R190441 | F63: =IFERROR(__xludf.DUMMYFUNCTION("""COMPUTED_VALUE"""),45967.47357638889) -> 45967.474 | G63: Nov 2025 | H63: 45 | I63: Thu | J63: =IF(A63<>"","No","") -> No | K63: Yes | L63: =IFERROR(__xludf.DUMMYFUNCTION("""COMPUTED_VALUE"""),"North Carolina") -> North Carolina | M63: =IFERROR(__xludf.DUMMYFUNCTION("""COMPUTED_VALUE"""),"") | N63: =IFERROR(__xludf.DUMMYFUNCTION("""COMPUTED_VALUE"""),"") | P63: =IF(A63<>"","0","") -> 0 | R63: =IF(A63<>"","Review","") -> Review | Z63: 45967 | AA63: 2025-W45 | AB63: 2025-11 | AC63: =IF(Z63="","", Z63 - WEEKDAY(Z63, 2) + 1) -> 45964 | AD63: =IF(Z63="","", WEEKDAY(Z63, 2)) -> 4
A64: 45968.003 | B64: Software Engineer, Backend Manage My Job Request a Coach | C64: Rivian | D64: Palo Alto, CA · 42 minutes ago · 39 people clicked apply Promoted by hirer · Responses managed off LinkedIn | E64: https://www.linkedin.com/jobs/view/4334713570/ | F64: =IFERROR(__xludf.DUMMYFUNCTION("""COMPUTED_VALUE"""),45968.00278935185) -> 45968.003 | G64: Nov 2025 | H64: 45 | I64: Fri | J64: =IF(A64<>"","No","") -> No | K64: =IF(A64<>"","No","") -> No | L64: =IFERROR(__xludf.DUMMYFUNCTION("""COMPUTED_VALUE"""),"Palo Alto, CA") -> Palo Alto, CA | M64: =IFERROR(__xludf.DUMMYFUNCTION("""COMPUTED_VALUE"""),"42 minutes ago") -> 42 minutes ago | N64: =IFERROR(__xludf.DUMMYFUNCTION("""COMPUTED_VALUE"""),42.0) -> 42 | P64: =IF(A64<>"","0","") -> 0 | R64: Reject | Z64: 45968 | AA64: 2025-W45 | AB64: 2025-11 | AC64: =IF(Z64="","", Z64 - WEEKDAY(Z64, 2) + 1) -> 45964 | AD64: =IF(Z64="","", WEEKDAY(Z64, 2)) -> 5
A65: 45968.012 | B65: AI Engineer (Mid-Senior Level) Manage My Job Request a Coach | C65: Banyan Infrastructure | D65: San Francisco, CA · 21 minutes ago · 2 people clicked apply Responses managed off LinkedIn | E65: https://www.linkedin.com/jobs/view/4337992338/ | F65: =IFERROR(__xludf.DUMMYFUNCTION("""COMPUTED_VALUE"""),45968.01212962963) -> 45968.012 | G65: Nov 2025 | H65: 45 | I65: Fri | J65: =IF(A65<>"","No","") -> No | K65: =IF(A65<>"","No","") -> No | L65: =IFERROR(__xludf.DUMMYFUNCTION("""COMPUTED_VALUE"""),"San Francisco, CA") -> San Francisco, CA | M65: =IFERROR(__xludf.DUMMYFUNCTION("""COMPUTED_VALUE"""),"21 minutes ago") -> 21 minutes ago | N65: =IFERROR(__xludf.DUMMYFUNCTION("""COMPUTED_VALUE"""),21.0) -> 21 | P65: =IF(A65<>"","0","") -> 0 | R65: =IF(A65<>"","Review","") -> Review | Z65: 45968 | AA65: 2025-W45 | AB65: 2025-11 | AC65: =IF(Z65="","", Z65 - WEEKDAY(Z65, 2) + 1) -> 45964 | AD65: =IF(Z65="","", WEEKDAY(Z65, 2)) -> 5
A66: 45968.88 | B66: Electrical Estimator | C66: Hatzel & Buehler, Inc | D66: Hauppauge, NY | E66: https://www.linkedin.com/jobs/view/4333908596/ | F66: =IFERROR(__xludf.DUMMYFUNCTION("""COMPUTED_VALUE"""),45968.879895833335) -> 45968.88 | G66: Nov 2025 | H66: 45 | I66: Fri | J66: =IF(A66<>"","No","") -> No | K66: =IF(A66<>"","No","") -> No | L66: =IFERROR(__xludf.DUMMYFUNCTION("""COMPUTED_VALUE"""),"Hauppauge, NY") -> Hauppauge, NY | M66: =IFERROR(__xludf.DUMMYFUNCTION("""COMPUTED_VALUE"""),"") | N66: =IFERROR(__xludf.DUMMYFUNCTION("""COMPUTED_VALUE"""),"") | P66: =IF(A66<>"","0","") -> 0 | R66: =IF(A66<>"","Review","") -> Review | Z66: 45968 | AA66: 2025-W45 | AB66: 2025-11 | AC66: =IF(Z66="","", Z66 - WEEKDAY(Z66, 2) + 1) -> 45964 | AD66: =IF(Z66="","", WEEKDAY(Z66, 2)) -> 5
A67: 45969.997 | B67: Software Engineer Manage My Job Request a Coach | C67: Benchmark | D67: New York, NY · 1 month ago · Over 100 applicants Promoted by hirer · Actively reviewing applicants | E67: https://www.linkedin.com/jobs/view/4310415694/ | F67: =IFERROR(__xludf.DUMMYFUNCTION("""COMPUTED_VALUE"""),45969.997094907405) -> 45969.997 | G67: Nov 2025 | H67: 45 | I67: Sat | J67: =IF(A67<>"","No","") -> No | K67: =IF(A67<>"","No","") -> No | L67: =IFERROR(__xludf.DUMMYFUNCTION("""COMPUTED_VALUE"""),"New York, NY") -> New York, NY | M67: =IFERROR(__xludf.DUMMYFUNCTION("""COMPUTED_VALUE"""),"1 month ago") -> 1 month ago | N67: =IFERROR(__xludf.DUMMYFUNCTION("""COMPUTED_VALUE"""),1.0) -> 1 | P67: =IF(A67<>"","0","") -> 0 | R67: =IF(A67<>"","Review","") -> Review | Z67: 45969 | AA67: 2025-W45 | AB67: 2025-11 | AC67: =IF(Z67="","", Z67 - WEEKDAY(Z67, 2) + 1) -> 45964 | AD67: =IF(Z67="","", WEEKDAY(Z67, 2)) -> 6
A68: 11/13/2025, 12:00:00 AM | B68: Software Engineer | C68: Miller Cooper | D68: Remote | E68: https://millercooper.atsondemand.com/#/jobDescription/904556 | F68: =IFERROR(__xludf.DUMMYFUNCTION("""COMPUTED_VALUE"""),45974.0) -> 45974 | G68: Nov 2025 | H68: 46 | I68: Thu | J68: =IF(A68<>"","No","") -> No | K68: =IF(A68<>"","No","") -> No | L68: =IFERROR(__xludf.DUMMYFUNCTION("""COMPUTED_VALUE"""),"Remote") -> Remote | M68: =IFERROR(__xludf.DUMMYFUNCTION("""COMPUTED_VALUE"""),"") | N68: =IFERROR(__xludf.DUMMYFUNCTION("""COMPUTED_VALUE"""),"") | P68: =IF(A68<>"","0","") -> 0 | R68: =IF(A68<>"","Review","") -> Review | Z68: 45974 | AA68: 2025-W46 | AB68: 2025-11 | AC68: =IF(Z68="","", Z68 - WEEKDAY(Z68, 2) + 1) -> 45971 | AD68: =IF(Z68="","", WEEKDAY(Z68, 2)) -> 4
A69: No rows marked done | F69: =IFERROR(__xludf.DUMMYFUNCTION("""COMPUTED_VALUE"""),"") | J69: =IF(A69<>"","No","") -> No | K69: =IF(A69<>"","No","") -> No | L69: =IFERROR(__xludf.DUMMYFUNCTION("""COMPUTED_VALUE"""),"") | M69: =IFERROR(__xludf.DUMMYFUNCTION("""COMPUTED_VALUE"""),"") | N69: =IFERROR(__xludf.DUMMYFUNCTION("""COMPUTED_VALUE"""),"") | P69: =IF(A69<>"","0","") -> 0 | R69: =IF(A69<>"","Review","") -> Review | AC69: =IF(Z69="","", Z69 - WEEKDAY(Z69, 2) + 1) | AD69: =IF(Z69="","", WEEKDAY(Z69, 2))
A70: 45975.53 | B70: Data Scientist - New Grad (2026 Start) Manage My Job Request a Coach | C70: Databricks | D70: Mountain View, CA · Reposted 7 hours ago · Over 100 people clicked apply Promoted by hirer · Responses managed off LinkedIn | E70: https://www.linkedin.com/jobs/view/4297746037/ | F70: =IFERROR(__xludf.DUMMYFUNCTION("""COMPUTED_VALUE"""),45975.52956018518) -> 45975.53 | G70: Nov 2025 | H70: 46 | I70: Fri | J70: =IF(A70<>"","No","") -> No | K70: =IF(A70<>"","No","") -> No | L70: =IFERROR(__xludf.DUMMYFUNCTION("""COMPUTED_VALUE"""),"Mountain View, CA") -> Mountain View, CA | M70: =IFERROR(__xludf.DUMMYFUNCTION("""COMPUTED_VALUE"""),"Reposted 7 hours ago") -> Reposted 7 hours ago | N70: =IFERROR(__xludf.DUMMYFUNCTION("""COMPUTED_VALUE"""),7.0) -> 7 | P70: =IF(A70<>"","0","") -> 0 | R70: =IF(A70<>"","Review","") -> Review | Z70: 45975 | AA70: 2025-W46 | AB70: 2025-11 | AC70: =IF(Z70="","", Z70 - WEEKDAY(Z70, 2) + 1) -> 45971 | AD70: =IF(Z70="","", WEEKDAY(Z70, 2)) -> 5
A71: 45975.537 | B71: Quality Engineer Manage My Job Request a Coach | C71: Oerlikon | D71: Westbury, NY · Reposted 7 hours ago · 46 people clicked apply Promoted by hirer · Responses managed off LinkedIn | E71: https://www.linkedin.com/jobs/view/4306806143/ | F71: =IFERROR(__xludf.DUMMYFUNCTION("""COMPUTED_VALUE"""),45975.53722222222) -> 45975.537 | G71: Nov 2025 | H71: 46 | I71: Fri | J71: =IF(A71<>"","No","") -> No | K71: =IF(A71<>"","No","") -> No | L71: =IFERROR(__xludf.DUMMYFUNCTION("""COMPUTED_VALUE"""),"Westbury, NY") -> Westbury, NY | M71: =IFERROR(__xludf.DUMMYFUNCTION("""COMPUTED_VALUE"""),"Reposted 7 hours ago") -> Reposted 7 hours ago | N71: =IFERROR(__xludf.DUMMYFUNCTION("""COMPUTED_VALUE"""),7.0) -> 7 | P71: =IF(A71<>"","0","") -> 0 | R71: =IF(A71<>"","Review","") -> Review | Z71: 45975 | AA71: 2025-W46 | AB71: 2025-11 | AC71: =IF(Z71="","", Z71 - WEEKDAY(Z71, 2) + 1) -> 45971 | AD71: =IF(Z71="","", WEEKDAY(Z71, 2)) -> 5
A72: 45975.537 | B72: Software Engineer Manage My Job Request a Coach | C72: Akamai Technologies | D72: United States · 1 minute ago · 0 people clicked apply Promoted by hirer · Responses managed off LinkedIn | E72: https://www.linkedin.com/jobs/view/4336231580/ | F72: =IFERROR(__xludf.DUMMYFUNCTION("""COMPUTED_VALUE"""),45975.53743055555) -> 45975.537 | G72: Nov 2025 | H72: 46 | I72: Fri | J72: =IF(A72<>"","No","") -> No | K72: =IF(A72<>"","No","") -> No | L72: =IFERROR(__xludf.DUMMYFUNCTION("""COMPUTED_VALUE"""),"United States") -> United States | M72: =IFERROR(__xludf.DUMMYFUNCTION("""COMPUTED_VALUE"""),"1 minute ago") -> 1 minute ago | N72: =IFERROR(__xludf.DUMMYFUNCTION("""COMPUTED_VALUE"""),1.0) -> 1 | P72: =IF(A72<>"","0","") -> 0 | R72: Under Consideration | Z72: 45975 | AA72: 2025-W46 | AB72: 2025-11 | AC72: =IF(Z72="","", Z72 - WEEKDAY(Z72, 2) + 1) -> 45971 | AD72: =IF(Z72="","", WEEKDAY(Z72, 2)) -> 5
A73: 45975.884 | B73: Software Engineer Backend/Platform Systems I (Full Time) – United States Manage My Job Request a Coach | C73: Cisco | D73: Fulton, MD · 19 minutes ago · 6 people clicked apply Promoted by hirer · Responses managed off LinkedIn | E73: https://www.linkedin.com/jobs/view/4336294749/ | F73: =IFERROR(__xludf.DUMMYFUNCTION("""COMPUTED_VALUE"""),45975.88449074074) -> 45975.884 | G73: Nov 2025 | H73: 46 | I73: Fri | J73: =IF(A73<>"","No","") -> No | K73: =IF(A73<>"","No","") -> No | L73: =IFERROR(__xludf.DUMMYFUNCTION("""COMPUTED_VALUE"""),"Fulton, MD") -> Fulton, MD | M73: =IFERROR(__xludf.DUMMYFUNCTION("""COMPUTED_VALUE"""),"19 minutes ago") -> 19 minutes ago | N73: =IFERROR(__xludf.DUMMYFUNCTION("""COMPUTED_VALUE"""),19.0) -> 19 | P73: =IF(A73<>"","0","") -> 0 | R73: =IF(A73<>"","Review","") -> Review | Z73: 45975 | AA73: 2025-W46 | AB73: 2025-11 | AC73: =IF(Z73="","", Z73 - WEEKDAY(Z73, 2) + 1) -> 45971 | AD73: =IF(Z73="","", WEEKDAY(Z73, 2)) -> 5
A74: 45975.886 | B74: Machine Learning Engineer, Strategy & Supply Optimization | C74: DoorDash | D74: San Francisco, CA · 46 minutes ago · 0 people clicked apply Promoted by hirer · Responses managed off LinkedIn | E74: https://www.linkedin.com/jobs/view/4340833443/ | F74: =IFERROR(__xludf.DUMMYFUNCTION("""COMPUTED_VALUE"""),45975.88605324074) -> 45975.886 | G74: Nov 2025 | H74: 46 | I74: Fri | J74: =IF(A74<>"","No","") -> No | K74: =IF(A74<>"","No","") -> No | L74: =IFERROR(__xludf.DUMMYFUNCTION("""COMPUTED_VALUE"""),"San Francisco, CA") -> San Francisco, CA | M74: =IFERROR(__xludf.DUMMYFUNCTION("""COMPUTED_VALUE"""),"46 minutes ago") -> 46 minutes ago | N74: =IFERROR(__xludf.DUMMYFUNCTION("""COMPUTED_VALUE"""),46.0) -> 46 | P74: =IF(A74<>"","0","") -> 0 | R74: =IF(A74<>"","Review","") -> Review | Z74: 45975 | AA74: 2025-W46 | AB74: 2025-11 | AC74: =IF(Z74="","", Z74 - WEEKDAY(Z74, 2) + 1) -> 45971 | AD74: =IF(Z74="","", WEEKDAY(Z74, 2)) -> 5
A75: 45975.887 | B75: Software Engineer Manage My Job Request a Coach | C75: Lowe's Companies, Inc. | D75: Charlotte, NC · 47 minutes ago · 5 people clicked apply Responses managed off LinkedIn | E75: https://www.linkedin.com/jobs/view/4322675546/ | F75: =IFERROR(__xludf.DUMMYFUNCTION("""COMPUTED_VALUE"""),45975.8872337963) -> 45975.887 | G75: Nov 2025 | H75: 46 | I75: Fri | J75: =IF(A75<>"","No","") -> No | K75: =IF(A75<>"","No","") -> No | L75: =IFERROR(__xludf.DUMMYFUNCTION("""COMPUTED_VALUE"""),"Charlotte, NC") -> Charlotte, NC | M75: =IFERROR(__xludf.DUMMYFUNCTION("""COMPUTED_VALUE"""),"47 minutes ago") -> 47 minutes ago | N75: =IFERROR(__xludf.DUMMYFUNCTION("""COMPUTED_VALUE"""),47.0) -> 47 | P75: =IF(A75<>"","0","") -> 0 | R75: =IF(A75<>"","Review","") -> Review | Z75: 45975 | AA75: 2025-W46 | AB75: 2025-11 | AC75: =IF(Z75="","", Z75 - WEEKDAY(Z75, 2) + 1) -> 45971 | AD75: =IF(Z75="","", WEEKDAY(Z75, 2)) -> 5
A76: 45975.892 | B76: (USA) Senior, Data Engineer Manage My Job Request a Coach | C76: Walmart | D76: Sunnyvale, CA · 20 minutes ago · 4 people clicked apply Promoted by hirer · Responses managed off LinkedIn | E76: https://www.linkedin.com/jobs/view/4340554040/ | F76: =IFERROR(__xludf.DUMMYFUNCTION("""COMPUTED_VALUE"""),45975.89199074074) -> 45975.892 | G76: Nov 2025 | H76: 46 | I76: Fri | J76: =IF(A76<>"","No","") -> No | K76: =IF(A76<>"","No","") -> No | L76: =IFERROR(__xludf.DUMMYFUNCTION("""COMPUTED_VALUE"""),"Sunnyvale, CA") -> Sunnyvale, CA | M76: =IFERROR(__xludf.DUMMYFUNCTION("""COMPUTED_VALUE"""),"20 minutes ago") -> 20 minutes ago | N76: =IFERROR(__xludf.DUMMYFUNCTION("""COMPUTED_VALUE"""),20.0) -> 20 | P76: =IF(A76<>"","0","") -> 0 | R76: =IF(A76<>"","Review","") -> Review | Z76: 45975 | AA76: 2025-W46 | AB76: 2025-11 | AC76: =IF(Z76="","", Z76 - WEEKDAY(Z76, 2) + 1) -> 45971 | AD76: =IF(Z76="","", WEEKDAY(Z76, 2)) -> 5
A77: 45975.898 | B77: Data Engineer Manage My Job Request a Coach | C77: Aquent | D77: Austin, TX · Reposted 1 hour ago · 3 people clicked apply Promoted by hirer · Responses managed off LinkedIn | E77: https://www.linkedin.com/jobs/view/4336284362/ | F77: =IFERROR(__xludf.DUMMYFUNCTION("""COMPUTED_VALUE"""),45975.89800925926) -> 45975.898 | G77: Nov 2025 | H77: 46 | I77: Fri | J77: =IF(A77<>"","No","") -> No | K77: =IF(A77<>"","No","") -> No | L77: =IFERROR(__xludf.DUMMYFUNCTION("""COMPUTED_VALUE"""),"Austin, TX") -> Austin, TX | M77: =IFERROR(__xludf.DUMMYFUNCTION("""COMPUTED_VALUE"""),"Reposted 1 hour ago") -> Reposted 1 hour ago | N77: =IFERROR(__xludf.DUMMYFUNCTION("""COMPUTED_VALUE"""),1.0) -> 1 | P77: =IF(A77<>"","0","") -> 0 | R77: =IF(A77<>"","Review","") -> Review | Z77: 45975 | AA77: 2025-W46 | AB77: 2025-11 | AC77: =IF(Z77="","", Z77 - WEEKDAY(Z77, 2) + 1) -> 45971 | AD77: =IF(Z77="","", WEEKDAY(Z77, 2)) -> 5
A78: 45976.979 | B78: Data Engineer Manage My Job Request a Coach | C78: Tupl Inc. | D78: Dallas, TX · 1 day ago · Over 100 people clicked apply Promoted by hirer · Responses managed off LinkedIn | E78: https://www.linkedin.com/jobs/view/4335949863/ | F78: =IFERROR(__xludf.DUMMYFUNCTION("""COMPUTED_VALUE"""),45976.978854166664) -> 45976.979 | G78: Nov 2025 | H78: 46 | I78: Sat | J78: =IF(A78<>"","No","") -> No | K78: =IF(A78<>"","No","") -> No | L78: =IFERROR(__xludf.DUMMYFUNCTION("""COMPUTED_VALUE"""),"Dallas, TX") -> Dallas, TX | M78: =IFERROR(__xludf.DUMMYFUNCTION("""COMPUTED_VALUE"""),"1 day ago") -> 1 day ago | N78: =IFERROR(__xludf.DUMMYFUNCTION("""COMPUTED_VALUE"""),1.0) -> 1 | P78: =IF(A78<>"","0","") -> 0 | R78: =IF(A78<>"","Review","") -> Review | Z78: 45976 | AA78: 2025-W46 | AB78: 2025-11 | AC78: =IF(Z78="","", Z78 - WEEKDAY(Z78, 2) + 1) -> 45971 | AD78: =IF(Z78="","", WEEKDAY(Z78, 2)) -> 6
A79: 45976.996 | B79: Backend Engineer Manage My Job Request a Coach | C79: Bevel | D79: New York, NY · 1 week ago · Over 100 people clicked apply Responses managed off LinkedIn | E79: https://www.linkedin.com/jobs/view/4334860779/ | F79: =IFERROR(__xludf.DUMMYFUNCTION("""COMPUTED_VALUE"""),45976.99643518519) -> 45976.996 | G79: Nov 2025 | H79: 46 | I79: Sat | J79: =IF(A79<>"","No","") -> No | K79: =IF(A79<>"","No","") -> No | L79: =IFERROR(__xludf.DUMMYFUNCTION("""COMPUTED_VALUE"""),"New York, NY") -> New York, NY | M79: =IFERROR(__xludf.DUMMYFUNCTION("""COMPUTED_VALUE"""),"1 week ago") -> 1 week ago | N79: =IFERROR(__xludf.DUMMYFUNCTION("""COMPUTED_VALUE"""),1.0) -> 1 | P79: =IF(A79<>"","0","") -> 0 | R79: =IF(A79<>"","Review","") -> Review | Z79: 45976 | AA79: 2025-W46 | AB79: 2025-11 | AC79: =IF(Z79="","", Z79 - WEEKDAY(Z79, 2) + 1) -> 45971 | AD79: =IF(Z79="","", WEEKDAY(Z79, 2)) -> 6
A80: 45977.86 | B80: Software Engineer (Networking) Manage My Job Request a Coach | C80: ORDR | D80: Santa Clara, CA · 9 hours ago · 86 applicants Promoted by hirer · No response insights available yet | E80: https://www.linkedin.com/jobs/view/4322941297/ | F80: =IFERROR(__xludf.DUMMYFUNCTION("""COMPUTED_VALUE"""),45977.86009259259) -> 45977.86 | G80: Nov 2025 | H80: 47 | I80: Sun | J80: =IF(A80<>"","No","") -> No | K80: =IF(A80<>"","No","") -> No | L80: =IFERROR(__xludf.DUMMYFUNCTION("""COMPUTED_VALUE"""),"Santa Clara, CA") -> Santa Clara, CA | M80: =IFERROR(__xludf.DUMMYFUNCTION("""COMPUTED_VALUE"""),"9 hours ago") -> 9 hours ago | N80: =IFERROR(__xludf.DUMMYFUNCTION("""COMPUTED_VALUE"""),9.0) -> 9 | P80: =IF(A80<>"","0","") -> 0 | R80: =IF(A80<>"","Review","") -> Review | Z80: 45977 | AA80: 2025-W46 | AB80: 2025-11 | AC80: =IF(Z80="","", Z80 - WEEKDAY(Z80, 2) + 1) -> 45971 | AD80: =IF(Z80="","", WEEKDAY(Z80, 2)) -> 7
A81: 45977.86 | B81: New Grad | C81: Optiver | D81: Chicago | E81: https://optiver.com/working-at-optiver/career-opportunities/7986419002/?gh_jid=7986419002&gh_src=hk2so9u22us | F81: =IFERROR(__xludf.DUMMYFUNCTION("""COMPUTED_VALUE"""),45977.86009259259) -> 45977.86 | G81: Nov 2025 | H81: 47 | I81: Sun | J81: =IF(A81<>"","No","") -> No | K81: =IF(A81<>"","No","") -> No | L81: =IFERROR(__xludf.DUMMYFUNCTION("""COMPUTED_VALUE"""),"Chicago") -> Chicago | M81: =IFERROR(__xludf.DUMMYFUNCTION("""COMPUTED_VALUE"""),"") | N81: =IFERROR(__xludf.DUMMYFUNCTION("""COMPUTED_VALUE"""),"") | P81: =IF(A81<>"","0","") -> 0 | R81: =IF(A81<>"","Review","") -> Review | Z81: 45977 | AA81: 2025-W46 | AB81: 2025-11 | AC81: =IF(Z81="","", Z81 - WEEKDAY(Z81, 2) + 1) -> 45971 | AD81: =IF(Z81="","", WEEKDAY(Z81, 2)) -> 7
A82: 45978.441 | B82: Product Engineer | C82: Fusion Life Sciences Technologies LLC | D82: Illinois, United States · 10 minutes ago · 1 applicant Promoted by hirer · Company review time is typically 1 week | E82: https://www.linkedin.com/jobs/view/4336780888/ | F82: =IFERROR(__xludf.DUMMYFUNCTION("""COMPUTED_VALUE"""),45978.44121527778) -> 45978.441 | G82: Nov 2025 | H82: 47 | I82: Mon | J82: =IF(A82<>"","No","") -> No | K82: =IF(A82<>"","No","") -> No | L82: =IFERROR(__xludf.DUMMYFUNCTION("""COMPUTED_VALUE"""),"Illinois, United States") -> Illinois, United States | M82: =IFERROR(__xludf.DUMMYFUNCTION("""COMPUTED_VALUE"""),"10 minutes ago") -> 10 minutes ago | N82: =IFERROR(__xludf.DUMMYFUNCTION("""COMPUTED_VALUE"""),10.0) -> 10 | P82: =IF(A82<>"","0","") -> 0 | R82: =IF(A82<>"","Review","") -> Review | Z82: 45978 | AA82: 2025-W47 | AB82: 2025-11 | AC82: =IF(Z82="","", Z82 - WEEKDAY(Z82, 2) + 1) -> 45978 | AD82: =IF(Z82="","", WEEKDAY(Z82, 2)) -> 1
A83: 45978.441 | B83: AI Engineer Manage My Job Request a Coach | C83: Avesta Computer Services | D83: Fremont, CA · 22 minutes ago · 33 applicants Promoted by hirer · No response insights available yet | E83: https://www.linkedin.com/jobs/view/4340943315/ | F83: =IFERROR(__xludf.DUMMYFUNCTION("""COMPUTED_VALUE"""),45978.441400462965) -> 45978.441 | G83: Nov 2025 | H83: 47 | I83: Mon | J83: =IF(A83<>"","No","") -> No | K83: =IF(A83<>"","No","") -> No | L83: =IFERROR(__xludf.DUMMYFUNCTION("""COMPUTED_VALUE"""),"Fremont, CA") -> Fremont, CA | M83: =IFERROR(__xludf.DUMMYFUNCTION("""COMPUTED_VALUE"""),"22 minutes ago") -> 22 minutes ago | N83: =IFERROR(__xludf.DUMMYFUNCTION("""COMPUTED_VALUE"""),22.0) -> 22 | P83: =IF(A83<>"","0","") -> 0 | R83: =IF(A83<>"","Review","") -> Review | Z83: 45978 | AA83: 2025-W47 | AB83: 2025-11 | AC83: =IF(Z83="","", Z83 - WEEKDAY(Z83, 2) + 1) -> 45978 | AD83: =IF(Z83="","", WEEKDAY(Z83, 2)) -> 1
A84: 45978.448 | B84: Senior Engineer/Architect - Software Engineering | C84: Slalom | D84: Massachusetts, United States | E84: https://www.linkedin.com/jobs/view/4317102285/ | F84: =IFERROR(__xludf.DUMMYFUNCTION("""COMPUTED_VALUE"""),45978.44778935185) -> 45978.448 | G84: Nov 2025 | H84: 47 | I84: Mon | J84: =IF(A84<>"","No","") -> No | K84: =IF(A84<>"","No","") -> No | L84: =IFERROR(__xludf.DUMMYFUNCTION("""COMPUTED_VALUE"""),"Massachusetts, United States") -> Massachusetts, United States | M84: =IFERROR(__xludf.DUMMYFUNCTION("""COMPUTED_VALUE"""),"") | N84: =IFERROR(__xludf.DUMMYFUNCTION("""COMPUTED_VALUE"""),"") | P84: =IF(A84<>"","0","") -> 0 | R84: =IF(A84<>"","Review","") -> Review | Z84: 45978 | AA84: 2025-W47 | AB84: 2025-11 | AC84: =IF(Z84="","", Z84 - WEEKDAY(Z84, 2) + 1) -> 45978 | AD84: =IF(Z84="","", WEEKDAY(Z84, 2)) -> 1
A85: 45978.448 | B85: Software Engineer Manage My Job Request a Coach | C85: Epic | D85: State College, PA · Reposted 21 minutes ago · 94 people clicked apply Promoted by hirer · Responses managed off LinkedIn | E85: https://www.linkedin.com/jobs/view/3986116449/ | F85: =IFERROR(__xludf.DUMMYFUNCTION("""COMPUTED_VALUE"""),45978.448159722226) -> 45978.448 | G85: Nov 2025 | H85: 47 | I85: Mon | J85: =IF(A85<>"","No","") -> No | K85: =IF(A85<>"","No","") -> No | L85: =IFERROR(__xludf.DUMMYFUNCTION("""COMPUTED_VALUE"""),"State College, PA") -> State College, PA | M85: =IFERROR(__xludf.DUMMYFUNCTION("""COMPUTED_VALUE"""),"Reposted 21 minutes ago") -> Reposted 21 minutes ago | N85: =IFERROR(__xludf.DUMMYFUNCTION("""COMPUTED_VALUE"""),21.0) -> 21 | P85: =IF(A85<>"","0","") -> 0 | R85: =IF(A85<>"","Review","") -> Review | Z85: 45978 | AA85: 2025-W47 | AB85: 2025-11 | AC85: =IF(Z85="","", Z85 - WEEKDAY(Z85, 2) + 1) -> 45978 | AD85: =IF(Z85="","", WEEKDAY(Z85, 2)) -> 1
A86: 45978.458 | B86: Data Engineer Manage My Job Request a Coach | C86: Mastech Digital | D86: Jersey City, NJ · 33 minutes ago · 57 applicants Promoted by hirer · No response insights available yet | E86: https://www.linkedin.com/jobs/view/4341123256/ | F86: =IFERROR(__xludf.DUMMYFUNCTION("""COMPUTED_VALUE"""),45978.458333333336) -> 45978.458 | G86: Nov 2025 | H86: 47 | I86: Mon | J86: =IF(A86<>"","No","") -> No | K86: =IF(A86<>"","No","") -> No | L86: =IFERROR(__xludf.DUMMYFUNCTION("""COMPUTED_VALUE"""),"Jersey City, NJ") -> Jersey City, NJ | M86: =IFERROR(__xludf.DUMMYFUNCTION("""COMPUTED_VALUE"""),"33 minutes ago") -> 33 minutes ago | N86: =IFERROR(__xludf.DUMMYFUNCTION("""COMPUTED_VALUE"""),33.0) -> 33 | P86: =IF(A86<>"","0","") -> 0 | R86: =IF(A86<>"","Review","") -> Review | Z86: 45978 | AA86: 2025-W47 | AB86: 2025-11 | AC86: =IF(Z86="","", Z86 - WEEKDAY(Z86, 2) + 1) -> 45978 | AD86: =IF(Z86="","", WEEKDAY(Z86, 2)) -> 1
A87: 45978.46 | B87: Solutions Architect Manage My Job Request a Coach | C87: ACL Digital | D87: Atlanta, GA · Reposted 36 minutes ago · 61 applicants Promoted by hirer · Actively reviewing applicants | E87: https://www.linkedin.com/jobs/view/4320743044/ | F87: =IFERROR(__xludf.DUMMYFUNCTION("""COMPUTED_VALUE"""),45978.45960648148) -> 45978.46 | G87: Nov 2025 | H87: 47 | I87: Mon | J87: =IF(A87<>"","No","") -> No | K87: =IF(A87<>"","No","") -> No | L87: =IFERROR(__xludf.DUMMYFUNCTION("""COMPUTED_VALUE"""),"Atlanta, GA") -> Atlanta, GA | M87: =IFERROR(__xludf.DUMMYFUNCTION("""COMPUTED_VALUE"""),"Reposted 36 minutes ago") -> Reposted 36 minutes ago | N87: =IFERROR(__xludf.DUMMYFUNCTION("""COMPUTED_VALUE"""),36.0) -> 36 | P87: =IF(A87<>"","0","") -> 0 | R87: =IF(A87<>"","Review","") -> Review | Z87: 45978 | AA87: 2025-W47 | AB87: 2025-11 | AC87: =IF(Z87="","", Z87 - WEEKDAY(Z87, 2) + 1) -> 45978 | AD87: =IF(Z87="","", WEEKDAY(Z87, 2)) -> 1
A88: 45978.659 | B88: Software Engineer, Frontend - Canada POD Manage My Job Request a Coach | C88: Coinbase | D88: Canada · Reposted 6 hours ago · Over 100 applicants Promoted by hirer · Actively reviewing applicants | E88: https://www.linkedin.com/jobs/view/4310860245/ | F88: =IFERROR(__xludf.DUMMYFUNCTION("""COMPUTED_VALUE"""),45978.65857638889) -> 45978.659 | G88: Nov 2025 | H88: 47 | I88: Mon | J88: =IF(A88<>"","No","") -> No | K88: =IF(A88<>"","No","") -> No | L88: =IFERROR(__xludf.DUMMYFUNCTION("""COMPUTED_VALUE"""),"Canada") -> Canada | M88: =IFERROR(__xludf.DUMMYFUNCTION("""COMPUTED_VALUE"""),"Reposted 6 hours ago") -> Reposted 6 hours ago | N88: =IFERROR(__xludf.DUMMYFUNCTION("""COMPUTED_VALUE"""),6.0) -> 6 | P88: =IF(A88<>"","0","") -> 0 | R88: =IF(A88<>"","Review","") -> Review | Z88: 45978 | AA88: 2025-W47 | AB88: 2025-11 | AC88: =IF(Z88="","", Z88 - WEEKDAY(Z88, 2) + 1) -> 45978 | AD88: =IF(Z88="","", WEEKDAY(Z88, 2)) -> 1
A89: 45978.659 | B89: Software Engineer, Backend - Financial Hub Manage My Job Request a Coach | C89: Coinbase | D89: United States · 55 minutes ago · Over 100 people clicked apply Promoted by hirer · Responses managed off LinkedIn | E89: https://www.linkedin.com/jobs/view/4336602991/ | F89: =IFERROR(__xludf.DUMMYFUNCTION("""COMPUTED_VALUE"""),45978.65876157407) -> 45978.659 | G89: Nov 2025 | H89: 47 | I89: Mon | J89: =IF(A89<>"","No","") -> No | K89: =IF(A89<>"","No","") -> No | L89: =IFERROR(__xludf.DUMMYFUNCTION("""COMPUTED_VALUE"""),"United States") -> United States | M89: =IFERROR(__xludf.DUMMYFUNCTION("""COMPUTED_VALUE"""),"55 minutes ago") -> 55 minutes ago | N89: =IFERROR(__xludf.DUMMYFUNCTION("""COMPUTED_VALUE"""),55.0) -> 55 | P89: =IF(A89<>"","0","") -> 0 | R89: =IF(A89<>"","Review","") -> Review | Z89: 45978 | AA89: 2025-W47 | AB89: 2025-11 | AC89: =IF(Z89="","", Z89 - WEEKDAY(Z89, 2) + 1) -> 45978 | AD89: =IF(Z89="","", WEEKDAY(Z89, 2)) -> 1
A90: 45978.684 | B90: Conversational AI Engineer Manage My Job Request a Coach | C90: Automated Health Systems | D90: Pittsburgh, PA · 25 minutes ago · 28 applicants Promoted by hirer · No response insights available yet | E90: https://www.linkedin.com/jobs/view/4336713425/ | F90: =IFERROR(__xludf.DUMMYFUNCTION("""COMPUTED_VALUE"""),45978.68446759259) -> 45978.684 | G90: Nov 2025 | H90: 47 | I90: Mon | J90: =IF(A90<>"","No","") -> No | K90: =IF(A90<>"","No","") -> No | L90: =IFERROR(__xludf.DUMMYFUNCTION("""COMPUTED_VALUE"""),"Pittsburgh, PA") -> Pittsburgh, PA | M90: =IFERROR(__xludf.DUMMYFUNCTION("""COMPUTED_VALUE"""),"25 minutes ago") -> 25 minutes ago | N90: =IFERROR(__xludf.DUMMYFUNCTION("""COMPUTED_VALUE"""),25.0) -> 25 | P90: =IF(A90<>"","0","") -> 0 | R90: =IF(A90<>"","Review","") -> Review | Z90: 45978 | AA90: 2025-W47 | AB90: 2025-11 | AC90: =IF(Z90="","", Z90 - WEEKDAY(Z90, 2) + 1) -> 45978 | AD90: =IF(Z90="","", WEEKDAY(Z90, 2)) -> 1
A91: 45978.685 | B91: Quartz/Python Trading Developer Manage My Job Request a Coach | C91: Matlen Silver | D91: Jersey City, NJ · 4 minutes ago · 0 applicants Promoted by hirer · No response insights available yet | E91: https://www.linkedin.com/jobs/view/4341324918/ | F91: =IFERROR(__xludf.DUMMYFUNCTION("""COMPUTED_VALUE"""),45978.6846875) -> 45978.685 | G91: Nov 2025 | H91: 47 | I91: Mon | J91: =IF(A91<>"","No","") -> No | K91: =IF(A91<>"","No","") -> No | L91: =IFERROR(__xludf.DUMMYFUNCTION("""COMPUTED_VALUE"""),"Jersey City, NJ") -> Jersey City, NJ | M91: =IFERROR(__xludf.DUMMYFUNCTION("""COMPUTED_VALUE"""),"4 minutes ago") -> 4 minutes ago | N91: =IFERROR(__xludf.DUMMYFUNCTION("""COMPUTED_VALUE"""),4.0) -> 4 | P91: =IF(A91<>"","0","") -> 0 | R91: =IF(A91<>"","Review","") -> Review | Z91: 45978 | AA91: 2025-W47 | AB91: 2025-11 | AC91: =IF(Z91="","", Z91 - WEEKDAY(Z91, 2) + 1) -> 45978 | AD91: =IF(Z91="","", WEEKDAY(Z91, 2)) -> 1
A92: 45978.685 | B92: AI Compute System Engineer Manage My Job Request a Coach | C92: Analog Devices | D92: Boston, MA · 40 minutes ago · 3 people clicked apply Promoted by hirer · Responses managed off LinkedIn | E92: https://www.linkedin.com/jobs/view/4341364391/ | F92: =IFERROR(__xludf.DUMMYFUNCTION("""COMPUTED_VALUE"""),45978.68483796297) -> 45978.685 | G92: Nov 2025 | H92: 47 | I92: Mon | J92: =IF(A92<>"","No","") -> No | K92: =IF(A92<>"","No","") -> No | L92: =IFERROR(__xludf.DUMMYFUNCTION("""COMPUTED_VALUE"""),"Boston, MA") -> Boston, MA | M92: =IFERROR(__xludf.DUMMYFUNCTION("""COMPUTED_VALUE"""),"40 minutes ago") -> 40 minutes ago | N92: =IFERROR(__xludf.DUMMYFUNCTION("""COMPUTED_VALUE"""),40.0) -> 40 | P92: =IF(A92<>"","0","") -> 0 | R92: =IF(A92<>"","Review","") -> Review | Z92: 45978 | AA92: 2025-W47 | AB92: 2025-11 | AC92: =IF(Z92="","", Z92 - WEEKDAY(Z92, 2) + 1) -> 45978 | AD92: =IF(Z92="","", WEEKDAY(Z92, 2)) -> 1
A93: 45978.689 | B93: Software Engineer Manage My Job Request a Coach | C93: Doppel | D93: New York, United States · 1 hour ago · Over 100 applicants Promoted by hirer · No response insights available yet | E93: https://www.linkedin.com/jobs/view/4336673196/ | F93: =IFERROR(__xludf.DUMMYFUNCTION("""COMPUTED_VALUE"""),45978.68913194445) -> 45978.689 | G93: Nov 2025 | H93: 47 | I93: Mon | J93: =IF(A93<>"","No","") -> No | K93: =IF(A93<>"","No","") -> No | L93: =IFERROR(__xludf.DUMMYFUNCTION("""COMPUTED_VALUE"""),"New York, United States") -> New York, United States | M93: =IFERROR(__xludf.DUMMYFUNCTION("""COMPUTED_VALUE"""),"1 hour ago") -> 1 hour ago | N93: =IFERROR(__xludf.DUMMYFUNCTION("""COMPUTED_VALUE"""),1.0) -> 1 | P93: =IF(A93<>"","0","") -> 0 | R93: =IF(A93<>"","Review","") -> Review | Z93: 45978 | AA93: 2025-W47 | AB93: 2025-11 | AC93: =IF(Z93="","", Z93 - WEEKDAY(Z93, 2) + 1) -> 45978 | AD93: =IF(Z93="","", WEEKDAY(Z93, 2)) -> 1
A94: 45978.689 | B94: Applied AI Engineer | C94: San Francisco’s Emerging Technologies | D94: San Francisco | E94: https://lnkd.in/gk6VDneS | F94: =IFERROR(__xludf.DUMMYFUNCTION("""COMPUTED_VALUE"""),45978.68913194445) -> 45978.689 | G94: Nov 2025 | H94: 47 | I94: Mon | J94: =IF(A94<>"","No","") -> No | K94: =IF(A94<>"","No","") -> No | L94: =IFERROR(__xludf.DUMMYFUNCTION("""COMPUTED_VALUE"""),"San Francisco") -> San Francisco | M94: =IFERROR(__xludf.DUMMYFUNCTION("""COMPUTED_VALUE"""),"") | N94: =IFERROR(__xludf.DUMMYFUNCTION("""COMPUTED_VALUE"""),"") | P94: =IF(A94<>"","0","") -> 0 | R94: =IF(A94<>"","Review","") -> Review | Z94: 45978 | AA94: 2025-W47 | AB94: 2025-11 | AC94: =IF(Z94="","", Z94 - WEEKDAY(Z94, 2) + 1) -> 45978 | AD94: =IF(Z94="","", WEEKDAY(Z94, 2)) -> 1
A95: 45978.967 | B95: Data Scientist, United States - BCG X Manage My Job Request a Coach | C95: Boston Consulting Group (BCG) | D95: Boston, MA · 1 hour ago · 41 people clicked apply Promoted by hirer · Responses managed off LinkedIn | E95: https://www.linkedin.com/jobs/view/4323131657/ | F95: =IFERROR(__xludf.DUMMYFUNCTION("""COMPUTED_VALUE"""),45978.96738425926) -> 45978.967 | G95: Nov 2025 | H95: 47 | I95: Mon | J95: =IF(A95<>"","No","") -> No | K95: =IF(A95<>"","No","") -> No | L95: =IFERROR(__xludf.DUMMYFUNCTION("""COMPUTED_VALUE"""),"Boston, MA") -> Boston, MA | M95: =IFERROR(__xludf.DUMMYFUNCTION("""COMPUTED_VALUE"""),"1 hour ago") -> 1 hour ago | N95: =IFERROR(__xludf.DUMMYFUNCTION("""COMPUTED_VALUE"""),1.0) -> 1 | P95: =IF(A95<>"","0","") -> 0 | R95: =IF(A95<>"","Review","") -> Review | Z95: 45978 | AA95: 2025-W47 | AB95: 2025-11 | AC95: =IF(Z95="","", Z95 - WEEKDAY(Z95, 2) + 1) -> 45978 | AD95: =IF(Z95="","", WEEKDAY(Z95, 2)) -> 1
A96: 45979.026 | B96: Machine Learning Engineer - Rider Pricing Manage My Job Request a Coach | C96: Uber | D96: San Francisco, CA · 2 hours ago · 47 people clicked apply Responses managed off LinkedIn | E96: https://www.linkedin.com/jobs/view/4341185605/ | F96: =IFERROR(__xludf.DUMMYFUNCTION("""COMPUTED_VALUE"""),45979.025659722225) -> 45979.026 | G96: Nov 2025 | H96: 47 | I96: Tue | J96: =IF(A96<>"","No","") -> No | K96: =IF(A96<>"","No","") -> No | L96: =IFERROR(__xludf.DUMMYFUNCTION("""COMPUTED_VALUE"""),"San Francisco, CA") -> San Francisco, CA | M96: =IFERROR(__xludf.DUMMYFUNCTION("""COMPUTED_VALUE"""),"2 hours ago") -> 2 hours ago | N96: =IFERROR(__xludf.DUMMYFUNCTION("""COMPUTED_VALUE"""),2.0) -> 2 | P96: =IF(A96<>"","0","") -> 0 | R96: Review | Z96: 45979 | AA96: 2025-W47 | AB96: 2025-11 | AC96: =IF(Z96="","", Z96 - WEEKDAY(Z96, 2) + 1) -> 45978 | AD96: =IF(Z96="","", WEEKDAY(Z96, 2)) -> 2
A97: 45979.026 | B97: Developer - AI Assisted Manage My Job Request a Coach | C97: Frontier Airlines | D97: Denver, CO · 3 hours ago · 71 people clicked apply Responses managed off LinkedIn | E97: https://www.linkedin.com/jobs/view/4336645524/ | F97: =IFERROR(__xludf.DUMMYFUNCTION("""COMPUTED_VALUE"""),45979.02578703704) -> 45979.026 | G97: Nov 2025 | H97: 47 | I97: Tue | J97: =IF(A97<>"","No","") -> No | K97: =IF(A97<>"","No","") -> No | L97: =IFERROR(__xludf.DUMMYFUNCTION("""COMPUTED_VALUE"""),"Denver, CO") -> Denver, CO | M97: =IFERROR(__xludf.DUMMYFUNCTION("""COMPUTED_VALUE"""),"3 hours ago") -> 3 hours ago | N97: =IFERROR(__xludf.DUMMYFUNCTION("""COMPUTED_VALUE"""),3.0) -> 3 | P97: =IF(A97<>"","0","") -> 0 | R97: OA Done | S97: Done | Z97: 45979 | AA97: 2025-W47 | AB97: 2025-11 | AC97: =IF(Z97="","", Z97 - WEEKDAY(Z97, 2) + 1) -> 45978 | AD97: =IF(Z97="","", WEEKDAY(Z97, 2)) -> 2
A98: 45979.032 | B98: Software Engineer Data/AI/Intelligent Systems I (Full Time) – United States | C98: Cisco | D98: Boston, MA | E98: https://www.linkedin.com/jobs/view/4336575505/ | F98: =IFERROR(__xludf.DUMMYFUNCTION("""COMPUTED_VALUE"""),45979.031643518516) -> 45979.032 | G98: Nov 2025 | H98: 47 | I98: Tue | J98: =IF(A98<>"","No","") -> No | K98: =IF(A98<>"","No","") -> No | L98: =IFERROR(__xludf.DUMMYFUNCTION("""COMPUTED_VALUE"""),"Boston, MA") -> Boston, MA | M98: =IFERROR(__xludf.DUMMYFUNCTION("""COMPUTED_VALUE"""),"") | N98: =IFERROR(__xludf.DUMMYFUNCTION("""COMPUTED_VALUE"""),"") | P98: =IF(A98<>"","0","") -> 0 | R98: =IF(A98<>"","Review","") -> Review | Z98: 45979 | AA98: 2025-W47 | AB98: 2025-11 | AC98: =IF(Z98="","", Z98 - WEEKDAY(Z98, 2) + 1) -> 45978 | AD98: =IF(Z98="","", WEEKDAY(Z98, 2)) -> 2
A99: 45979.039 | B99: Data Engineer | C99: Protingent | D99: Santa Clara, CA · Reposted 5 hours ago · 67 applicants Promoted by hirer · No response insights available yet | E99: https://www.linkedin.com/jobs/view/4323130696/ | F99: =IFERROR(__xludf.DUMMYFUNCTION("""COMPUTED_VALUE"""),45979.039039351854) -> 45979.039 | G99: Nov 2025 | H99: 47 | I99: Tue | J99: =IF(A99<>"","No","") -> No | K99: =IF(A99<>"","No","") -> No | L99: =IFERROR(__xludf.DUMMYFUNCTION("""COMPUTED_VALUE"""),"Santa Clara, CA") -> Santa Clara, CA | M99: =IFERROR(__xludf.DUMMYFUNCTION("""COMPUTED_VALUE"""),"Reposted 5 hours ago") -> Reposted 5 hours ago | N99: =IFERROR(__xludf.DUMMYFUNCTION("""COMPUTED_VALUE"""),5.0) -> 5 | P99: =IF(A99<>"","0","") -> 0 | R99: =IF(A99<>"","Review","") -> Review | Z99: 45979 | AA99: 2025-W47 | AB99: 2025-11 | AC99: =IF(Z99="","", Z99 - WEEKDAY(Z99, 2) + 1) -> 45978 | AD99: =IF(Z99="","", WEEKDAY(Z99, 2)) -> 2
